Workbook
Name OLE_LINK1: 'Excercise - Al '!$P$59
Name OLE_LINK1: 'MSEL INFO ONLY'!$P$149

Sheet Excercise - Al 
A1: MSEL NUMBER | B1: DATE | C1: Time | D1: STATUS | E1: INJECT DTG | F1: SUBJECT | G1: INJECT MODE | H1: SEND FROM (Simulated) | I1: INJECTED BY | J1: SEND TO | K1: STORYLINE/THREAD | L1: ESF | M1: DESCRIPTION | N1: EXPECTED ACTION | O1: NOTES/REMARKS | P1: IMPLEMENTER (Actual Narrative) | Q1: BACKGROUND INFORMATION | R1: Inject Author
A2: 1 | D2: Omitted | E2: 40298.208 | F2: 31st CHEM BDE - Notifies select staff | G2: Not Injected | R2: Napier
A3: 2 | B3: 40299 | C3: 40299.167 | D3: Injected | E3: 40299.167 | F3: INFO | G3: Email | H3: Simcell - National Hurricane Center | I3: KEANE | J3: JOC, All | K3: Tropical Depression One Forms | L3: 5, 15 | M3: Tropical Depression One Forms | P3: On 01 May, 0400 HRS CDT, The National Hurricane Center issues Tropical Depression Advisory "One". Current Location 14.5 N 74.1 W Max Sustained Wind 30mph | R3: Keane
A4: 3 | D4: Omitted | E4: 40299.208 | F4: 31st CHEM BDE - Telecon with unit CDRs and issue verbal WARNO | G4: Not Injected | R4: Napier
A5: 4 | D5: Omitted | E5: 40299.208 | F5: 31st CHEM BDE - Test alert roster of key personnel and for the 1165th and 690th | G5: Not Injected | R5: Napier
A6: 5 | B6: 40299 | C6: 40299.417 | D6: Injected | E6: 40299.417 | F6: INFO | G6: Email | H6: Simcell - National Hurricane Center | I6: KEANE | J6: JOC, All | K6: Tropical Storm Al Update 2 | L6: 5, 15 | M6: Tropical Storm Al Update 2 | P6: ...FIRST TROPICAL STORM OF THE SEASON...AL NEARS THE COAST OF NICARAGUA... SUMMARY OF 1100 AM EDT...1500 UTC...INFORMATION ----------------------------------------------- LOCATION...14.9N 74.9W ABOUT 220 MILES...354 KM...SOUTH SOUTHEAST OF KINGSTON JAMAICA ABOUT 280 MILES...450 KM...NORTH OF BARRANQUILLA COLUMBIA ABOUT 510 MILES...820 KM...NORTHEAST OF PANAMA CITY PANAMA MAXIMUM SUSTAINED WINDS...45 MPH...39 KM/HR PRESENT MOVEMENT...WNW OR 276 DEGREES AT 15 MPH...24 KM/HR MINIMUM CENTRAL PRESSURE...999 MB...29.5 INCHES | R6: Keane
A7: 6 | B7: 40299 | C7: 40299.667 | D7: Injected | E7: 40299.667 | F7: INFO | G7: Email | H7: Simcell - National Hurricane Center | I7: KEANE | J7: JOC, All | K7: Tropical Storm Al Update 3 | L7: 5, 15 | M7: Tropical Storm Al Update 3 | P7: ...TROPICAL STORM AL STRENGTHENS AS IT NEARS THE COAST OF NICARAGUA... SUMMARY OF 1700 AM EDT...2100 UTC...INFORMATION ----------------------------------------------- LOCATION...15.30 N 76.20 W ABOUT 188 MILES...303 KM...167 DEGREES...SOUTH-SOUTHEAST OF KINGSTON JAMAICA ABOUT 312 MILES...502 KM...343 DEGREES...NORTH-NORTHWEST OF BARRANQUILLA COLUMBIA MAXIMUM SUSTAINED WINDS...60 MPH...99 KM/HR PRESENT MOVEMENT...WESTERLY OR 275 DEGREES AT 10 MPH...16 KM/HR MINIMUM CENTRAL PRESSURE...997 MB...29.44 INCHES | R7: Keane
A8: 7 | B8: 40299 | C8: 40299.917 | D8: Injected | E8: 40299.917 | F8: INFO | G8: Email | H8: Simcell - National Hurricane Center | I8: KEANE | J8: JOC, All | K8: Tropical Storm Al Update 4 | L8: 5, 15 | M8: Tropical Storm Al Update 4 | P8: ...AL BECOMES A HURRICANE AS IT NEARS THE NORTH COAST OF NICARAGUA... SUMMARY OF 1100 PM EDT...0300 UTC...INFORMATION ----------------------------------------------- LOCATION...15.50 N 77.10 W ABOUT 172 MILES...277 KM...SOUTH SOUTHEAST OF KINGSTON JAMAICA ABOUT 366 MILES...589 KM...NORTH-NORTHWEST OF CARTAGENA COLUMBIA MAXIMUM SUSTAINED WINDS...85 MPH...137 KM/HR PRESENT MOVEMENT...WNW OR 284 DEGREES AT 12 MPH...19 KM/HR MINIMUM CENTRAL PRESSURE...980 MB...28.94 INCHES | R8: Keane
A9: 8 | B9: 40300 | C9: 40300.167 | D9: Injected | E9: 40300.167 | F9: INFO | G9: Email | H9: Simcell - National Hurricane Center | I9: KEANE | J9: JOC, All | K9: Tropical Storm Al Update 4 | L9: 5, 15 | M9: Tropical Storm Al Update 4 | P9: ...AL REMAINS A CAT 1 HURRICANE MOVING EAST TO WEST...SOUTH OF JAMAICA...GAINING STRENGTH... SUMMARY OF 0500 AM EDT...0900 UTC...INFORMATION ----------------------------------------------- LOCATION...15.90 N 78.10 W ABOUT 159 MILES... 255 KM... SOUTH NEGRIL JAMAICA ABOUT 317 MILES... 510 KM... SOUTHEAST OF GEORGE TOWN CAYMAN ISLANDS ABOUT 375 MILES... 604 KM... EAST-NORTHEAST OF PUERTO CABEZAS NICARAGUA MAXIMUM SUSTAINED WINDS...85 MPH...137 KM/HR PRESENT MOVEMENT...WNW OR 282 DEGREES AT 12 MPH...19 KM/HR MINIMUM CENTRAL PRESSURE...979 MB...28.91 INCHES | R9: Keane
A10: 9 | B10: 40300.208 | C10: 40300.208 | D10: Injected | E10: 40300.208 | F10: INFO | K10: Tropical Storm Al Update 5 | M10: Tropical Storm Al Update 5 | R10: Jenne
A11: 10 | B11: 40300 | C11: 40300.417 | D11: Injected | E11: 40300.417 | F11: INFO | G11: Email | H11: Simcell - National Hurricane Center | I11: KEANE | J11: JOC, All | K11: Tropical Storm Al Update 6 | L11: 5, 15 | M11: Tropical Storm Al Update 6 | P11: ... HURRICANE AL TRACKS TOWARD THE YUCATAN... SUMMARY OF 1100 AM EDT...0900 UTC...INFORMATION ----------------------------------------------- LOCATION...16.3N 79.0W ABOUT 257 MILES... 321 KM...SOUTH SOUTHEAST OF GEORGE TOWN CAYMAN ISLANDS ABOUT 137 MILES... 222 KM...SOUTH OF NEGRIL JAMAICA MAXIMUM SUSTAINED WINDS...85 MPH...137 KM/HR PRESENT MOVEMENT...WNW OR 284 DEGREES AT 12 MPH...19 KM/HR MINIMUM CENTRAL PRESSURE...977 MB...28.85 INCHES | R11: Keane
A12: 11 | B12: 40300 | C12: 0.5 | D12: Injected | E12: 40300.5 | F12: RFI | G12: Email | H12: Each Task Force | I12: TF S2 | J12: JOC, J2 | M12: Weather Update/Storm Track | N12: J2 Provides latest Weather and Storm Track to the TFs | P12: Weather RFI from Task Force to J2 | R12: Houlton
A13: 12 | B13: 40300 | C13: 40300.667 | D13: Injected | E13: 40300.667 | F13: INFO | G13: Email | H13: Simcell - National Hurricane Center | I13: KEANE | J13: JOC, All | K13: Tropical Storm Al Update 7 | L13: 5, 15 | M13: Tropical Storm Al Update 7 | P13: ... HURRICANE AL TRACKS TOWARD THE YUCATAN...AS A CATEGORY TWO HURRICANE... SUMMARY OF 0500 AM EDT...0900 UTC...INFORMATION ----------------------------------------------- LOCATION...16.7N 80.0W ABOUT 199 MILES... 321 KM...SOUTH SOUTHEAST OF GEORGE TOWN CAYMAN ISLANDS ABOUT 150 MILES... 241 KM...NEGRIL JAMAICA MAXIMUM SUSTAINED WINDS...105 MPH...169 KM/HR PRESENT MOVEMENT...WNW OR 292 DEGREES AT 12 MPH...19 KM/HR MINIMUM CENTRAL PRESSURE...968 MB...28.59 INCHES | R13: Keane
A14: 13 | B14: 40300 | C14: 40300.917 | D14: Injected | E14: 40300.917 | F14: INFO | G14: Email | H14: Simcell - National Hurricane Center | I14: KEANE | J14: JOC, All | K14: Tropical Storm Al Update 8 | L14: 5, 15 | M14: Tropical Storm Al Update 8 | P14: ... HURRICANE AL GAINS MOMENTUM AS A CATEGORY TWO HURRICANE... SUMMARY OF 2300 PM EDT...0300 UTC...INFORMATION ----------------------------------------------- LOCATION...17.1N 80.9W ABOUT 184 MILES...296 KM...WEST-SOUTHWEST NEGRIL JAMAICA ABOUT 154 MILES...249 KM...SOUTH-SOUTHEAST OF GEORGE TOWN CAYMAN ISLANDS MAXIMUM SUSTAINED WINDS...105 MPH...169 KM/HR PRESENT MOVEMENT...WNW OR 292 DEGREES AT 15 MPH...24 KM/HR MINIMUM CENTRAL PRESSURE...963 MB...28.44 INCHES | R14: Keane
A15: 14 | B15: 40301 | C15: 40301.167 | D15: Injected | E15: 40301.167 | F15: INFO | G15: Email | H15: Simcell - National Hurricane Center | I15: KEANE | J15: JOC, All | K15: Tropical Storm Al Update 9 | L15: 5, 15 | M15: Tropical Storm Al Update 9 | P15: ... HURRICANE AL CONTINUES ON A TRACK TOWARD COZUMEL... SUMMARY OF 0500 AM EDT...0900 UTC...INFORMATION ----------------------------------------------- LOCATION...17.7N 82.1W ABOUT 250 MILES...401 KM...WEST-SOUTHWEST NEGRIL JAMAICA ABOUT 154 MILES...249 KM...SOUTH-SOUTHEAST OF GEORGE TOWN CAYMAN ISLANDS MAXIMUM SUSTAINED WINDS...105 MPH...169 KM/HR PRESENT MOVEMENT...WNW OR 294 DEGREES AT 14 MPH...23 KM/HR MINIMUM CENTRAL PRESSURE...960 MB...28.35 INCHES | R15: Keane
A16: 15 | D16: Omitted | E16: 40301.208 | F16: 31st CHEM BDE - Stands up the CAC and begins tracking storm | G16: Not Injected | R16: Napier
A17: 16 | D17: Omitted | E17: 40301.208 | F17: 31st CHEM BDE - Alert 1165th & 690th O/O Activate | G17: Not Injected | R17: Napier
A18: 17 | B18: 40301 | C18: 40301.292 | D18: Injected | E18: 40301.292 | F18: LNO to SEOC | G18: EMITS | H18: SEOC LNO | I18: SEOC LNO | J18: JOC | M18: NG LNO's to State EOC by 0700 4 May 10 | P18: NG LNO's to State EOC by 0700 4 May 10 | R18: Keane
A19: 18 | B19: 40301.312 | C19: 40301.312 | D19: Injected | E19: 40301.313 | F19: RFI - Holman Prison | G19: Phone Call | H19: JTF-S White Cell (subordinnate commander) | I19: TOMBERLIN | J19: 226 MEB | K19: Holman Prison Blues | M19: Company commander requests guidance on soldier | O19: Inject called in on schedule. Monitoring of JOC message traffic indicates that information apparently did not make it outside of 226 MEB. | P19: Company commander has a soldier who is a prison guard at Holman Prison. Soldier states that he has been directed to remain at prison and not to report to Guard. Indicates rumors of potential inmate takeover and mass escape during hurricane. Soldier/guard states that inmates are apparently planning a takeover while hurricane is in progress, followed by mass escape. There are indications that they may receive external support by an affilated gang. Soldier/guard states that prison officials are discussing requesting security assistance from Guard. | R19: Jenne
A20: 19 | D20: Injected | E20: 40301.314 | F20: MISSION | G20: EMITS | H20: AEMA ESF 5 | I20: SEOC LNO | J20: JOC | L20: 5 | M20: Provide meteorological services to SEOC (AL) | P20: Provide meteorological services to SEOC (AL) | R20: Keane
A21: 20 | D21: Injected | E21: 40301.333 | F21: AEMA Contacts JOC | G21: Phone | H21: AEMA | I21: ALAN PETTY | J21: AL J3 | M21: AEMA Director contacts AL TAG/J3 to discuss hurricane response planning/operations. | P21: AEMA Director contacts AL TAG/J3 to discuss hurricane response planning/operations. AEMA Director states that they are making preliminary plans for possible Alex response operations. Suggests issuing warning orders to MACOMs for potential in-state response operations. | R21: Keane
A22: 21 | B22: 40301 | C22: 0.33333333 | D22: Injected | E22: 40301.335 | F22: MISSION - SASO | G22: Email | H22: simcell-SEOC | I22: SEOC LNO | J22: J35 | K22: SASO | M22: SASO Request | N22: EOC contacts 122CSG | P22: Email Emits message' AEMA SEOC Request ALNG Provide SASO to MAFB | R22: Messer
A23: 22 | B23: 40301 | C23: 0.33333333 | D23: Injected | E23: 40301.335 | F23: MISSION - SEOC LOG CELL | G23: Email | H23: simcell-SEOC | I23: SEOC LNO | J23: J35 | K23: SEOC Log Cell | M23: SEOC Log Cell Request | N23: EOC contacts 122CSG | P23: Email Emits message' AEMA SEOC Request ALNG Provide SEOC Log Cell to Clanton Al. | R23: Messer
A24: 23 | B24: 40301 | C24: 0.35416667 | D24: Deferred | E24: 40301.354 | F24: INFO | G24: Phone | H24: simcell-citizen | I24: HOWARD | J24: Message Center | K24: MVC/ Fatality | M24: Report of Accident | N24: EOC RFIs MACOMS regarding report of accident/vehicles on road | P24: Citizen: I am a retired ARNG member and I just say one of your Humvee's run a stop sign and hit a mini van, and flipped it and it ran off the road. I didn't see anyone get out of either vehicle. I have called 911, just thought you guys wanted to know. | R24: Messer
A25: 24 | D25: Injected | E25: 40301.376 | F25: INFO | G25: Email | H25: JIEE | I25: KAHL | J25: JOC | K25: Set NGB Conference call up on DCO | R25: Kahl
A26: 25 | B26: 40301 | C26: 0.375 | D26: Injected | E26: 40301.376 | F26: INFO | G26: Phone | H26: simcell_LNO | I26: SEOC LNO | J26: J35 | K26: Contra Flow | M26: Informal message from LNO | N26: WARNO to 62nd Troop Command | P26: I just heard that the Governor is probably going to order contra flow on I 65 sometimes tomorrow morning. I will let you know more as I hear it. | R26: Messer
A27: 26 | D27: Injected | E27: 40301.377 | F27: INFO | G27: Email | H27: NGB | I27: KAHL | J27: JOC | K27: Set up event and Share with NGB | R27: Kahl
A28: 27 | D28: Injected | E28: 40301.378 | F28: RFI | G28: JIEE | H28: JIEE | I28: KAHL | J28: JOC | K28: Does the JOC need a JET or PARRT | M28: Request for JET | R28: Kahl
A29: 28 | B29: 40301 | D29: Injected | E29: 40301.378 | F29: INFO | I29: SEOC LNO | M29: The State Emergency Response Team (SERT) is recalled to the State Emergency Operations Center (SEOC (AL)) and activated at Level 1 effective 0900 3 May 2010. | P29: The State Emergency Response Team (SERT) is recalled to the State Emergency Operations Center (SEOC (AL)) and activated at Level 1 effective 0900 3 May 2010. | R29: Keane
A30: 29 | B30: 40301 | C30: 40301.375 | D30: Injected | E30: 40301.379 | F30: MISSION | G30: Email | H30: USPFO, S&S | I30: DENNIS | J30: JOC J4 | M30: USPFO Warehouse to push 20 pallets of MREs and 20 pallets of bottled water to Ft McClellan, AL (pre-positioning for soldier support). | P30: USPFO Warehouse to push 20 pallets of MREs and 20 pallets of bottled water to Ft McClellan, AL (pre-positioning for soldier support). | Q30: USPFO Warehouse SOP, SA only | R30: Keane
A31: 30 | B31: 40301 | D31: Injected | E31: 40301.381 | F31: INFO - Evacuation | I31: SEOC LNO | M31: AEMA recommends voluntary evacuation of Baldwin and Mobile counties. | P31: AEMA recommends voluntary evacuation of Baldwin and Mobile counties. Voluntary evacuations recommended for citizens living in mobile homes for the following counties: Washington, Clarke, Monroe, Conecuh, Escambia, Covington, Geneva, and Houston. | R31: Keane
A32: 31 | B32: 40301 | D32: Injected | E32: 40301.381 | F32: INFO | I32: KEANE | M32: JFHQ activates JTF-South (FTUS) Primary Staff (LNO's)and local units for possible support | P32: JFHQ activates JTF-South (FTUS) Primary Staff (LNO's)and local units for possible support | R32: Keane
A33: 32 | D33: Injected | E33: 40301.385 | F33: INFO | G33: Email | H33: MED DET | I33: BENTON | J33: SPS MED & J1 | K33: 1 Soldier found HIV positive in the 226th MEB after a periodic health assessment (PHA) performed by the medical detachment, from 10-11 Apr 10 SRP in Mobile. | M33: 1 Soldier found HIV positive in the 226th MEB after a periodic health assessment (PHA) performed by the medical detachment, from 10-11 Apr 10 SRP in Mobile. | P33: 1 Soldier found HIV positive in the 226th MEB after a periodic health assessment (PHA) performed by the medical detachment, from 10-11 Apr 10 SRP in Mobile. | R33: Benton
A34: 33 | D34: Injected | E34: 40301.385 | I34: P. MCDONALD | J34: JOC MSG CTR | K34: Army National Guard CAT requests Alabama review resources available IOT support FL with 1X Med Trk Co and 1X DS/GS Maint Co. | O34: At 0939 hours LTC Small , ARNG CAT, contacted MAJ Davis @ 334.273.3547 after several attempts to other numbers provided by SGT Vice. He is to advise. At 1114 hours, MAJ Davis advises TAG-AL requests a 48 hour hold before approving the EMAC request. | P34: Army National Guard CAT requests Alabama review resources available IOT support FL with 1X Med Trk Co and 1X DS/GS Maint Co. | R34: McDonald
A35: 34 | D35: Injected | E35: 40301.386 | F35: INFO | G35: Telephone Call | H35: STATE SURGEON | I35: BENTON | J35: SPS MED | K35: All JTFs must perform a medical readiness screening of the potential personnel being considered for DSCA support mission to ensure that they have a current PHA, Dental Exam, Routine Adult Immunizations (to include H1N1) and have no outstanding noon-deployable medical conditions. Submit status report back to SPS.MED NLT 1200 4 May 10. | M35: All JTFs must perform a medical readiness screening of the potential personnel being considered for DSCA support mission to ensure that they have a current PHA, Dental Exam, Routine Adult Immunizations (to include H1N1) and have no outstanding noon-deployable medical conditions. Submit status report back to SPS.MED NLT 1200 4 May 10. | P35: All JTFs must perform a medical readiness screening of the potential personnel being considered for DSCA support mission to ensure that they have a current PHA, Dental Exam, Routine Adult Immunizations (to include H1N1) and have no outstanding noon-deployable medical conditions. Submit status report back to SPS.MED NLT 1200 4 May 10. | R35: Benton
A36: 35 | B36: 40301 | D36: Injected | E36: 40301.387 | F36: INFO | I36: SEOC LNO | M36: TF South gets notification of pending activation | P36: TF South gets notification of pending activation | R36: Keane
A37: 36 | D37: Injected | E37: 40301.389 | I37: P. MCDONALD | K37: Army National Guard CAT requests Alabama review resources available IOT support TX with 1x Light/Medium Truck Company and 1x POL Co. | O37: At 0923 hours LTC Small, ARNG CAT, contacted MSG Woodall @ 334.213.7748 and he took message and would have someone return our call. At 1007 hours called MSG Woodall and advised no one had called. Left another message. At 1114 hours MAJ Davis, AL JOC returned call and received request. Will advise. At 1715 hours, MAJ Davis advises TAG will concur with request but requests a 48 hours delay for the EMAC request. | P37: Army National Guard CAT requests Alabama review resources available IOT support TX with 1x Light/Medium Truck Company and 1x POL Co. | R37: McDonald
A38: 37 | B38: 40301 | D38: Injected | E38: 40301.39 | F38: INFO | I38: SEOC LNO | M38: FEMA Region JFO ERT-A will deploy to AEMA on 4 May about 1200, FEMA Region 9 DCO will serve as JFO-AL DCO | P38: FEMA Region JFO ERT-A will deploy to AEMA on 4 May about 1200, FEMA Region 9 DCO will serve as JFO-AL DCO | R38: Keane
A39: 38 | B39: 40301 | D39: Injected | E39: 40301.39 | F39: MISSION | I39: SEOC LNO | M39: Deploy SERT (AL) LNOs to Mobile and Baldwin counties NLT 4 May 1800. | P39: Deploy SERT (AL)LNOs to Mobile and Baldwin counties NLT 4 May 1800. | R39: Keane
A40: 39 | D40: Omitted | E40: 40301.392 | K40: Army National Guard CAT requests Alabama review resources available IOT support Tx and LA with unfilled EMAC Requests. | P40: Army National Guard CAT requests Alabama review resources available IOT support Tx and LA with unfilled EMAC Requests.
A41: 40 | B41: 40301 | D41: Injected | E41: 40301.395 | F41: INFO | I41: KEANE | M41: AEMA Teleconference | P41: AEMA Teleconference | R41: Keane
A42: 41 | B42: 40301 | C42: 40301.375 | D42: Injected | E42: 40301.396 | F42: MISSION | G42: Email | H42: USPFO, S&S | I42: SEOC LNO | J42: JOC J4 | M42: USPFO Warehouse to push 20 pallets of MREs and 20 pallets of bottled water to Ft Whiting, Mobile, AL (pre-positioning for soldier support). | P42: USPFO Warehouse to push 20 pallets of MREs and 20 pallets of bottled water to Ft Whiting, Mobile, AL (pre-positioning for soldier support). | Q42: USPFO Warehouse SOP, SA only | R42: Keane
A43: 42 | B43: 40301 | C43: 40301.382 | D43: Injected | E43: 40301.406 | F43: RFI | G43: JIEE or Email | H43: ARNG CAT | I43: KAHL | J43: JOC | K43: EMAC | M43: Army National Guard CAT requests Alabama review resources available, specifically UH 60/CH 47 BN and BDE level multipurpose purpose task forces. | P43: Army National Guard CAT requests Alabama review resources available, specifically UH 60/CH 47 BN and BDE level multipurpose purpose task forces. | R43: Keane
A44: 43 | B44: 40301 | C44: 0.41666667 | D44: Deferred | E44: 40301.417 | F44: INFO | G44: Email | H44: simcell-SEOC | I44: SEOC LNO | J44: MSG CTR/TAG | M44: The Governor of Alabama has issued a declaration of emergency for Mobile, Baldwin and surrounding counties. | N44: MSG CTR informs TAG/Sr. Staff/JOC | P44: The Governor of Alabama has issued a declaration of emergency for Mobile, Baldwin and surrounding counties. | R44: Messer
A45: 44 | D45: Omitted | E45: 40301.417 | F45: 31st CHEM BDE - Dispatch LNO to Montgomery | G45: Not Injected | R45: Napier
A46: 45 | B46: 40301 | C46: 40301.417 | D46: Injected | E46: 40301.417 | F46: INFO | G46: Email | H46: Simcell - National Hurricane Center | I46: KEANE | J46: JOC, All | K46: Tropical Storm Al Update 10 | L46: 5, 15 | M46: Tropical Storm Al Update 10 | P46: ... HURRICANE AL MOVING NORTHWESTWARD...APPROACHING THE YUCATAN PENINSULA TOMORROW... SUMMARY OF 1100 AM EDT...1500 UTC...INFORMATION ----------------------------------------------- LOCATION...18.3N 83.1W ABOUT 129 MILES...208 KM...SOUTHWEST OF GEORGE TOWN CAYMAN ISLANDS ABOUT 290 MILES...466 KM...SOUTHEAST OF COZUMEL MEXICO ABOUT 339 MILES...545 KM...EAST-NORTHEAST OF BELIZE CITY BELIZE MAXIMUM SUSTAINED WINDS...120 MPH...193 KM/HR PRESENT MOVEMENT...WNW OR 303 DEGREES AT 14 MPH...23 KM/HR MINIMUM CENTRAL PRESSURE...956 MB...28.23 INCHES | R46: Keane
A47: 46 | B47: 40301 | D47: Injected | E47: 40301.438 | F47: RFI | G47: Phone | I47: SEOC LNO/P MCDONALD | J47: JOC-AVN | K47: EMAC | M47: Mississippi Issues EMAC Request for Aviation support, 3x UH60's for SAR | O47: At 1107 hours, MAJ Johns, MS-JOC- Battle Capt, contacted CW5 Fontenot, AVN, he said to send EMAC request ALNG can support 3 UH60 out of Mobile because they are having to relocate due to impeding storm. | P47: Mississippi Issues EMAC Request for Aviation support, 3x UH60's for SAR | R47: McDonald
A48: 47 | D48: Injected | E48: 40301.448 | F48: MISSION | G48: Email | I48: TOMBERLIN | M48: Request 900 MREs, 100 cots, and 100 blankets to be prepositioned at Fort Whiting, Mobile AL. | P48: Request 900 MREs, 100 cots, and 100 blankets to be preposition at Fort Whiting, Mobile AL. | R48: Therman
A49: 48 | B49: 40301 | D49: Ready to Inject | E49: 40301.458 | F49: RFI | I49: SEOC LNO | K49: EMAC | M49: Army National Guard CAT requests Alabama review resources available IOT support MSNG 3X UH60. | P49: Army National Guard CAT requests Alabama review resources available IOT support MSNG 3X UH60. | R49: Keane
A50: 49 | B50: 40301 | D50: Ready to Inject | E50: 40301.479 | F50: MISSION - BPT | I50: SEOC LNO | M50: BPT establish LSA | P50: BPT establish ONE LSA Brookley Field, Mobile, requires 20 PAX, 24hrs operations duration of support TBD. | R50: Keane
A51: 50 | B51: 40301 | D51: Ready to Inject | E51: 40301.499 | F51: MISSION - BPT | I51: SEOC LNO | M51: BPT establish and staff 15 PODs at Mobile and Baldwin counties | P51: BPT establish and staff 15 PODs at Mobile and Baldwin counties | R51: Keane
A52: 51 | B52: 40301 | C52: 0.5 | D52: Deleted | E52: 40301.5 | F52: RFI | G52: Email | H52: Each Task Force | I52: TF S2 | J52: JOC, J2 | M52: Weather Update/Storm Track | N52: J2 Provides latest Weather and Storm Track to the TFs | P52: Weather RFI from Task Force to J2 | R52: Houlton
A53: 52 | B53: 40301 | D53: Ready to Inject | E53: 40301.521 | F53: MISSION | I53: SEOC LNO | M53: Provide support to SERT (AL)LOG Chief in SEOC (AL) | P53: Provide support to SERT (AL)LOG Chief in SEOC (AL) | R53: Keane
A54: 53 | B54: 40301 | D54: Ready to Inject | E54: 40301.542 | F54: MISSION - BPT | I54: SEOC LNO | M54: Stage & BPT deploy 2 SAR teams to Mobile and Baldwin County EOC locations. | P54: Stage & BPT deploy 2 SAR teams consisting of 4ea 5tons 16 PAX to Mobile and Baldwin County EOC locations. POC will be Mr. Evens and Mr Raines | R54: Keane
A55: 54 | D55: Injected | E55: 40301.542 | F55: RFI | G55: Email | I55: HICKS | K55: CHAPLAIN & UMT ACTIIVITIES | N55: Deny request & cover with chaplain from another unit | P55: A Battalion commander reports his unit chaplain cannot be contacted. As a replacement he wants to bring with the unit his civilian pastor to do the chaplain work | R55: Hicks
A56: 55 | B56: 40301 | D56: Injected | E56: 40301.583 | F56: MISSION | I56: SEOC LNO | L56: 9 | M56: Provide SAR Planner to SEOC (AL) ESF 9 | P56: Provide SAR Planner to SEOC (AL) ESF 9 | R56: Keane
A57: 56 | B57: 40301 | D57: Injected | E57: 40301.604 | F57: MISSION - BPT | I57: SEOC LNO | M57: BPT support Aviation assets to assist with SAR | P57: BPT support Aviation assets to assist with SAR | R57: Keane
A58: 57 | B58: 40301 | D58: Injected | E58: 40301.625 | F58: MISSION - BPT | I58: SEOC LNO | M58: BPT to provide airlift of Gov and his key staff for aerial assessment on or about 6 May 10 | P58: BPT to provide airlift of Gov and his key staff for aerial assessment on or about 6 May 10 | R58: Keane
A59: 58 | D59: Injected | E59: 40301.625 | K59: Due to the impending threat of Hurricane Al the Governor's of Texas, LA, MS has ordered a state of emergency for all of the respective Coastal areas. Officials ordered a mandatory evacuation of visitors and special needs clients beginning at 9 a.m. Tuesday, 4 May. A phased evacuation of all residents begins Tuesday, May 4, 2010 at 8 a.m. | P59: Due to the impending threat of Hurricane Al the Governor's of Texas, LA, MS has ordered a state of emergency for all of the respective Coastal areas. Officials ordered a mandatory evacuation of visitors and special needs clients beginning at 9 a.m. Tuesday, 4 May. A phased evacuation of all residents begins Tuesday, May 4, 2010 at 8 a.m.
A60: 59 | B60: 40301 | D60: Injected | E60: 40301.646 | F60: MISSION - BPT | I60: SEOC LNO | M60: BPT provide Comms to affected areas EOCs | P60: BPT provide Comms to affected areas EOCs | R60: Keane
A61: 60 | B61: 40301 | D61: Injected | E61: 40301.656 | F61: MISSION - BPT | I61: SEOC LNO | M61: BPT to provide 3000 Soldiers for security operations in South and Central Alabama | P61: BPT to provide 3000 Soldiers for security operations in South and Central Alabama; locations TBD. Request units be self sustaining. | R61: Keane
A62: 61 | B62: 40301 | C62: 40301.667 | D62: Injected | E62: 40301.667 | F62: INFO | G62: Email | H62: Simcell - National Hurricane Center | I62: KEANE | J62: JOC, All | K62: Tropical Storm Al Update 11 | L62: 5, 15 | M62: Tropical Storm Al Update 11 | P62: ... HURRICANE AL MOVING NORTHWESTWARD...APPROACHING THE YUCATAN PENINSULA TOMORROW... SUMMARY OF 1700 AM EDT...2100 UTC...INFORMATION ----------------------------------------------- LOCATION...19.0N 84.1W ABOUT 179 MILES...288 KM...SOUTHWEST OF GEORGE TOWN CAYMAN ISLANDS ABOUT 229 MILES...367 KM...SOUTHEAST OF COZUMEL MEXICO ABOUT 287 MILES...463 KM...EAST-NORTHEAST OF BELIZE CITY BELIZE MAXIMUM SUSTAINED WINDS...120 MPH...193 KM/HR PRESENT MOVEMENT...WNW OR 307 DEGREES AT 15 MPH...24 KM/HR MINIMUM CENTRAL PRESSURE...953 MB...28.14 INCHES | R62: Keane
A63: 62 | B63: 40301 | D63: Injected | E63: 40301.688 | I63: DENNIS | M63: USPFO - ADP requests a 30 KW generator to be positioned at the USPFO building to maintain computer connectivity for AL Nat Guard. | P63: USPFO - ADP requests a 30 KW generator to be positioned at the USPFO building to maintain computer connectivity for AL Nat Guard. | R63: Keane
A64: 63 | B64: 40301.698 | C64: 40301.698 | D64: Injected | E64: 40301.698 | F64: INFO - Holman Prison | G64: E-Mail | H64: SEOC Department of Public Safety LNO | I64: SEOC LNO | J64: JOC Message Center | K64: Holman Prison Blues | M64: Gulf Shores police report confrontation with motorcycle gang | P64: Gulf Shores Police Department reports confrontation with twelve members of out-of-state outlaw motorcycle club(Road Vermin M/C) who were drunk and disorderly at a local bar. Gulf Shores Police indicate that incident was handled with no need for arrests. They also indicate that an unusually large number of outlaw M/C members are present in the Gulf Coast area, particularly prior to a hurricane. They indicate that the Road Vermin M/C has known alliances with white supremacist organizations. | R64: Jenne
A65: 64 | B65: 40301 | D65: Injected | E65: 40301.708 | F65: MISSION - BPT | I65: SEOC LNO | M65: BPT provide Engineer assets for re-entry and debris operations in affected counties. | P65: BPT provide Engineer assets for re-entry and debris operations in affected counties. | R65: Keane
A66: 65 | D66: Injected | E66: 40301.708 | F66: RFI | G66: Phone | I66: P. MCDONALD | K66: The Department of Defense has ordered an evacuation of personnel, aircraft and ships from the Gulf of Mexico. Some DoD aircraft will be made available to state and federal agencies until 24 hours from estimated landfall. | O66: At 1711 hours, CAPT Manson, DCSOPS NAVOPS, advised MAJ Davis, AL-JOC that DoD assets were available through DCO. | P66: The Department of Defense has ordered an evacuation of personnel, aircraft and ships from the Gulf of Mexico. Some DoD aircraft will be made available to state and federal agencies until 24 hours from estimated landfall. | R66: McDonald
A67: 66 | B67: 40301 | D67: Injected | E67: 40301.728 | F67: RFI | I67: SEOC LNO | K67: CONTRA FLOW | M67: DOT through AEMA requests information on availability of 100 soldiers and 50 vehicles for assistance in implementing the I-65 Lane Reversal Contingency Plan. | P67: DOT through AEMA requests information on availability of 100 soldiers and 50 vehicles for assistance in implementing the I-65 Lane Reversal Contingency Plan. | R67: Keane
A68: 67 | B68: 40301.771 | C68: 40301.771 | D68: Injected | E68: 40301.771 | F68: INFO - Holman Prison | G68: Phone Call | H68: SEOC LNO | I68: SEOC LNO | J68: J-3 | K68: Holman Prison Blues | M68: SEOC LNO calls in "heads up" notification that DOC may request Guard assistance at Holman Prison | P68: SEOC LNO describes developing situation at Holman Prison in which inmates apparently intend to riot and take over the prison during the hurricane, followed by a mass escape assisted by external forces. LNO states that DOC and State Troopers are confident that they can manage the situation inside the prison, to include the perimeter, but are concerned about the potential of external forces attempting to force their way in to breach fences and other security measures. Are considering asking for "two to three platoons" of MPs or infantry to establish extra security perimeter. | R68: Jenne
A69: 68 | B69: 40301 | C69: 0.625 | D69: Injected | E69: 40301.875 | F69: INFO | G69: email | H69: simcell-SEOC | I69: SEOC LNO | J69: J35 | K69: CONTRA FLOW | M69: Governor orders Contra-flow of I-65 | N69: FRAGO to 62nd Troop Command | P69: Governor oders I 65 contra flow operations conducted beginning 0800 4 May 2010 | R69: Messer
A70: 69 | D70: Injected | E70: 40301.913 | F70: INFO - Evacuation | G70: Email | I70: SEOC LNO | K70: EVACUATION | M70: Governor Orders Evacuation of Dauphin Island and Gulf Shores | P70: Governor Orders Evacuation of Dauphin Island and Gulf Shores | R70: Keane
A71: 70 | B71: 40301 | C71: 40301.917 | D71: Injected | E71: 40301.917 | F71: INFO | G71: Email | H71: Simcell - National Hurricane Center | I71: KEANE | J71: JOC, All | K71: Tropical Storm Al Update 12 | L71: 5, 15 | M71: Tropical Storm Al Update 12 | P71: ... HURRICANE AL THREATENS CANCUN... SUMMARY OF 2300 AM EDT...0300 UTC...INFORMATION ----------------------------------------------- LOCATION...19.9N 85.1W ABOUT 141 MILES...228 KM...SOUTHWEST OF CANCUN MEXICO ABOUT 245 MILES...395 KM...WEST-SOUTHWEST OF GEORGE TOWN CAYMAN ISLANDS ABOUT 261 MILES...421 KM...NORTHEAST OF BELIZE CITY BELIZE MAXIMUM SUSTAINED WINDS...120 MPH...193 KM/HR PRESENT MOVEMENT...WNW OR 306 DEGREES AT 20 MPH...32 KM/HR MINIMUM CENTRAL PRESSURE...952 MB...28.11 INCHES | R71: Keane
A72: 71 | B72: 40302 | C72: 40302.167 | D72: Injected | E72: 40302.167 | F72: INFO | G72: Email | H72: Simcell - National Hurricane Center | I72: KEANE | J72: JOC, All | K72: Tropical Storm Al Update 13 | L72: 5, 15 | M72: Tropical Storm Al Update 13 | P72: ... HURRICANE AL EYE JUST OFF THE TIP OF THE YUCATAN... SUMMARY OF 0500 AM EDT...0900 UTC...INFORMATION ----------------------------------------------- LOCATION...21.2N 86.2W ABOUT 41 MILES...66 KM...EAST OF CANCUN MEXICO ABOUT 67 MILES...109 KM...NORTHEAST COZUMEL MEXICO ABOUT 94 MILES...152 KM...WEST-SOUTHWEST OF THE WESTERN TIP OF CUBA MAXIMUM SUSTAINED WINDS...105 MPH...168 KM/HR PRESENT MOVEMENT...WNW OR 316 DEGREES AT 12 MPH...19 KM/HR MINIMUM CENTRAL PRESSURE...955 MB...28.20 INCHES | R72: Keane
A73: 72 | D73: Omitted | E73: 40302.167 | F73: 31st CHEM BDE - Staff security requirements for Evac Shelters | G73: Not Injected | R73: Napier
A74: 73 | D74: Omitted | E74: 40302.208 | F74: 31st CHEM BDE - Coordinate w/ JTF-S and establish direct communications with 1165th and 690th | G74: Not Injected | R74: Napier
A75: 74 | D75: Injected | E75: 40302.292 | G75: EMITS | H75: White Cell - AEMA | I75: SEOC LNO | J75: JOC | P75: DOT through AEMA requests resources resources (vehicles and manpower) to staff twenty traffic control points to assist in implementing the I-65 Lane Reversal Contingency Plan. | R75: Keane
A76: 75 | B76: 40302.083 | C76: 40302.083 | D76: Injected | E76: 40302.302 | F76: INFO - Holman Prison | G76: E-Mail | H76: SEOC Department of Public Safety LNO | I76: SEOC LNO | J76: JOC Message Center | K76: Holman Prison Blues | M76: Armored cars stolen in Mobile | P76: Mobile Police Department reports incident where three armored cars were stolen from a Brinks Company parking lot in Mobile. Report states that parking lot guard and vehicle dispatcher were overpowered by five armed men at approximately 0200. Three armored cars (no money or valuables) were taken. Vehicles were equipped with tracking devices, but the tracking devices were disabled shortly after the incident. | R76: Jenne
A77: 76 | D77: Injected | E77: 40302.316 | F77: INFO - KC-135 Crash | I77: JENNE | M77: Initial Report of KC-135 Crash in Birmingham (soldier calls in to report that it is on the news)
A78: 77 | D78: Injected | E78: 40302.319 | F78: INFO - KC-135 Crash | I78: 117TH OPS | M78: Follow-Up Report on KC-135 Crash (from 117th Operations to Air ATAG)
A79: 78 | D79: Injected | E79: 40302.333 | F79: INFO - KC-135 Crash | I79: 117TH OPS | M79: Follow-Up Report on KC-135 Crash (from 117th Operations to Air ATAG) concerning radioactive materials found on aircraft
A80: 79 | D80: Omitted | E80: 40302.333 | F80: 31st CHME BDE - Stands up the CMOC | G80: Not Injected | R80: Napier
A81: 80 | B81: 40302.354 | C81: 40302.354 | D81: Injected | E81: 40302.354 | F81: RFI - Holman Prison | G81: EMITS | H81: SEOC | I81: SEOC LNO | J81: JOC Message Center | K81: Holman Prison Blues | M81: SEOC requests contingency study on providing security assistance at Holman Prison | P81: SEOC requests that Guard conduct a contingency study to determine if they can provide security assistance to Holman Prison at same time hurricane response operations are underway. Potential security assistance requirement is for approximately a company-sized element (preferably MPs or infantry) to establish VCPs, roadblocks and blocking positions on external perimeter to prevent external forces from entering prison compound and providing assistance to prisoners. All Guard operations are anticipated to be external to prison; DOC and State Troopers will manage in-prison and internal security perimeter. Governor states that because of political sensitivity of situation, he wants a detailed briefback on ground tactical plan (via VTC or other means, if necessary) to Directors of DOC and DPS. | R81: Jenne
A82: 81 | D82: Injected | E82: 40302.417 | F82: INFO | G82: Phone | H82: White Cell - JTF South | I82: POLLARD | J82: JTF South | M82: Sgt ……. Vehicle rolled over on interstate in route to armory. He was wearing a seat belt but rolled into ditch and drowned | Q82: SIR should be developed/ NGB notified/ TAG/ PAO/ CCIR tracking established | R82: Kahl
A83: 82 | D83: Injected | E83: 40302.427 | F83: INFO - KC-135 Crash | I83: HOWARD | M83: News media calling concerning KC-135 Crash and radioactive materials
A84: 83 | B84: 40303.396 | C84: 0.39583333 | D84: Injected | E84: 40302.438 | F84: INFO - Train Derailment | G84: Telephone | H84: FTUS NCO manning Grove Hill armory | I84: POLLARD | J84: JTF-S | K84: Grove Hill Train Derailment | M84: Grove Hill soldier reports significant train derailment | N84: JTF-S should pass this information upline to JFHQ JOC. | O84: The entire purpose of ths thread is to determine if the information (which will be received from multiple sources at different levels) is passed up-line to JFHQ JOC, and then subsequently assessed by various J-Staff elements. The location of the train derailment is directly adjacent to US 43, which should be an MSR for moving troops and equipment downrange, so will J-2 and J-4 receive info and advise TAG and units accordingly? | P84: FTUS NCO from Det 1, Co A, 711 BSB is standing by at Grove Hill armory to support hurricane response operations. He reports that a north-bound Norfolk Southern train experienced a serious derailment between Grove Hill and Thomasville (to the north). Clarke County Sheriff's Department and local fire departments are responding. A hazardous materials release is suspected. NCO states that local officials indicate that Grove Hill and surrounding communities will likely be evacuated. He is requesting guidance if evacuation is required. | R84: Jenne
A85: 84 | D85: Injected | E85: 40302.441 | F85: INFO - KC-135 Crash | H85: BFRS | I85: JENNE | M85: Birmingham Fire and Rescue Service isolating KC-135 crash site until radioactive materials can be identified. Requesting Guard assistance.
A86: 85 | B86: 40302.396 | C86: 0.40625 | D86: Injected | E86: 40302.448 | F86: INFO - Train Derailment | G86: Telephone or e-mail | H86: SEOC LNO | I86: SEOC LNO | J86: JOC Chief | K86: Grove Hill Train Derailment | M86: SEOC LNO reports train derailment just north of Grove Hill | N86: JOC Chief should notify TAG and key leaders, pertinent staff personnel and JTFs. | O86: The entire purpose of ths thread is to determine if the information (which will be received from multiple sources at different levels) is passed up-line to JFHQ JOC, and then subsequently assessed by various J-Staff elements. The location of the train derailment is directly adjacent to US 43, which should be an MSR for moving troops and equipment downrange, so will J-2 and J-4 receive info and advise TAG and units accordingly? | P86: SEOC LNO calls JOC Chief with a "heads up" that a Norfolk Southern train has derailed approximately ten miles north of Grove Hill (Clarke County). The train was being "pushed" north to get it out of the hurricane impact area. Derailment involves multiple tank cars of hazardous materials, including chlorine, anhydrous ammonia, and flourine. Local emergency responders are on scene; State Troopers and ADEM are en route. SEOC LNO states that EMA may request technical assistance from the CST. | R86: Jenne
A87: 86 | B87: 40302 | C87: 40302.417 | D87: Injected | E87: 40302.417 | F87: INFO | G87: Email | H87: Simcell - National Hurricane Center | I87: KEANE | J87: JOC, All | K87: Tropical Storm Al Update 14 | L87: 5, 15 | M87: Tropical Storm Al Update 14 | P87: ... HURRICANE AL PASSES NORTH OF CANCUN...ENTERS THE GULF OF MEXICO... SUMMARY OF 1100 AM EDT...1500 UTC...INFORMATION ----------------------------------------------- LOCATION...22.0N 86.8W ABOUT 58 MILES...94 KM...NORTH OF CANCUN MEXICO ABOUT 120 MILES...193 KM...WEST OF THE WESTERN TIP OF CUBA MAXIMUM SUSTAINED WINDS...105 MPH...169 KM/HR PRESENT MOVEMENT...WNW OR 314 DEGREES AT 15 MPH...24 KM/HR MINIMUM CENTRAL PRESSURE...960 MB...28.35 INCHES | R87: Keane
A88: 87 | D88: Injected | E88: 40302.459 | G88: Email | I88: TOMBERLIN | K88: All units activated submit travel vouchers for identified soldiers. | P88: All units activated submit travel vouchers for identified soldiers. | R88: Therman
A89: 88 | D89: Injected | E89: 40302.479 | F89: RFI | G89: Email | I89: DENNIS | M89: Task Force South is requesting a Class A Agent. | P89: Task Force South is requesting a Class A Agent. | R89: Therman
A90: 89 | D90: Injected | E90: 40302.486 | F90: INFO - KC-135 Crash | I90: JENNE | M90: Birmingham Police bomb robot being used to inspect interior of aircraft. Located container with marking (NSN number)
A91: 90 | B91: 40302.396 | C91: 0.44791667 | D91: Injected | E91: 40302.49 | F91: RFI - Train Derailment | G91: EMITS | H91: SEOC WC | I91: SEOC LNO | J91: JOC Message Center | K91: Grove Hill Train Derailment | M91: EMITS Request for Assistance for Train Derailment emergency response | N91: JOC Chief should notify TAG and key leaders, pertinent staff personnel and JTFs. | O91: The entire purpose of ths thread is to determine if the information (which will be received from multiple sources at different levels) is passed up-line to JFHQ JOC, and then subsequently assessed by various J-Staff elements. The location of the train derailment is directly adjacent to US 43, which should be an MSR for moving troops and equipment downrange, so will J-2 and J-4 receive info and advise TAG and units accordingly? | P91: EMITS message requests capability assessment of potential Guard capabilities to assist with train derailment north of Grove Hill. Area, including US 43, is being evacuated. EMA wants to know viability of CST providing hazardous materials assistance. Additionally, EMA wants to determine availability of FLIRS-equipped R/W aircraft to locate "hot spots" in train, to assist in firefighting effort. There is extensive smoke as a result of multiple fires, which is why FLIR is being requested. State Trooper FLIR-equipped aircraft are currently tasked to other activities. | R91: Jenne
A92: 91 | B92: 40302 | C92: 0.45833333 | D92: Injected | E92: 40302.501 | F92: INFO | G92: Phone | H92: GATE GUARD | I92: DONAHUE | J92: MSG CTR | K92: AT/FP | M92: Citizen reports accident at front gate | N92: MSG CTR reports to J3/ who calls 911? | P92: I just witnessed an accident at the gate in which a large truck was hit by a civilian car. What should I do? | R92: Messer
A93: 92 | D93: Injected | E93: 40302.501 | F93: RFI | G93: Email | H93: USPFO | I93: DENNIS | M93: National Guard Bureau is requesting a spreadsheet which capture and track funding costs associated with the hurricane disaster. | P93: National Guard Bureau is requesting a spreadsheet which capture and track funding costs associated with the hurricane disaster. | R93: Therman
A94: 93 | D94: Injected | E94: 40302.521 | F94: INFO - KC-135 Crash | H94: GOVERNOR'S OFFICE | I94: REAGAN | M94: Governor asks TAG to conduct press conference concerning KC-135 crash
A95: 94 | B95: 40302 | C95: 0.5 | D95: Injected | E95: 40302.042 | F95: RFI | G95: Email | I95: TF S2 | J95: JOC, J2 | M95: Weather Update/Storm Track | N95: J2 Provides latest Weather and Storm Track to the TFs | P95: Weather RFI from Task Force to J2 | R95: Houlton
A96: 95 | B96: 40302 | C96: 0.54166667 | D96: Injected | E96: 40302.583 | F96: RFI | G96: Email | I96: MCLEOD | J96: CFMO | K96: Provide information as to what armories are under construction. Specifically in areas of the projected landfall, or planned staging areas. | M96: SA | P96: Provide information as to what armories are under construction. Specifically in areas of the projected landfall, or planned staging areas. | R96: McLeod
A97: 96 | B97: 40302.396 | C97: 0.54166667 | D97: Injected | E97: 40302.584 | F97: INFO - Train Derailment | G97: Telephone | H97: SEOC WC | I97: SEOC LNO | J97: JOC Message Center | K97: Grove Hill Train Derailment | M97: SEOC LNO forwards report from DPS concerning train derailment north of Grove Hill | N97: JOC Chief should notify TAG and key leaders, pertinent staff personnel and JTFs. | O97: The entire purpose of ths thread is to determine if the information (which will be received from multiple sources at different levels) is passed up-line to JFHQ JOC, and then subsequently assessed by various J-Staff elements. The location of the train derailment is directly adjacent to US 43, which should be an MSR for moving troops and equipment downrange, so will J-2 and J-4 receive info and advise TAG and units accordingly? | P97: SEOC LNO calls to report that DPS has just given a briefing on Grove Hill train derailment. DPS stated that the derailment involved a train consisting of four diesel-electric locomotives and roughly two hundred railcars of varying types. They stated that at least a third of the rolling stock had physically left the railroad tracks as a result of the derailment. The accident involved numerous tank cars containing hazardous materials, but there is no clear indication whether any of these cars are breached or in danger of breaching. The derailment involves multiple fires, most apparently involving rail cars carrying building materials (plywood) and bulk carpet scraps. Because of the fires, thesre is considerable amount of low-hanging smoke in the area, which is slowing the efforts of emergency responders to assess damages. Until hazards can be completely assessed, a mandatory evacuation is currently underway for the towns of Grove Hill, Fulton, Dickenson, and Thomasville. US 43 is closed, and all motorists are advised to avoid Clarke County because of all the evacuation-related traffic in the vicinity of the accident. | R97: Jenne
A98: 97 | D98: Injected | E98: 40302.585 | F98: INFO | G98: Email | H98: USPFO | I98: DENNIS | M98: There are no military transportation assets available, provide commercial haul to deliver 50 tents (GP Medium) to Fort Whiting. | N98: Identify assets to be used for haul | P98: There are no military transportation assets available, provide commercial haul to deliver 50 tents (GP Medium) to Fort Whiting. | R98: Therman
A99: 98 | B99: 40302 | C99: 0.5625 | D99: Injected | E99: 40302.604 | F99: INFO | G99: Email | I99: MCLEOD | J99: CFMO | M99: "X" armory is being renovated, and is not suitable for occupation before, during, or after land fall. BPT coordinate with local/regional contractors for services at alternate locations. | P99: "X" armory is being renovated, and is not suitable for occupation before, during, or after land fall. BPT coordinate with local/regional contractors for services at alternate locations. | R99: McLeod
A100: 99 | B100: 40302.396 | C100: 0.58333333 | D100: Injected | E100: 40302.625 | F100: RFI - Train Derailment | G100: EMITS | H100: SEOC WC | I100: SEOC LNO | J100: JOC Message Center | K100: Grove Hill Train Derailment | M100: EMITS Request for Assistance for Train Derailment emergency response | N100: JOC Chief should notify TAG and key leaders, pertinent staff personnel and JTFs. | O100: JOC planners may determine that a more appropriate targeting/attack method would be linear slurry drops with fixed wing aircraft (like C-130s) rather than spot attacks with helicopters. JOC may determine if slurry-equipped aircraft are available for EMACS request. | P100: EMITS message requests capability assessment of potential Guard capabilities to assist with train derailment north of Grove Hill. Request is to determine availability of CH-47 or UH-60 "Bambi Bucket" capability to help extinguish fires on railcars because of difficulty reaching fires with conventional fire apparatus. | R100: Jenne
...

Sheet MSEL INFO ONLY
A1: MSEL NUMBER | B1: DATE | C1: Time | D1: INJECT DTG | E1: INJECT MODE | F1: SEND FROM (Simulated) | G1: INJECTED BY | H1: SEND TO | I1: STORYLINE/THREAD | J1: ESF | K1: DESCRIPTION | L1: INJECT MODE | M1: OBJ. (SA, RFA, RFI, NGA - Action that generates planning or activity) | N1: INITIATED BY | O1: Inject Entry (JOC, JTF-N/S, DRU, AEMA, Staff, Leadership, Other) | P1: NARRATIVE | Q1: BACKGROUND INFORMATION
E2: Weather | K2: Weather
E3: AEMA SA/RFI | K3: AEMA SA/RFI
E4: Weather and Threat related | K4: Weather and Threat related
E5: AEMA Mission Tasker | K5: AEMA Mission Tasker
E6: JFHQ Staff | K6: JFHQ Staff
E7: JTF/Task Force/ DRU RFI/RFA | K7: JTF/Task Force/ DRU RFI/RFA
E8: EMAC Related | K8: EMAC Related
B10: 41399 | C10: 41399.167 | D10: 41398.167 | E10: Email | F10: Simcell - National Hurricane Center | G10: Keane | H10: JOC, All | I10: Tropical Depression One Forms | J10: 5, 15 | K10: Tropical Depression One Forms | L10: EMITS or Email | M10: SA | N10: White Cell | O10: JOC | P10: On 04 May, 0400 HRS CDT, The National Hurricane Center issues Tropical Depression Advisory "One". Current Location 14.5 N 74.1 W Max Sustained Wind 30mph
B11: 41398.208 | C11: 41398.208 | D11: 41398.213 | E11: Not Injected - MSEL Planning Info only | I11: Background Information (Hurricane Synchronization Matrix) | K11: J-1 / Safety - Begin statewide push on Hurricane and Tornado | L11: EMITS or Email | M11: SA | N11: White Cell | O11: JOC
B12: 41398.208 | C12: 41398.208 | D12: 41398.213 | E12: Not Injected - MSEL Planning Info only | I12: Background Information (Hurricane Synchronization Matrix) | K12: J-1 / Strength - Review J-1 / Medical, Avn/Trans, EN, MP, LG and SIG/IT Personnel Assets | L12: EMITS or Email | M12: SA | N12: White Cell | O12: JOC
B13: 41398.208 | C13: 41398.208 | D13: 41398.214 | E13: Not Injected - MSEL Planning Info only | I13: Background Information (Hurricane Synchronization Matrix) | K13: J-4 / Class I - Review MRE DOS, ensure sufficient 2 DOS per JTF | L13: EMITS or Email | M13: SA | N13: White Cell | O13: JOC
B14: 41398.208 | C14: 41398.208 | D14: 41398.215 | E14: Not Injected - MSEL Planning Info only | I14: Background Information (Hurricane Synchronization Matrix) | K14: J-4 / Class III - Link up with SPDOF and verify that fuel contracts listed are valid | L14: EMITS or Email | M14: SA | N14: White Cell | O14: JOC
B15: 41398.208 | C15: 41398.208 | D15: 41398.215 | E15: Not Injected - MSEL Planning Info only | I15: Background Information (Hurricane Synchronization Matrix) | K15: J-4 / Class IX - Verify status of CL IX push package. Verify maint status of equipement | L15: EMITS or Email | M15: SA | N15: White Cell | O15: JOC
B16: 41398.208 | C16: 41398.208 | D16: 41398.216 | E16: Not Injected - MSEL Planning Info only | I16: Background Information (Hurricane Synchronization Matrix) | K16: J-4 / Class V - Review requirements with FMARNGTC ATP. Verify sufficient on hand | L16: EMITS or Email | M16: SA | N16: White Cell | O16: JOC
B17: 41398.208 | C17: 41398.208 | D17: 41398.217 | E17: Not Injected - MSEL Planning Info only | I17: Background Information (Hurricane Synchronization Matrix) | K17: J-4 / Class VII - Review initial density report. Determine shortages and X-Level | L17: EMITS or Email | M17: SA | N17: White Cell | O17: JOC
B18: 41398.208 | C18: 41398.208 | D18: 41398.217 | E18: Not Injected - MSEL Planning Info only | I18: Background Information (Hurricane Synchronization Matrix) | K18: J-4 / Class VIII - Review quantities available, specifically IV fluids for CLS Bags | L18: EMITS or Email | M18: SA | N18: White Cell | O18: JOC
B19: 41398.208 | C19: 41398.208 | D19: 41398.218 | E19: Not Injected - MSEL Planning Info only | I19: Background Information (Hurricane Synchronization Matrix) | K19: J-4 / Class II - Inventory DERT, note shortages and makeup shortages | L19: EMITS or Email | M19: SA | N19: White Cell | O19: JOC
B20: 41398.208 | C20: 41398.208 | D20: 41398.219 | E20: Not Injected - MSEL Planning Info only | I20: Background Information (Hurricane Synchronization Matrix) | K20: J-4 / Misc Funding - Review available funds for use during contingency operations. Monitor funding levels. | L20: EMITS or Email | M20: SA | N20: White Cell | O20: JOC
B21: 41398.208 | C21: 41398.208 | D21: 41398.219 | E21: Not Injected - MSEL Planning Info only | I21: Background Information (Hurricane Synchronization Matrix) | K21: J-4 / Transportation - Prepare to issue convoy orders to affected units to strike sector. Verify status of enablers | L21: EMITS or Email | M21: SA | N21: White Cell | O21: JOC
B22: 41398.208 | C22: 41398.208 | D22: 41398.22 | E22: Not Injected - MSEL Planning Info only | I22: Background Information (Hurricane Synchronization Matrix) | K22: JTF-187 FW - FTUS Hurricane Tracking | L22: EMITS or Email | M22: SA | N22: White Cell | O22: JOC
... B36: 41399.208 | C36: 41399.208 | D36: 41398.217 | E36: Not Injected - MSEL Planning Info only | I36: Background Information (Hurricane Synchronization Matrix) | K36: White Cell JTF-Tarpon - Test alert roster for key personnel TPFDD to JTF-S | L36: EMITS or Email | M36: SA | N36: White Cell | O36: JOC
B37: 41399 | C37: 41399.417 | D37: 41398.417 | E37: Email | F37: Simcell - National Hurricane Center | G37: Keane | H37: JOC, All | I37: Tropical Storm Al Update 2 | J37: 5, 15 | K37: Tropical Storm Al Update 2 | L37: EMITS or Email | M37: SA | N37: White Cell | O37: JOC | P37: ...FIRST TROPICAL STORM OF THE SEASON...AL NEARS THE COAST OF NICARAGUA... SUMMARY OF 1100 AM EDT...1500 UTC...INFORMATION ----------------------------------------------- LOCATION...14.9N 74.9W ABOUT 220 MILES...354 KM...SOUTH SOUTHEAST OF KINGSTON JAMA
B38: 41399 | C38: 41399.667 | D38: 41398.667 | E38: Email | F38: Simcell - National Hurricane Center | G38: Keane | H38: JOC, All | I38: Tropical Storm Al Update 3 | J38: 5, 15 | K38: Tropical Storm Al Update 3 | L38: EMITS or Email | M38: SA | N38: White Cell | O38: JOC | P38: ...TROPICAL STORM AL STRENGTHENS AS IT NEARS THE COAST OF NICARAGUA... SUMMARY OF 1700 AM EDT...2100 UTC...INFORMATION ----------------------------------------------- LOCATION...15.30 N 76.20 W ABOUT 188 MILES...303 KM...167 DEGREES...SOUTH-SOUTHEAST OF
B39: 41399 | C39: 41399.917 | D39: 41398.917 | E39: Email | F39: Simcell - National Hurricane Center | H39: JOC, All | I39: Tropical Storm Al Update 4 | J39: 5, 15 | K39: Tropical Storm Al Update 4 | L39: EMITS or Email | M39: SA | N39: White Cell | O39: JOC | P39: ...AL BECOMES A HURRICANE AS IT NEARS THE NORTH COAST OF NICARAGUA... SUMMARY OF 1100 PM EDT...0300 UTC...INFORMATION ----------------------------------------------- LOCATION...15.50 N 77.10 W ABOUT 172 MILES...277 KM...SOUTH SOUTHEAST OF KINGSTON JAMAI
B40: 41400.208 | C40: 41400.208 | D40: 41399.208 | E40: Not Injected - MSEL Planning Info only | I40: Tropical Storm Al Update 5 | K40: Tropical Storm Al Update 5 | L40: EMITS or Email | M40: SA | N40: White Cell | O40: JOC | P40: ... AT 5 AM AST...0900Z...AL BECOMES A HURRICANE AS IT NEARS THE NORTH COAST OF NICARAGUALOCATION...15.90 N 78.10 W ABOUT 159 MILES... 255 KM... SOUTH NEGRIL JAMAICA ABOUT 375 MILES... 604 KM... EAST-NORTHEAST OF PUERTO CABEZAS NICARAGUA MAXIMUM SUSTAINED WINDS...85 MPH...137 KM/HR PRESENT MOVEMENT...WNW OR 275 DEGREES AT 12 MPH...19 KM/HR
B41: 41400.208 | C41: 41400.208 | D41: 41399.209 | E41: Not Injected - MSEL Planning Info only | I41: Background Information (Hurricane Synchronization Matrix) | K41: 187 FW - Issue BPT deploy order to 122d ASG and alert LNOs | L41: EMITS or Email | M41: SA | N41: White Cell | O41: JOC
B42: 41399.208 | C42: 41399.208 | D42: 41399.21 | E42: Not Injected - MSEL Planning Info only | I42: Background Information (Hurricane Synchronization Matrix) | K42: 167 TSC - Implement CEMP 10-2 Annex B | L42: EMITS or Email | M42: SA | N42: White Cell | O42: JOC
B43: 41399.208 | C43: 41399.208 | D43: 41399.21 | E43: Not Injected - MSEL Planning Info only | I43: Background Information (Hurricane Synchronization Matrix) | K43: 20 SF - Dispatch LNO to State JOC, Cooridnate with 131st AVN | L43: EMITS or Email | M43: SA | N43: White Cell | O43: JOC
B44: 41399.208 | C44: 41399.208 | D44: 41399.211 | E44: Not Injected - MSEL Planning Info only | I44: Background Information (Hurricane Synchronization Matrix) | K44: JTF Tarpon TC - Issue WARN ORDER 1, CMC Prep | L44: EMITS or Email | M44: SA | N44: White Cell | O44: JOC
B45: 41399.208 | C45: 41399.208 | D45: 41399.212 | E45: Not Injected - MSEL Planning Info only | I45: Background Information (Hurricane Synchronization Matrix) | K45: AEMA SEOC - Alert Alabama Mutual Aid System and County Liaisons | L45: EMITS or Email | M45: SA | N45: White Cell | O45: JOC
B46: 41399.208 | C46: 41399.208 | D46: 41399.213 | E46: Not Injected - MSEL Planning Info only | I46: Background Information (Hurricane Synchronization Matrix) | K46: AEMA SEOC -Activate Logistics Staging at Maxwell AFB | L46: EMITS or Email | M46: SA | N46: White Cell | O46: JOC
B47: 41399.208 | C47: 41399.208 | D47: 41399.213 | E47: Not Injected - MSEL Planning Info only | I47: Background Information (Hurricane Synchronization Matrix) | K47: AEMA SEOC -Activate Resource Contracts for Security, Food, Ice and Water | L47: EMITS or Email | M47: SA | N47: White Cell | O47: JOC
B48: 41399.208 | C48: 41399.208 | D48: 41399.214 | E48: Not Injected - MSEL Planning Info only | I48: Background Information (Hurricane Synchronization Matrix) | K48: AEMA SEOC -Begin Opening Shelters | L48: EMITS or Email | M48: SA | N48: White Cell | O48: JOC
B49: 41399.208 | C49: 41399.208 | D49: 41399.215 | E49: Not Injected - MSEL Planning Info only | I49: Background Information (Hurricane Synchronization Matrix) | K49: AEMA SEOC -Begin Public Information Briefings | L49: EMITS or Email | M49: SA | N49: White Cell | O49: JOC
B50: 41399.208 | C50: 41399.208 | D50: 41399.215 | E50: Not Injected - MSEL Planning Info only | I50: Background Information (Hurricane Synchronization Matrix) | K50: AEMA SEOC -Begin Twice Daily Situation Updates | L50: EMITS or Email | M50: SA | N50: White Cell | O50: JOC
B51: 41399.208 | C51: 41399.208 | D51: 41399.216 | E51: Not Injected - MSEL Planning Info only | I51: Background Information (Hurricane Synchronization Matrix) | K51: AEMA SEOC -Participate in FEMA and Hurricane Liaison Team Conference Calls | L51: EMITS or Email | M51: SA | N51: White Cell | O51: JOC
B52: 41399.208 | C52: 41399.208 | D52: 41399.217 | E52: Not Injected - MSEL Planning Info only | I52: Background Information (Hurricane Synchronization Matrix) | K52: AEMA SEOC -Request Shelter Generators | L52: EMITS or Email | M52: SA | N52: White Cell | O52: JOC
... B67: 41399.208 | C67: 41399.208 | D67: 41399.227 | E67: Not Injected - MSEL Planning Info only | I67: Background Information (Hurricane Synchronization Matrix) | K67: LNO'S - ALERT LNOs | L67: EMITS or Email | M67: NGA | N67: White Cell | O67: JOC
B68: 41399 | C68: 41399.417 | D68: 41399.417 | E68: Email | F68: Simcell - National Hurricane Center | H68: JOC, All | I68: Tropical Storm Al Update 6 | J68: 5, 15 | K68: Tropical Storm Al Update 6 | L68: EMITS or Email | M68: SA | N68: White Cell | O68: JOC | P68: ... HURRICANE AL TRACKS TOWARD THE YUCATAN... SUMMARY OF 1100 AM EDT...0900 UTC...INFORMATION ----------------------------------------------- LOCATION...16.3N 79.0W ABOUT 257 MILES... 321 KM...SOUTH SOUTHEAST OF GEORGE TOWN CAYMAN ISLANDS ABOUT 137 MIL
D69: 5/5/2013 10:100:00 AM | K69: 4 HEMIT 2500 gallon tankers with JP-8 fuel | L69: EMITS or Email | M69: NGA | N69: White Cell | O69: J4/8 | P69: SAO is anticipating relocating airlift support at remote locations within the State. There is an immediate need to top off 4 HEMIT 2500 gallon tankers with JP-8 fuel in support of this mission. Please advise on procedure to obtain fuel.
D70: 41399.425 | K70: Availability of HMMWVs and Cargo Trucks | L70: EMITS or Email | M70: RFI | N70: AEMA | P70: AEMA has determined that there may be a requirement to use high water vehicles in support of possible evacuation and SAR missions. AEMA has inquired to the ALNG about the availability of HMMWVs and Cargo Trucks that could be used in high water conditions if necessary to carry personnel, light cargo and emergency supplies. The SEOC wants to know the availability of high water vehicles in the ALNG by types.
D71: 41399.427 | K71: ISO high water operations | L71: EMITS or Email | M71: RFI | N71: AEMA | P71: In anticipation of possible missions ISO high water operations, the SEOC requires information on the maximum depth of water military vehicles can ford . (fording capabilities)
B72: 40301 | C72: 41400.375 | D72: 41399.428 | E72: Email | F72: USPFO, S&S | H72: JOC J4 | K72: USPFO Pre-Position | L72: EMITS or Email | M72: RFA | N72: USPFO, S&S | O72: JOC | P72: USPFO Warehouse to push 20 pallets of MREs and 20 pallets of bottled water to Ft McClellan, AL (pre-positioning for soldier support). | Q72: USPFO Warehouse SOP, SA only
B73: 40301 | C73: 41400.375 | D73: 41400.428 | E73: Email | F73: USPFO, S&S | H73: JOC J4 | K73: USPFO Pre-Position | L73: EMITS or Email | M73: RFA | N73: USPFO, S&S | O73: JOC | P73: USPFO Warehouse to push 20 pallets of MREs and 20 pallets of bottled water to Ft Whiting, Mobile, AL (pre-positioning for soldier support). | Q73: USPFO Warehouse SOP, SA only
B74: 41399 | C74: 0.5 | D74: 41399.5 | E74: Email | F74: Each Task Force | G74: TF S2 | H74: JOC, J2 | K74: Weather Update/Storm Track | L74: EMITS or Email | M74: SA | N74: White Cell | O74: JOC | P74: Weather RFI from Task Force to J2
B75: 41399 | C75: 41401.667 | D75: 41399.667 | E75: Email | F75: Simcell - National Hurricane Center | H75: JOC, All | I75: Tropical Storm Al Update 7 | J75: 5, 15 | K75: Tropical Storm Al Update 7 | L75: EMITS or Email | M75: SA | N75: White Cell | O75: JOC | P75: ... HURRICANE AL TRACKS TOWARD THE YUCATAN...AS A CATEGORY TWO HURRICANE... SUMMARY OF 0500 AM EDT...0900 UTC...INFORMATION ----------------------------------------------- LOCATION...16.7N 80.0W ABOUT 199 MILES... 321 KM...SOUTH SOUTHEAST OF GEORGE TOWN
B76: 41401 | C76: 41401.917 | D76: 41399.917 | E76: Email | F76: Simcell - National Hurricane Center | H76: JOC, All | I76: Tropical Storm Al Update 8 | J76: 5, 15 | K76: Tropical Storm Al Update 8 | L76: EMITS or Email | M76: SA | N76: White Cell | O76: JOC | P76: ... HURRICANE AL GAINS MOMENTUM AS A CATEGORY TWO HURRICANE... SUMMARY OF 2300 PM EDT...0300 UTC...INFORMATION ----------------------------------------------- LOCATION...17.1N 80.9W ABOUT 184 MILES...296 KM...WEST-SOUTHWEST NEGRIL JAMAICA ABOUT 154 MIL
B77: 40301 | C77: 41401.167 | D77: 41400.167 | E77: Email | F77: Simcell - National Hurricane Center | H77: JOC, All | I77: Tropical Storm Al Update 9 | J77: 5, 15 | K77: Tropical Storm Al Update 9 | L77: EMITS or Email | M77: SA | N77: White Cell | O77: JOC | P77: ... HURRICANE AL CONTINUES ON A TRACK TOWARD COZUMEL... SUMMARY OF 0500 AM EDT...0900 UTC...INFORMATION ----------------------------------------------- LOCATION...17.7N 82.1W ABOUT 250 MILES...401 KM...WEST-SOUTHWEST NEGRIL JAMAICA ABOUT 154 MILES...24
B78: 41401.208 | C78: 41401.208 | D78: 41400.208 | E78: Not Injected - MSEL Planning Info only | I78: Background Information (Hurricane Synchronization Matrix) | K78: J-6 - Alert JISCC | L78: EMITS or Email | M78: SA | N78: White Cell | O78: JOC
B79: 41400.208 | C79: 41400.208 | D79: 41400.209 | E79: Not Injected - MSEL Planning Info only | I79: Background Information (Hurricane Synchronization Matrix) | K79: 167 TSC - 122d dispatches LNO's to JTFHQ | L79: EMITS or Email | M79: SA | N79: White Cell | O79: JOC
B80: 41400.208 | C80: 41400.208 | D80: 41400.21 | E80: Not Injected - MSEL Planning Info only | I80: Background Information (Hurricane Synchronization Matrix) | K80: 187 FW - Implement HURCON 4 Checklist/Identify personnel for JOC tasking | L80: EMITS or Email | M80: SA | N80: White Cell | O80: JOC
B81: 41400.208 | C81: 41400.208 | D81: 41400.21 | E81: Not Injected - MSEL Planning Info only | I81: Background Information (Hurricane Synchronization Matrix) | K81: JTF Tarpon - Stand up CMC with FTUS, Coordinate with other JTFs for handoff and receipt of subordinate units, issue WARN ORD 2 | L81: EMITS or Email | M81: SA | N81: White Cell | O81: JOC
B82: 41400.208 | C82: 41400.208 | D82: 41400.211 | E82: Not Injected - MSEL Planning Info only | I82: Background Information (Hurricane Synchronization Matrix) | K82: AEMA SEOC - Begin Incident Action Plan | L82: EMITS or Email | M82: SA | N82: White Cell | O82: JOC
B83: 41400.208 | C83: 41400.208 | D83: 41400.212 | E83: Not Injected - MSEL Planning Info only | I83: Background Information (Hurricane Synchronization Matrix) | K83: AEMA SEOC - Deploy Communications Vans | L83: EMITS or Email | M83: SA | N83: White Cell | O83: JOC
B84: 41400.208 | C84: 41400.208 | D84: 41400.213 | E84: Not Injected - MSEL Planning Info only | I84: Background Information (Hurricane Synchronization Matrix) | K84: AEMA SEOC - Deploy County Liaisons | L84: EMITS or Email | M84: SA | N84: White Cell | O84: JOC
B85: 41400.208 | C85: 41400.208 | D85: 41400.213 | E85: Not Injected - MSEL Planning Info only | I85: Background Information (Hurricane Synchronization Matrix) | K85: AEMA SEOC - Establish Unified Command | L85: EMITS or Email | M85: SA | N85: White Cell | O85: JOC
B86: 41400.208 | C86: 41400.208 | D86: 41400.214 | E86: Not Injected - MSEL Planning Info only | I86: Background Information (Hurricane Synchronization Matrix) | K86: AEMA SEOC - Initiate Voluntary Evacuations | L86: EMITS or Email | M86: SA | N86: White Cell | O86: JOC
B87: 41400.208 | C87: 41400.208 | D87: 41400.215 | E87: Not Injected - MSEL Planning Info only | I87: Background Information (Hurricane Synchronization Matrix) | K87: AEMA SEOC - Plan Back-Up Communications | L87: EMITS or Email | M87: SA | N87: White Cell | O87: JOC
B88: 41400.208 | C88: 41400.208 | D88: 41400.215 | E88: Not Injected - MSEL Planning Info only | I88: Background Information (Hurricane Synchronization Matrix) | K88: AEMA SEOC - Receive FEMA Emergency Response Team | L88: EMITS or Email | M88: SA | N88: White Cell | O88: JOC
B89: 41400.208 | C89: 41400.208 | D89: 41400.216 | E89: Not Injected - MSEL Planning Info only | I89: Background Information (Hurricane Synchronization Matrix) | K89: AEMA SEOC -SEOC Activates at Level Two | L89: EMITS or Email | M89: SA | N89: White Cell | O89: JOC
... B102: 41400.208 | C102: 41400.208 | D102: 41400.225 | E102: Not Injected - MSEL Planning Info only | I102: Background Information (Hurricane Synchronization Matrix) | K102: LNO'S - Dispatch LNOs to AL EMA; Dispatched LOG Cell to EMA JOC | L102: EMITS or Email | M102: SA | N102: White Cell | O102: JOC
B103: 41400.312 | C103: 41400.312 | D103: 41400.313 | E103: Phone Call | F103: JTF-S White Cell (subordinnate commander) | G103: JTF-S WC | H103: 226 MEB | I103: Holman Prison Blues | K103: Company commander requests guidance on soldier | L103: Phone | M103: RFI | N103: White Cell White Cell JTF-Tarpon | P103: Company commander has a soldier who is a prison guard at Holman Prison. Soldier states that he has been directed to remain at prison and not to report to Guard. Indicates rumors of potential inmate takeover and mass escape during hurricane. Soldier/guard needs guidence
D104: 41400.316 | K104: MISSION | L104: EMITS or Email | M104: RFA | N104: AEMA ESF 9 | P104: Provide SAR Planner to SEOC (AL) ESF 9
D105: 41400.319 | E105: EMITS | F105: AEMA ESF 5 | H105: JOC | J105: 5 | K105: MISSION | L105: EMITS or Email | M105: RFA | N105: AEMA ESF 6 | P105: Provide meteorological services to SEOC (AL)
D106: 41400.323 | E106: EMITS | F106: Director AEMA | H106: JOC | K106: BPT Provide 3000 Soldiers | L106: EMITS or Email | M106: NGA | N106: AEMA | P106: BPT to provide 3000 Soldiers for security operations in South and Central Alabama; locations TBD. Request units be self sustaining.
K107: Bus Support Request | L107: EMITS or Email | M107: RFA | N107: White Cell JTF-Tarpon | P107: Provide 2 each 44 PAX busses to transport up to 80 PAX in 711 BSB and 3 buses to transport up to 120 PAX in 877 Engr Bde. Request buses be provided pre-landfall if possible so they can be positioned as necessary.
D108: 41400.333 | E108: Phone | F108: AEMA | H108: AL J3 | K108: AEMA Director contacts AL TAG/J3 to discuss hurricane response planning/operations. | L108: Email | M108: SA | N108: AEMA | P108: AEMA Director contacts AL TAG/J3 to discuss hurricane response planning/operations. AEMA Director states that they are making preliminary plans for possible Alex response operations. Suggests issuing warning orders to MACOMs for potential in-state respon
B109: 40301 | C109: 0.33333333 | D109: 41400.334 | E109: Email | F109: simcell-SEOC | G109: AEMA | H109: J35 | K109: LNO Request | L109: EOC contacts Troop Command | M109: NGA | N109: AEMA | P109: Email Emits message' AEMA SEOC Request ALNG Provide LNO to Mobile and Baldwin Cty EMAs. Report to County EOC
B110: 40301 | C110: 0.33333333 | D110: 41400.335 | E110: Email | F110: simcell-SEOC | G110: AEMA | H110: J35 | I110: SASO | K110: SASO Request | L110: EMITS | M110: RFA | N110: AEMA | P110: Email Emits message' AEMA SEOC Request ALNG Provide SASO to MAFB
B111: 40301 | C111: 0.33333333 | D111: 41400.335 | E111: Email | F111: simcell-SEOC | G111: AEMA | H111: J35 | I111: SEOC Log Cell | K111: SEOC Log Cell Request | L111: EMITS | M111: RFA | N111: AEMA | P111: Email Emits message' AEMA SEOC Request ALNG Provide SEOC Log Cell to Clanton Al.
B112: 40301 | C112: 0.35416667 | D112: 41400.354 | E112: Phone | F112: simcell-citizen | G112: citizen | H112: Message Center | I112: MVC/ Fatality | K112: Report of Accident | L112: Phone | M112: SA | N112: White Cell | O112: JOC | P112: Citizen: I am a retired ARNG member and I just say one of your Humvee's run a stop sign and hit a mini van, and flipped it and it ran off the road. I didn't see anyone get out of either vehicle. I have called 911, just thought you guys wanted to know.
D113: 41400.358 | K113: Payroll | L113: Email | M113: NGA | N113: White Cell | O113: USPFO/State Comptroller | P113: BPT coordinate transition of payroll (From state to federal or federal to state status).
D114: 41400.361 | K114: Contract Officer | L114: Email | M114: NGA | N114: White Cell | O114: J4/8 | P114: BPT support forward deployed TFs with contracting officer.
D115: 41400.376 | E115: Email | F115: JIEE | G115: NGB | H115: JOC | I115: Set NGB Conference call up on DCO | K115: SAD Pay | L115: EMail | M115: NGA | N115: White Cell | O115: J1 | P115: Coordinate pay submission and pay dates for soldiers in SAD status (Wireless/LAN).
B116: 40301 | C116: 0.375 | D116: 41400.376 | E116: Phone | F116: simcell_LNO | G116: SEOC/LNO | H116: J35 | I116: Contra Flow | K116: Contract Transition | L116: Email | M116: NGA | N116: White Cell JTF-Tarpon | O116: USPFO/State Comptroller | P116: BPT coordinate transition of contracts (From state to federal or federal to state status).
D117: 41400.377 | E117: Email | F117: NGB | G117: NGB | H117: JOC | I117: Set up event and Share with NGB | K117: FEMA Deployment | L117: EMITS or Email | M117: SA | N117: AEMA | P117: FEMA Region JFO ERT-A will deploy to AEMA on 18 May about 1200, FEMA Region 9 DCO will serve as JFO-AL DCO
D118: 41400.378 | E118: JIEE | F118: JIEE | G118: NGB | H118: JOC | I118: Does the JOC need a JET or PARRT | K118: Request for JET | L118: JIEE | M118: SA | N118: NGB-JOC
B119: 40301 | D119: 41400.378 | K119: State Emergency Operations Center (SEOC (AL)) and activated at Level 1 | L119: EMITS or Email | M119: SA | N119: AEMA White Cell | P119: The State Emergency Response Team (SERT) is recalled to the State Emergency Operations Center (SEOC (AL)) and activated at Level 1 effective 0900 6 May 2013.
B120: 40301 | D120: 41400.381 | K120: AEMA recommends voluntary evacuation of Baldwin and Mobile counties. | L120: EMITS or Email | M120: SA | N120: AEMA | P120: AEMA recommends voluntary evacuation of Baldwin and Mobile counties. Voluntary evacuations recommended for citizens living in mobile homes for the following counties: Washington, Clarke, Monroe, Conecuh, Escambia, Covington, Geneva, and Houston.
B121: 40301 | D121: 41400.381 | K121: JFHQ activates JTF-South (FTUS) Primary Staff (LNO's)and local units for possible support | L121: EMAIL | M121: SA | N121: White Cell JTF-Tarpon | P121: JFHQ activates JTF-South (FTUS) Primary Staff (LNO's)and local units for possible support
B122: 40301 | D122: 41400.383 | I122: EMAC | K122: Army National Guard CAT requests Alabama review resources available IOT support MSNG 3X UH60. | M122: NGA | N122: NGB-JOC | P122: Army National Guard CAT requests Alabama review resources available IOT support MSNG 3X UH60.
B123: 40301 | D123: 41400.384 | K123: BPT establish LSA | L123: EMITS or Email | M123: NGA | N123: AEMA | P123: BPT establish LSA Brookley Field, Mobile, requires 20 PAX, 24hrs operations duration of support TBD.
B124: 40301 | D124: 41400.385 | K124: BPT establish and staff 15 PODs | L124: EMITS or Email | M124: NGA | N124: AEMA | P124: BPT establish and staff 15 PODs at Mobile and Baldwin counties
B125: 40301 | D125: 41400.385 | K125: Provide support to SERT (AL)LOG Chief in SEOC (AL) | L125: EMITS or Email | M125: NGA | N125: AEMA | P125: Provide support to SERT (AL)LOG Chief in SEOC (AL)
B126: 40301 | D126: 41400.386 | K126: Stage & BPT deploy 2 SAR teams to Mobile and Baldwin County EOC locations. | L126: EMITS or Email | M126: NGA | N126: AEMA | P126: Stage & BPT deploy 2 SAR teams consisting of 4ea 5tons 16 PAX to Mobile and Baldwin County EOC locations. POC will be Mr. Evens and Mr Raines
B127: 40301 | D127: 41400.387 | K127: White Cell White Cell JTF-Tarpon gets notification of pending activation | L127: EMITS or Email | M127: SA | N127: White Cell | O127: White Cell White Cell JTF-Tarpon | P127: TF South gets notification of pending activation
B128: 40301 | D128: 41400.387 | K128: Provide meteorological services to SEOC (AL) | L128: EMITS or Email | N128: AEMA | P128: Provide meteorological services to SEOC (AL)
B129: 40301 | D129: 41400.388 | J129: 9 | K129: Increase in Limit for TF GPC Cardholders | L129: EMITS or Email | M129: NGA | N129: White Cell | O129: J4/8 | P129: Request Increase in Single Purchase Limit for TF GPC Cardholders from NGB-PARC.
B130: 40301 | D130: 41400.389 | K130: BPT support Aviation assets to assist with SAR | L130: EMITS or Email | N130: White Cell | O130: JOC | P130: BPT support Aviation assets to assist with SAR
B131: 40301 | D131: 41400.39 | K131: FEMA Update | L131: EMITS or Email | M131: SA | N131: AEMA | P131: FEMA Region JFO ERT-A will deploy to AEMA on 4 May about 1200, FEMA Region 9 DCO will serve as JFO-AL DCO
B132: 40301 | D132: 41400.39 | K132: MISSION | L132: EMITS or Email | M132: NGA | N132: White Cell JTF-Tarpon | P132: Deploy SERT (AL)LNOs to Mobile and Baldwin counties NLT 4 May 1800.
B133: 40301 | D133: 41400.391 | K133: BPT | L133: EMITS or Email | M133: NGA | N133: AEMA | P133: BPT to provide airlift of Gov and his key staff for aerial assessment on or about 6 May 10
B134: 40301 | D134: 41400.392 | K134: BPT provide Comms to affected areas EOCs | L134: EMITS or Email | M134: NGA | N134: AEMA | P134: BPT provide Comms to affected areas EOCs
B135: 40301 | D135: 41400.392 | K135: BPT to provide 3000 Soldiers for security operations in South and Central Alabama | L135: EMITS or Email | M135: NGA | N135: AEMA | P135: BPT to provide 3000 Security personnel security operations in South and Central Alabama; locations TBD. Request units be self sustaining.
B136: 40301 | D136: 41400.393 | K136: USPFO Pre-Position | M136: RFA | N136: White Cell | O136: J4 | P136: USPFO - ADP requests a 30 KW generator to be positioned at the USPFO building to maintain computer connectivity for AL Nat Guard.
B137: 40301 | D137: 41400.394 | K137: BPT provide Engineer assets for re-entry and debris operations in affected counties. | L137: EMITS or Email | M137: NGA | N137: AEMA | P137: BPT provide Engineer assets for re-entry and debris operations in affected counties.
B138: 40301 | D138: 41400.394 | I138: CONTRA FLOW | K138: DOT through AEMA requests information on availability of 100 soldiers and 50 vehicles for assistance in implementing the I-65 Lane Reversal Contingency Plan. | L138: EMITS or Email | M138: RFI | N138: AEMA | P138: DOT through AEMA requests information on availability of 100 soldiers and 50 vehicles for assistance in implementing the I-65 Lane Reversal Contingency Plan.
B139: 40301 | D139: 41400.395 | K139: AEMA Teleconference | L139: EMITS or Email | M139: SA | N139: AEMA | P139: AEMA Teleconference
B140: 40301 | C140: 41400.382 | D140: 41400.382 | E140: JIEE or Email | F140: ARNG CAT | H140: JOC | I140: EMAC | K140: Army National Guard CAT requests Alabama review resources available, specifically UH 60/CH 47 BN and BDE level multipurpose purpose task forces. | L140: EMITS or Email | N140: NGB-JOC | P140: Army National Guard CAT requests Alabama review resources available, specifically UH 60/CH 47 BN and BDE level multipurpose purpose task forces.
...

Sheet Backup
A1: Hurricane Scenario
A2: Master Scenario Events List (MSEL)
A3: MSEL NUMBER | B3: DATE | C3: INJECT DTG | D3: SUBJECT | E3: INJECT MODE | F3: SEND FROM (Simulated) | G3: INJECTED BY | H3: SEND TO | I3: STORYLINE/THREAD | J3: ESF | K3: DESCRIPTION | L3: EXPECTED ACTION | M3: NOTES/REMARKS | N3: IMPLEMENTER (Actual Narrative) | O3: BACKGROUND INFORMATION | P3: Inject Author

Sheet PRINT_SMALL
A1: MSEL # | B1: STATUS | C1: DTG | D1: SUBJECT | E1: INJECT MODE: / SEND FROM: / INJECTED BY: / SEND TO: | F1: STORYLINE / DESCRIPTION / NOTES & REMARKS / BACKGROUND INFO | G1: IMPLEMENTER | H1: EXPECTED ACTIONS | I1: AUTHOR
A2: ='Excercise - Al '!A2 -> 1 | B2: Ready to Inject | C2: ='Excercise - Al '!E2 -> 40298.208 | D2: =IF('Excercise - Al '!F2<>0,'Excercise - Al '!F2,"") -> 31st CHEM BDE - Notifies select staff | E2: =IF('Excercise - Al '!G2<>"","MODE: "&'Excercise - Al '!G2,"")&IF('Excercise - Al '!H2<>""," FROM: "&'Excercise - Al '!H2,"")&IF('Excercise - Al '!I2<>""," INJECTED BY: "&'Excercise - Al '!I2,"")&IF('Excercise - Al '!J2<>""," SEND TO: "&'Excercise - Al '!J2,"") -> MODE: Not Injected | F2: =IF('Excercise - Al '!K2<>"","STORYLINE: "&'Excercise - Al '!K2,"")&IF('Excercise - Al '!M2<>""," DESCRIPTION: "&'Excercise - Al '!M2,"")&IF('Excercise - Al '!O2<>""," NOTES/REMARKS: "&'Excercise - Al '!O2,"")&IF('Excercise - Al '!Q2<>""," BACKGROUND INFO: "&'Excercise - Al '!Q2,"") | G2: =IF('Excercise - Al '!P2<>"","IMPLEMENTER: "&'Excercise - Al '!P2,"") | H2: =IF('Excercise - Al '!N2<>"","EXPECTED ACTIONS: "&'Excercise - Al '!N2,"") | I2: ='Excercise - Al '!R2 -> Napier
A3: ='Excercise - Al '!A3 -> 2 | C3: ='Excercise - Al '!E3 -> 40299.167 | D3: =IF('Excercise - Al '!F3<>0,'Excercise - Al '!F3,"") -> INFO | E3: =IF('Excercise - Al '!G3<>"","MODE: "&'Excercise - Al '!G3,"")&IF('Excercise - Al '!H3<>""," FROM: "&'Excercise - Al '!H3,"")&IF('Excercise - Al '!I3<>""," INJECTED BY: "&'Excercise - Al '!I3,"")&IF('Excercise - Al '!J3<>""," SEND TO: "&'Excercise - Al '!J3,"") -> MODE: Email FROM: Simcell - National Hurricane Center INJECTED BY: KEANE SEND TO: JOC, All | F3: =IF('Excercise - Al '!K3<>"","STORYLINE: "&'Excercise - Al '!K3,"")&IF('Excercise - Al '!M3<>""," DESCRIPTION: "&'Excercise - Al '!M3,"")&IF('Excercise - Al '!O3<>""," NOTES/REMARKS: "&'Excercise - Al '!O3,"")&IF('Excercise - Al '!Q3<>""," BACKGROUND INFO: "&'Excercise - Al '!Q3,"") -> STORYLINE: Tropical Depression One Forms DESCRIPTION: Tropical Depression One Forms | G3: =IF('Excercise - Al '!P3<>"","IMPLEMENTER: "&'Excercise - Al '!P3,"") -> IMPLEMENTER: On 01 May, 0400 HRS CDT, The National Hurricane Center issues Tropical Depression Advisory "One". Current Location 14.5 N 74.1 W Max Sustained Wind 30mph | H3: =IF('Excercise - Al '!N3<>"","EXPECTED ACTIONS: "&'Excercise - Al '!N3,"") | I3: ='Excercise - Al '!R3 -> Keane
A4: ='Excercise - Al '!A4 -> 3 | C4: ='Excercise - Al '!E4 -> 40299.208 | D4: =IF('Excercise - Al '!F4<>0,'Excercise - Al '!F4,"") -> 31st CHEM BDE - Telecon with unit CDRs and issue verbal WARNO | E4: =IF('Excercise - Al '!G4<>"","MODE: "&'Excercise - Al '!G4,"")&IF('Excercise - Al '!H4<>""," FROM: "&'Excercise - Al '!H4,"")&IF('Excercise - Al '!I4<>""," INJECTED BY: "&'Excercise - Al '!I4,"")&IF('Excercise - Al '!J4<>""," SEND TO: "&'Excercise - Al '!J4,"") -> MODE: Not Injected | F4: =IF('Excercise - Al '!K4<>"","STORYLINE: "&'Excercise - Al '!K4,"")&IF('Excercise - Al '!M4<>""," DESCRIPTION: "&'Excercise - Al '!M4,"")&IF('Excercise - Al '!O4<>""," NOTES/REMARKS: "&'Excercise - Al '!O4,"")&IF('Excercise - Al '!Q4<>""," BACKGROUND INFO: "&'Excercise - Al '!Q4,"") | G4: =IF('Excercise - Al '!P4<>"","IMPLEMENTER: "&'Excercise - Al '!P4,"") | H4: =IF('Excercise - Al '!N4<>"","EXPECTED ACTIONS: "&'Excercise - Al '!N4,"") | I4: ='Excercise - Al '!R4 -> Napier
A5: ='Excercise - Al '!A5 -> 4 | C5: ='Excercise - Al '!E5 -> 40299.208 | D5: =IF('Excercise - Al '!F5<>0,'Excercise - Al '!F5,"") -> 31st CHEM BDE - Test alert roster of key personnel and for the 1165th and 690th | E5: =IF('Excercise - Al '!G5<>"","MODE: "&'Excercise - Al '!G5,"")&IF('Excercise - Al '!H5<>""," FROM: "&'Excercise - Al '!H5,"")&IF('Excercise - Al '!I5<>""," INJECTED BY: "&'Excercise - Al '!I5,"")&IF('Excercise - Al '!J5<>""," SEND TO: "&'Excercise - Al '!J5,"") -> MODE: Not Injected | F5: =IF('Excercise - Al '!K5<>"","STORYLINE: "&'Excercise - Al '!K5,"")&IF('Excercise - Al '!M5<>""," DESCRIPTION: "&'Excercise - Al '!M5,"")&IF('Excercise - Al '!O5<>""," NOTES/REMARKS: "&'Excercise - Al '!O5,"")&IF('Excercise - Al '!Q5<>""," BACKGROUND INFO: "&'Excercise - Al '!Q5,"") | G5: =IF('Excercise - Al '!P5<>"","IMPLEMENTER: "&'Excercise - Al '!P5,"") | H5: =IF('Excercise - Al '!N5<>"","EXPECTED ACTIONS: "&'Excercise - Al '!N5,"") | I5: ='Excercise - Al '!R5 -> Napier
A6: ='Excercise - Al '!A6 -> 5 | C6: ='Excercise - Al '!E6 -> 40299.417 | D6: =IF('Excercise - Al '!F6<>0,'Excercise - Al '!F6,"") -> INFO | E6: =IF('Excercise - Al '!G6<>"","MODE: "&'Excercise - Al '!G6,"")&IF('Excercise - Al '!H6<>""," FROM: "&'Excercise - Al '!H6,"")&IF('Excercise - Al '!I6<>""," INJECTED BY: "&'Excercise - Al '!I6,"")&IF('Excercise - Al '!J6<>""," SEND TO: "&'Excercise - Al '!J6,"") -> MODE: Email FROM: Simcell - National Hurricane Center INJECTED BY: KEANE SEND TO: JOC, All | F6: =IF('Excercise - Al '!K6<>"","STORYLINE: "&'Excercise - Al '!K6,"")&IF('Excercise - Al '!M6<>""," DESCRIPTION: "&'Excercise - Al '!M6,"")&IF('Excercise - Al '!O6<>""," NOTES/REMARKS: "&'Excercise - Al '!O6,"")&IF('Excercise - Al '!Q6<>""," BACKGROUND INFO: "&'Excercise - Al '!Q6,"") -> STORYLINE: Tropical Storm Al Update 2 DESCRIPTION: Tropical Storm Al Update 2 | G6: =IF('Excercise - Al '!P6<>"","IMPLEMENTER: "&'Excercise - Al '!P6,"") -> IMPLEMENTER: ...FIRST TROPICAL STORM OF THE SEASON...AL NEARS THE COAST OF NICARAGUA... SUMMARY OF 1100 AM EDT...1500 UTC...INFORMATION ----------------------------------------------- LOCATION...14.9N 74.9W ABOUT 220 MILES...354 KM...SOUTH SOUTHEAST OF KINGSTON JAMAICA ABOUT 280 MILES...450 KM...NORTH OF BARRANQUILLA COLUMBIA ABOUT 510 MILES...820 KM...NORTHEAST OF PANAMA CITY PANAMA MAXIMUM SUSTAINED WINDS...45 MPH...39 KM/HR PRESENT MOVEMENT...WNW OR 276 DEGREES AT 15 MPH...24 KM/HR MINIMUM CENTRAL PRESSURE...999 MB...29.5 INCHES | H6: =IF('Excercise - Al '!N6<>"","EXPECTED ACTIONS: "&'Excercise - Al '!N6,"") | I6: ='Excercise - Al '!R6 -> Keane
A7: ='Excercise - Al '!A7 -> 6 | C7: ='Excercise - Al '!E7 -> 40299.667 | D7: =IF('Excercise - Al '!F7<>0,'Excercise - Al '!F7,"") -> INFO | E7: =IF('Excercise - Al '!G7<>"","MODE: "&'Excercise - Al '!G7,"")&IF('Excercise - Al '!H7<>""," FROM: "&'Excercise - Al '!H7,"")&IF('Excercise - Al '!I7<>""," INJECTED BY: "&'Excercise - Al '!I7,"")&IF('Excercise - Al '!J7<>""," SEND TO: "&'Excercise - Al '!J7,"") -> MODE: Email FROM: Simcell - National Hurricane Center INJECTED BY: KEANE SEND TO: JOC, All | F7: =IF('Excercise - Al '!K7<>"","STORYLINE: "&'Excercise - Al '!K7,"")&IF('Excercise - Al '!M7<>""," DESCRIPTION: "&'Excercise - Al '!M7,"")&IF('Excercise - Al '!O7<>""," NOTES/REMARKS: "&'Excercise - Al '!O7,"")&IF('Excercise - Al '!Q7<>""," BACKGROUND INFO: "&'Excercise - Al '!Q7,"") -> STORYLINE: Tropical Storm Al Update 3 DESCRIPTION: Tropical Storm Al Update 3 | G7: =IF('Excercise - Al '!P7<>"","IMPLEMENTER: "&'Excercise - Al '!P7,"") -> IMPLEMENTER: ...TROPICAL STORM AL STRENGTHENS AS IT NEARS THE COAST OF NICARAGUA... SUMMARY OF 1700 AM EDT...2100 UTC...INFORMATION ----------------------------------------------- LOCATION...15.30 N 76.20 W ABOUT 188 MILES...303 KM...167 DEGREES...SOUTH-SOUTHEAST OF KINGSTON JAMAICA ABOUT 312 MILES...502 KM...343 DEGREES...NORTH-NORTHWEST OF BARRANQUILLA COLUMBIA MAXIMUM SUSTAINED WINDS...60 MPH...99 KM/HR PRESENT MOVEMENT...WESTERLY OR 275 DEGREES AT 10 MPH...16 KM/HR MINIMUM CENTRAL PRESSURE...997 MB...29.44 INCHES | H7: =IF('Excercise - Al '!N7<>"","EXPECTED ACTIONS: "&'Excercise - Al '!N7,"") | I7: ='Excercise - Al '!R7 -> Keane
A8: ='Excercise - Al '!A8 -> 7 | C8: ='Excercise - Al '!E8 -> 40299.917 | D8: =IF('Excercise - Al '!F8<>0,'Excercise - Al '!F8,"") -> INFO | E8: =IF('Excercise - Al '!G8<>"","MODE: "&'Excercise - Al '!G8,"")&IF('Excercise - Al '!H8<>""," FROM: "&'Excercise - Al '!H8,"")&IF('Excercise - Al '!I8<>""," INJECTED BY: "&'Excercise - Al '!I8,"")&IF('Excercise - Al '!J8<>""," SEND TO: "&'Excercise - Al '!J8,"") -> MODE: Email FROM: Simcell - National Hurricane Center INJECTED BY: KEANE SEND TO: JOC, All | F8: =IF('Excercise - Al '!K8<>"","STORYLINE: "&'Excercise - Al '!K8,"")&IF('Excercise - Al '!M8<>""," DESCRIPTION: "&'Excercise - Al '!M8,"")&IF('Excercise - Al '!O8<>""," NOTES/REMARKS: "&'Excercise - Al '!O8,"")&IF('Excercise - Al '!Q8<>""," BACKGROUND INFO: "&'Excercise - Al '!Q8,"") -> STORYLINE: Tropical Storm Al Update 4 DESCRIPTION: Tropical Storm Al Update 4 | G8: =IF('Excercise - Al '!P8<>"","IMPLEMENTER: "&'Excercise - Al '!P8,"") -> IMPLEMENTER: ...AL BECOMES A HURRICANE AS IT NEARS THE NORTH COAST OF NICARAGUA... SUMMARY OF 1100 PM EDT...0300 UTC...INFORMATION ----------------------------------------------- LOCATION...15.50 N 77.10 W ABOUT 172 MILES...277 KM...SOUTH SOUTHEAST OF KINGSTON JAMAICA ABOUT 366 MILES...589 KM...NORTH-NORTHWEST OF CARTAGENA COLUMBIA MAXIMUM SUSTAINED WINDS...85 MPH...137 KM/HR PRESENT MOVEMENT...WNW OR 284 DEGREES AT 12 MPH...19 KM/HR MINIMUM CENTRAL PRESSURE...980 MB...28.94 INCHES | H8: =IF('Excercise - Al '!N8<>"","EXPECTED ACTIONS: "&'Excercise - Al '!N8,"") | I8: ='Excercise - Al '!R8 -> Keane
A9: ='Excercise - Al '!A9 -> 8 | C9: ='Excercise - Al '!E9 -> 40300.167 | D9: =IF('Excercise - Al '!F9<>0,'Excercise - Al '!F9,"") -> INFO | E9: =IF('Excercise - Al '!G9<>"","MODE: "&'Excercise - Al '!G9,"")&IF('Excercise - Al '!H9<>""," FROM: "&'Excercise - Al '!H9,"")&IF('Excercise - Al '!I9<>""," INJECTED BY: "&'Excercise - Al '!I9,"")&IF('Excercise - Al '!J9<>""," SEND TO: "&'Excercise - Al '!J9,"") -> MODE: Email FROM: Simcell - National Hurricane Center INJECTED BY: KEANE SEND TO: JOC, All | F9: =IF('Excercise - Al '!K9<>"","STORYLINE: "&'Excercise - Al '!K9,"")&IF('Excercise - Al '!M9<>""," DESCRIPTION: "&'Excercise - Al '!M9,"")&IF('Excercise - Al '!O9<>""," NOTES/REMARKS: "&'Excercise - Al '!O9,"")&IF('Excercise - Al '!Q9<>""," BACKGROUND INFO: "&'Excercise - Al '!Q9,"") -> STORYLINE: Tropical Storm Al Update 4 DESCRIPTION: Tropical Storm Al Update 4 | G9: =IF('Excercise - Al '!P9<>"","IMPLEMENTER: "&'Excercise - Al '!P9,"") -> IMPLEMENTER: ...AL REMAINS A CAT 1 HURRICANE MOVING EAST TO WEST...SOUTH OF JAMAICA...GAINING STRENGTH... SUMMARY OF 0500 AM EDT...0900 UTC...INFORMATION ----------------------------------------------- LOCATION...15.90 N 78.10 W ABOUT 159 MILES... 255 KM... SOUTH NEGRIL JAMAICA ABOUT 317 MILES... 510 KM... SOUTHEAST OF GEORGE TOWN CAYMAN ISLANDS ABOUT 375 MILES... 604 KM... EAST-NORTHEAST OF PUERTO CABEZAS NICARAGUA MAXIMUM SUSTAINED WINDS...85 MPH...137 KM/HR PRESENT MOVEMENT...WNW OR 282 DEGREES AT 12 MPH...19 KM/HR MINIMUM CENTRAL PRESSURE...979 MB...28.91 INCHES | H9: =IF('Excercise - Al '!N9<>"","EXPECTED ACTIONS: "&'Excercise - Al '!N9,"") | I9: ='Excercise - Al '!R9 -> Keane
A10: ='Excercise - Al '!A10 -> 9 | C10: ='Excercise - Al '!E10 -> 40300.208 | D10: =IF('Excercise - Al '!F10<>0,'Excercise - Al '!F10,"") -> INFO | E10: =IF('Excercise - Al '!G10<>"","MODE: "&'Excercise - Al '!G10,"")&IF('Excercise - Al '!H10<>""," FROM: "&'Excercise - Al '!H10,"")&IF('Excercise - Al '!I10<>""," INJECTED BY: "&'Excercise - Al '!I10,"")&IF('Excercise - Al '!J10<>""," SEND TO: "&'Excercise - Al '!J10,"") | F10: =IF('Excercise - Al '!K10<>"","STORYLINE: "&'Excercise - Al '!K10,"")&IF('Excercise - Al '!M10<>""," DESCRIPTION: "&'Excercise - Al '!M10,"")&IF('Excercise - Al '!O10<>""," NOTES/REMARKS: "&'Excercise - Al '!O10,"")&IF('Excercise - Al '!Q10<>""," BACKGROUND INFO: "&'Excercise - Al '!Q10,"") -> STORYLINE: Tropical Storm Al Update 5 DESCRIPTION: Tropical Storm Al Update 5 | G10: =IF('Excercise - Al '!P10<>"","IMPLEMENTER: "&'Excercise - Al '!P10,"") | H10: =IF('Excercise - Al '!N10<>"","EXPECTED ACTIONS: "&'Excercise - Al '!N10,"") | I10: ='Excercise - Al '!R10 -> Jenne
A11: ='Excercise - Al '!A11 -> 10 | C11: ='Excercise - Al '!E11 -> 40300.417 | D11: =IF('Excercise - Al '!F11<>0,'Excercise - Al '!F11,"") -> INFO | E11: =IF('Excercise - Al '!G11<>"","MODE: "&'Excercise - Al '!G11,"")&IF('Excercise - Al '!H11<>""," FROM: "&'Excercise - Al '!H11,"")&IF('Excercise - Al '!I11<>""," INJECTED BY: "&'Excercise - Al '!I11,"")&IF('Excercise - Al '!J11<>""," SEND TO: "&'Excercise - Al '!J11,"") -> MODE: Email FROM: Simcell - National Hurricane Center INJECTED BY: KEANE SEND TO: JOC, All | F11: =IF('Excercise - Al '!K11<>"","STORYLINE: "&'Excercise - Al '!K11,"")&IF('Excercise - Al '!M11<>""," DESCRIPTION: "&'Excercise - Al '!M11,"")&IF('Excercise - Al '!O11<>""," NOTES/REMARKS: "&'Excercise - Al '!O11,"")&IF('Excercise - Al '!Q11<>""," BACKGROUND INFO: "&'Excercise - Al '!Q11,"") -> STORYLINE: Tropical Storm Al Update 6 DESCRIPTION: Tropical Storm Al Update 6 | G11: =IF('Excercise - Al '!P11<>"","IMPLEMENTER: "&'Excercise - Al '!P11,"") -> IMPLEMENTER: ... HURRICANE AL TRACKS TOWARD THE YUCATAN... SUMMARY OF 1100 AM EDT...0900 UTC...INFORMATION ----------------------------------------------- LOCATION...16.3N 79.0W ABOUT 257 MILES... 321 KM...SOUTH SOUTHEAST OF GEORGE TOWN CAYMAN ISLANDS ABOUT 137 MILES... 222 KM...SOUTH OF NEGRIL JAMAICA MAXIMUM SUSTAINED WINDS...85 MPH...137 KM/HR PRESENT MOVEMENT...WNW OR 284 DEGREES AT 12 MPH...19 KM/HR MINIMUM CENTRAL PRESSURE...977 MB...28.85 INCHES | H11: =IF('Excercise - Al '!N11<>"","EXPECTED ACTIONS: "&'Excercise - Al '!N11,"") | I11: ='Excercise - Al '!R11 -> Keane
A12: ='Excercise - Al '!A12 -> 11 | C12: ='Excercise - Al '!E12 -> 40300.5 | D12: =IF('Excercise - Al '!F12<>0,'Excercise - Al '!F12,"") -> RFI | E12: =IF('Excercise - Al '!G12<>"","MODE: "&'Excercise - Al '!G12,"")&IF('Excercise - Al '!H12<>""," FROM: "&'Excercise - Al '!H12,"")&IF('Excercise - Al '!I12<>""," INJECTED BY: "&'Excercise - Al '!I12,"")&IF('Excercise - Al '!J12<>""," SEND TO: "&'Excercise - Al '!J12,"") -> MODE: Email FROM: Each Task Force INJECTED BY: TF S2 SEND TO: JOC, J2 | F12: =IF('Excercise - Al '!K12<>"","STORYLINE: "&'Excercise - Al '!K12,"")&IF('Excercise - Al '!M12<>""," DESCRIPTION: "&'Excercise - Al '!M12,"")&IF('Excercise - Al '!O12<>""," NOTES/REMARKS: "&'Excercise - Al '!O12,"")&IF('Excercise - Al '!Q12<>""," BACKGROUND INFO: "&'Excercise - Al '!Q12,"") -> DESCRIPTION: Weather Update/Storm Track | G12: =IF('Excercise - Al '!P12<>"","IMPLEMENTER: "&'Excercise - Al '!P12,"") -> IMPLEMENTER: Weather RFI from Task Force to J2 | H12: =IF('Excercise - Al '!N12<>"","EXPECTED ACTIONS: "&'Excercise - Al '!N12,"") -> EXPECTED ACTIONS: J2 Provides latest Weather and Storm Track to the TFs | I12: ='Excercise - Al '!R12 -> Houlton
A13: ='Excercise - Al '!A13 -> 12 | C13: ='Excercise - Al '!E13 -> 40300.667 | D13: =IF('Excercise - Al '!F13<>0,'Excercise - Al '!F13,"") -> INFO | E13: =IF('Excercise - Al '!G13<>"","MODE: "&'Excercise - Al '!G13,"")&IF('Excercise - Al '!H13<>""," FROM: "&'Excercise - Al '!H13,"")&IF('Excercise - Al '!I13<>""," INJECTED BY: "&'Excercise - Al '!I13,"")&IF('Excercise - Al '!J13<>""," SEND TO: "&'Excercise - Al '!J13,"") -> MODE: Email FROM: Simcell - National Hurricane Center INJECTED BY: KEANE SEND TO: JOC, All | F13: =IF('Excercise - Al '!K13<>"","STORYLINE: "&'Excercise - Al '!K13,"")&IF('Excercise - Al '!M13<>""," DESCRIPTION: "&'Excercise - Al '!M13,"")&IF('Excercise - Al '!O13<>""," NOTES/REMARKS: "&'Excercise - Al '!O13,"")&IF('Excercise - Al '!Q13<>""," BACKGROUND INFO: "&'Excercise - Al '!Q13,"") -> STORYLINE: Tropical Storm Al Update 7 DESCRIPTION: Tropical Storm Al Update 7 | G13: =IF('Excercise - Al '!P13<>"","IMPLEMENTER: "&'Excercise - Al '!P13,"") -> IMPLEMENTER: ... HURRICANE AL TRACKS TOWARD THE YUCATAN...AS A CATEGORY TWO HURRICANE... SUMMARY OF 0500 AM EDT...0900 UTC...INFORMATION ----------------------------------------------- LOCATION...16.7N 80.0W ABOUT 199 MILES... 321 KM...SOUTH SOUTHEAST OF GEORGE TOWN CAYMAN ISLANDS ABOUT 150 MILES... 241 KM...NEGRIL JAMAICA MAXIMUM SUSTAINED WINDS...105 MPH...169 KM/HR PRESENT MOVEMENT...WNW OR 292 DEGREES AT 12 MPH...19 KM/HR MINIMUM CENTRAL PRESSURE...968 MB...28.59 INCHES | H13: =IF('Excercise - Al '!N13<>"","EXPECTED ACTIONS: "&'Excercise - Al '!N13,"") | I13: ='Excercise - Al '!R13 -> Keane
A14: ='Excercise - Al '!A14 -> 13 | C14: ='Excercise - Al '!E14 -> 40300.917 | D14: =IF('Excercise - Al '!F14<>0,'Excercise - Al '!F14,"") -> INFO | E14: =IF('Excercise - Al '!G14<>"","MODE: "&'Excercise - Al '!G14,"")&IF('Excercise - Al '!H14<>""," FROM: "&'Excercise - Al '!H14,"")&IF('Excercise - Al '!I14<>""," INJECTED BY: "&'Excercise - Al '!I14,"")&IF('Excercise - Al '!J14<>""," SEND TO: "&'Excercise - Al '!J14,"") -> MODE: Email FROM: Simcell - National Hurricane Center INJECTED BY: KEANE SEND TO: JOC, All | F14: =IF('Excercise - Al '!K14<>"","STORYLINE: "&'Excercise - Al '!K14,"")&IF('Excercise - Al '!M14<>""," DESCRIPTION: "&'Excercise - Al '!M14,"")&IF('Excercise - Al '!O14<>""," NOTES/REMARKS: "&'Excercise - Al '!O14,"")&IF('Excercise - Al '!Q14<>""," BACKGROUND INFO: "&'Excercise - Al '!Q14,"") -> STORYLINE: Tropical Storm Al Update 8 DESCRIPTION: Tropical Storm Al Update 8 | G14: =IF('Excercise - Al '!P14<>"","IMPLEMENTER: "&'Excercise - Al '!P14,"") -> IMPLEMENTER: ... HURRICANE AL GAINS MOMENTUM AS A CATEGORY TWO HURRICANE... SUMMARY OF 2300 PM EDT...0300 UTC...INFORMATION ----------------------------------------------- LOCATION...17.1N 80.9W ABOUT 184 MILES...296 KM...WEST-SOUTHWEST NEGRIL JAMAICA ABOUT 154 MILES...249 KM...SOUTH-SOUTHEAST OF GEORGE TOWN CAYMAN ISLANDS MAXIMUM SUSTAINED WINDS...105 MPH...169 KM/HR PRESENT MOVEMENT...WNW OR 292 DEGREES AT 15 MPH...24 KM/HR MINIMUM CENTRAL PRESSURE...963 MB...28.44 INCHES | H14: =IF('Excercise - Al '!N14<>"","EXPECTED ACTIONS: "&'Excercise - Al '!N14,"") | I14: ='Excercise - Al '!R14 -> Keane
... A240: ='Excercise - Al '!A240 -> 239 | C240: ='Excercise - Al '!E240 -> 40304.75 | D240: =IF('Excercise - Al '!F240<>0,'Excercise - Al '!F240,"") | E240: =IF('Excercise - Al '!G240<>"","MODE: "&'Excercise - Al '!G240,"")&IF('Excercise - Al '!H240<>""," FROM: "&'Excercise - Al '!H240,"")&IF('Excercise - Al '!I240<>""," INJECTED BY: "&'Excercise - Al '!I240,"")&IF('Excercise - Al '!J240<>""," SEND TO: "&'Excercise - Al '!J240,"") | F240: =IF('Excercise - Al '!K240<>"","STORYLINE: "&'Excercise - Al '!K240,"")&IF('Excercise - Al '!M240<>""," DESCRIPTION: "&'Excercise - Al '!M240,"")&IF('Excercise - Al '!O240<>""," NOTES/REMARKS: "&'Excercise - Al '!O240,"")&IF('Excercise - Al '!Q240<>""," BACKGROUND INFO: "&'Excercise - Al '!Q240,"") -> STORYLINE: Transport food, water, and ice from LSA Brookley Field to LSA's located in Mobile and Baldwin Counties. Commodities to move are 400 Pallets of MRE, 500 Pallets of water, 100 Pallets of Ice, this will be a LOG Push mission daily. Mission duration is TBD. | G240: =IF('Excercise - Al '!P240<>"","IMPLEMENTER: "&'Excercise - Al '!P240,"") -> IMPLEMENTER: Transport food, water, and ice from LSA Brookley Field to LSA's located in Mobile and Baldwin Counties. Commodities to move are 400 Pallets of MRE, 500 Pallets of water, 100 Pallets of Ice, this will be a LOG Push mission daily. Mission duration is TBD. | H240: =IF('Excercise - Al '!N240<>"","EXPECTED ACTIONS: "&'Excercise - Al '!N240,"") | I240: ='Excercise - Al '!R240 -> 0
