Workbook
Name OLE_LINK1: 'Excercise - Al '!$P$59
Name OLE_LINK1: 'MSEL INFO ONLY'!$O$147

Sheet Excercise - Al 
A1: MSEL NUMBER | B1: DATE | C1: Time | D1: STATUS | E1: INJECT DTG | F1: SUBJECT | G1: INJECT MODE | H1: SEND FROM (Simulated) | I1: INJECTED BY | J1: SEND TO | K1: STORYLINE/THREAD | L1: ESF | M1: DESCRIPTION | N1: EXPECTED ACTION | O1: NOTES/REMARKS | P1: IMPLEMENTER (Actual Narrative) | Q1: BACKGROUND INFORMATION | R1: Inject Author
A2: 1 | D2: Omitted | E2: 40298.208 | F2: 31st CHEM BDE - Notifies select staff | G2: Not Injected | R2: Napier
A3: 2 | B3: 40299 | C3: 40299.167 | D3: Injected | E3: 40299.167 | F3: INFO | G3: Email | H3: Simcell - National Hurricane Center | I3: KEANE | J3: JOC, All | K3: Tropical Depression One Forms | L3: 5, 15 | M3: Tropical Depression One Forms | P3: On 01 May, 0400 HRS CDT, The National Hurricane Center issues Tropical Depression Advisory "One". Current Location 14.5 N 74.1 W Max Sustained Wind 30mph | R3: Keane
A4: 3 | D4: Omitted | E4: 40299.208 | F4: 31st CHEM BDE - Telecon with unit CDRs and issue verbal WARNO | G4: Not Injected | R4: Napier
A5: 4 | D5: Omitted | E5: 40299.208 | F5: 31st CHEM BDE - Test alert roster of key personnel and for the 1165th and 690th | G5: Not Injected | R5: Napier
A6: 5 | B6: 40299 | C6: 40299.417 | D6: Injected | E6: 40299.417 | F6: INFO | G6: Email | H6: Simcell - National Hurricane Center | I6: KEANE | J6: JOC, All | K6: Tropical Storm Al Update 2 | L6: 5, 15 | M6: Tropical Storm Al Update 2 | P6: ...FIRST TROPICAL STORM OF THE SEASON...AL NEARS THE COAST OF NICARAGUA... SUMMARY OF 1100 AM EDT...1500 UTC...INFORMATION ----------------------------------------------- LOCATION...14.9N 74.9W ABOUT 220 MILES...354 KM...SOUTH SOUTHEAST OF KINGSTON JAMAICA ABOUT 280 MILES...450 KM...NORTH OF BARRANQUILLA COLUMBIA ABOUT 510 MILES...820 KM...NORTHEAST OF PANAMA CITY PANAMA MAXIMUM SUSTAINED WINDS...45 MPH...39 KM/HR PRESENT MOVEMENT...WNW OR 276 DEGREES AT 15 MPH...24 KM/HR MINIMUM CENTRAL PRESSURE...999 MB...29.5 INCHES | R6: Keane
A7: 6 | B7: 40299 | C7: 40299.667 | D7: Injected | E7: 40299.667 | F7: INFO | G7: Email | H7: Simcell - National Hurricane Center | I7: KEANE | J7: JOC, All | K7: Tropical Storm Al Update 3 | L7: 5, 15 | M7: Tropical Storm Al Update 3 | P7: ...TROPICAL STORM AL STRENGTHENS AS IT NEARS THE COAST OF NICARAGUA... SUMMARY OF 1700 AM EDT...2100 UTC...INFORMATION ----------------------------------------------- LOCATION...15.30 N 76.20 W ABOUT 188 MILES...303 KM...167 DEGREES...SOUTH-SOUTHEAST OF KINGSTON JAMAICA ABOUT 312 MILES...502 KM...343 DEGREES...NORTH-NORTHWEST OF BARRANQUILLA COLUMBIA MAXIMUM SUSTAINED WINDS...60 MPH...99 KM/HR PRESENT MOVEMENT...WESTERLY OR 275 DEGREES AT 10 MPH...16 KM/HR MINIMUM CENTRAL PRESSURE...997 MB...29.44 INCHES | R7: Keane
A8: 7 | B8: 40299 | C8: 40299.917 | D8: Injected | E8: 40299.917 | F8: INFO | G8: Email | H8: Simcell - National Hurricane Center | I8: KEANE | J8: JOC, All | K8: Tropical Storm Al Update 4 | L8: 5, 15 | M8: Tropical Storm Al Update 4 | P8: ...AL BECOMES A HURRICANE AS IT NEARS THE NORTH COAST OF NICARAGUA... SUMMARY OF 1100 PM EDT...0300 UTC...INFORMATION ----------------------------------------------- LOCATION...15.50 N 77.10 W ABOUT 172 MILES...277 KM...SOUTH SOUTHEAST OF KINGSTON JAMAICA ABOUT 366 MILES...589 KM...NORTH-NORTHWEST OF CARTAGENA COLUMBIA MAXIMUM SUSTAINED WINDS...85 MPH...137 KM/HR PRESENT MOVEMENT...WNW OR 284 DEGREES AT 12 MPH...19 KM/HR MINIMUM CENTRAL PRESSURE...980 MB...28.94 INCHES | R8: Keane
A9: 8 | B9: 40300 | C9: 40300.167 | D9: Injected | E9: 40300.167 | F9: INFO | G9: Email | H9: Simcell - National Hurricane Center | I9: KEANE | J9: JOC, All | K9: Tropical Storm Al Update 4 | L9: 5, 15 | M9: Tropical Storm Al Update 4 | P9: ...AL REMAINS A CAT 1 HURRICANE MOVING EAST TO WEST...SOUTH OF JAMAICA...GAINING STRENGTH... SUMMARY OF 0500 AM EDT...0900 UTC...INFORMATION ----------------------------------------------- LOCATION...15.90 N 78.10 W ABOUT 159 MILES... 255 KM... SOUTH NEGRIL JAMAICA ABOUT 317 MILES... 510 KM... SOUTHEAST OF GEORGE TOWN CAYMAN ISLANDS ABOUT 375 MILES... 604 KM... EAST-NORTHEAST OF PUERTO CABEZAS NICARAGUA MAXIMUM SUSTAINED WINDS...85 MPH...137 KM/HR PRESENT MOVEMENT...WNW OR 282 DEGREES AT 12 MPH...19 KM/HR MINIMUM CENTRAL PRESSURE...979 MB...28.91 INCHES | R9: Keane
A10: 9 | B10: 40300.208 | C10: 40300.208 | D10: Injected | E10: 40300.208 | F10: INFO | K10: Tropical Storm Al Update 5 | M10: Tropical Storm Al Update 5 | R10: Jenne
A11: 10 | B11: 40300 | C11: 40300.417 | D11: Injected | E11: 40300.417 | F11: INFO | G11: Email | H11: Simcell - National Hurricane Center | I11: KEANE | J11: JOC, All | K11: Tropical Storm Al Update 6 | L11: 5, 15 | M11: Tropical Storm Al Update 6 | P11: ... HURRICANE AL TRACKS TOWARD THE YUCATAN... SUMMARY OF 1100 AM EDT...0900 UTC...INFORMATION ----------------------------------------------- LOCATION...16.3N 79.0W ABOUT 257 MILES... 321 KM...SOUTH SOUTHEAST OF GEORGE TOWN CAYMAN ISLANDS ABOUT 137 MILES... 222 KM...SOUTH OF NEGRIL JAMAICA MAXIMUM SUSTAINED WINDS...85 MPH...137 KM/HR PRESENT MOVEMENT...WNW OR 284 DEGREES AT 12 MPH...19 KM/HR MINIMUM CENTRAL PRESSURE...977 MB...28.85 INCHES | R11: Keane
A12: 11 | B12: 40300 | C12: 0.5 | D12: Injected | E12: 40300.5 | F12: RFI | G12: Email | H12: Each Task Force | I12: TF S2 | J12: JOC, J2 | M12: Weather Update/Storm Track | N12: J2 Provides latest Weather and Storm Track to the TFs | P12: Weather RFI from Task Force to J2 | R12: Houlton
A13: 12 | B13: 40300 | C13: 40300.667 | D13: Injected | E13: 40300.667 | F13: INFO | G13: Email | H13: Simcell - National Hurricane Center | I13: KEANE | J13: JOC, All | K13: Tropical Storm Al Update 7 | L13: 5, 15 | M13: Tropical Storm Al Update 7 | P13: ... HURRICANE AL TRACKS TOWARD THE YUCATAN...AS A CATEGORY TWO HURRICANE... SUMMARY OF 0500 AM EDT...0900 UTC...INFORMATION ----------------------------------------------- LOCATION...16.7N 80.0W ABOUT 199 MILES... 321 KM...SOUTH SOUTHEAST OF GEORGE TOWN CAYMAN ISLANDS ABOUT 150 MILES... 241 KM...NEGRIL JAMAICA MAXIMUM SUSTAINED WINDS...105 MPH...169 KM/HR PRESENT MOVEMENT...WNW OR 292 DEGREES AT 12 MPH...19 KM/HR MINIMUM CENTRAL PRESSURE...968 MB...28.59 INCHES | R13: Keane
A14: 13 | B14: 40300 | C14: 40300.917 | D14: Injected | E14: 40300.917 | F14: INFO | G14: Email | H14: Simcell - National Hurricane Center | I14: KEANE | J14: JOC, All | K14: Tropical Storm Al Update 8 | L14: 5, 15 | M14: Tropical Storm Al Update 8 | P14: ... HURRICANE AL GAINS MOMENTUM AS A CATEGORY TWO HURRICANE... SUMMARY OF 2300 PM EDT...0300 UTC...INFORMATION ----------------------------------------------- LOCATION...17.1N 80.9W ABOUT 184 MILES...296 KM...WEST-SOUTHWEST NEGRIL JAMAICA ABOUT 154 MILES...249 KM...SOUTH-SOUTHEAST OF GEORGE TOWN CAYMAN ISLANDS MAXIMUM SUSTAINED WINDS...105 MPH...169 KM/HR PRESENT MOVEMENT...WNW OR 292 DEGREES AT 15 MPH...24 KM/HR MINIMUM CENTRAL PRESSURE...963 MB...28.44 INCHES | R14: Keane
A15: 14 | B15: 40301 | C15: 40301.167 | D15: Injected | E15: 40301.167 | F15: INFO | G15: Email | H15: Simcell - National Hurricane Center | I15: KEANE | J15: JOC, All | K15: Tropical Storm Al Update 9 | L15: 5, 15 | M15: Tropical Storm Al Update 9 | P15: ... HURRICANE AL CONTINUES ON A TRACK TOWARD COZUMEL... SUMMARY OF 0500 AM EDT...0900 UTC...INFORMATION ----------------------------------------------- LOCATION...17.7N 82.1W ABOUT 250 MILES...401 KM...WEST-SOUTHWEST NEGRIL JAMAICA ABOUT 154 MILES...249 KM...SOUTH-SOUTHEAST OF GEORGE TOWN CAYMAN ISLANDS MAXIMUM SUSTAINED WINDS...105 MPH...169 KM/HR PRESENT MOVEMENT...WNW OR 294 DEGREES AT 14 MPH...23 KM/HR MINIMUM CENTRAL PRESSURE...960 MB...28.35 INCHES | R15: Keane
A16: 15 | D16: Omitted | E16: 40301.208 | F16: 31st CHEM BDE - Stands up the CAC and begins tracking storm | G16: Not Injected | R16: Napier
A17: 16 | D17: Omitted | E17: 40301.208 | F17: 31st CHEM BDE - Alert 1165th & 690th O/O Activate | G17: Not Injected | R17: Napier
A18: 17 | B18: 40301 | C18: 40301.292 | D18: Injected | E18: 40301.292 | F18: LNO to SEOC | G18: EMITS | H18: SEOC LNO | I18: SEOC LNO | J18: JOC | M18: NG LNO's to State EOC by 0700 4 May 10 | P18: NG LNO's to State EOC by 0700 4 May 10 | R18: Keane
A19: 18 | B19: 40301.312 | C19: 40301.312 | D19: Injected | E19: 40301.313 | F19: RFI - Holman Prison | G19: Phone Call | H19: JTF-S White Cell (subordinnate commander) | I19: TOMBERLIN | J19: 226 MEB | K19: Holman Prison Blues | M19: Company commander requests guidance on soldier | O19: Inject called in on schedule. Monitoring of JOC message traffic indicates that information apparently did not make it outside of 226 MEB. | P19: Company commander has a soldier who is a prison guard at Holman Prison. Soldier states that he has been directed to remain at prison and not to report to Guard. Indicates rumors of potential inmate takeover and mass escape during hurricane. Soldier/guard states that inmates are apparently planning a takeover while hurricane is in progress, followed by mass escape. There are indications that they may receive external support by an affilated gang. Soldier/guard states that prison officials are discussing requesting security assistance from Guard. | R19: Jenne
A20: 19 | D20: Injected | E20: 40301.314 | F20: MISSION | G20: EMITS | H20: AEMA ESF 5 | I20: SEOC LNO | J20: JOC | L20: 5 | M20: Provide meteorological services to SEOC (AL) | P20: Provide meteorological services to SEOC (AL) | R20: Keane
A21: 20 | D21: Injected | E21: 40301.333 | F21: AEMA Contacts JOC | G21: Phone | H21: AEMA | I21: ALAN PETTY | J21: AL J3 | M21: AEMA Director contacts AL TAG/J3 to discuss hurricane response planning/operations. | P21: AEMA Director contacts AL TAG/J3 to discuss hurricane response planning/operations. AEMA Director states that they are making preliminary plans for possible Alex response operations. Suggests issuing warning orders to MACOMs for potential in-state response operations. | R21: Keane
A22: 21 | B22: 40301 | C22: 0.33333333 | D22: Injected | E22: 40301.335 | F22: MISSION - SASO | G22: Email | H22: simcell-SEOC | I22: SEOC LNO | J22: J35 | K22: SASO | M22: SASO Request | N22: EOC contacts 122CSG | P22: Email Emits message' AEMA SEOC Request ALNG Provide SASO to MAFB | R22: Messer
A23: 22 | B23: 40301 | C23: 0.33333333 | D23: Injected | E23: 40301.335 | F23: MISSION - SEOC LOG CELL | G23: Email | H23: simcell-SEOC | I23: SEOC LNO | J23: J35 | K23: SEOC Log Cell | M23: SEOC Log Cell Request | N23: EOC contacts 122CSG | P23: Email Emits message' AEMA SEOC Request ALNG Provide SEOC Log Cell to Clanton Al. | R23: Messer
A24: 23 | B24: 40301 | C24: 0.35416667 | D24: Deferred | E24: 40301.354 | F24: INFO | G24: Phone | H24: simcell-citizen | I24: HOWARD | J24: Message Center | K24: MVC/ Fatality | M24: Report of Accident | N24: EOC RFIs MACOMS regarding report of accident/vehicles on road | P24: Citizen: I am a retired ARNG member and I just say one of your Humvee's run a stop sign and hit a mini van, and flipped it and it ran off the road. I didn't see anyone get out of either vehicle. I have called 911, just thought you guys wanted to know. | R24: Messer
A25: 24 | D25: Injected | E25: 40301.376 | F25: INFO | G25: Email | H25: JIEE | I25: KAHL | J25: JOC | K25: Set NGB Conference call up on DCO | R25: Kahl
A26: 25 | B26: 40301 | C26: 0.375 | D26: Injected | E26: 40301.376 | F26: INFO | G26: Phone | H26: simcell_LNO | I26: SEOC LNO | J26: J35 | K26: Contra Flow | M26: Informal message from LNO | N26: WARNO to 62nd Troop Command | P26: I just heard that the Governor is probably going to order contra flow on I 65 sometimes tomorrow morning. I will let you know more as I hear it. | R26: Messer
A27: 26 | D27: Injected | E27: 40301.377 | F27: INFO | G27: Email | H27: NGB | I27: KAHL | J27: JOC | K27: Set up event and Share with NGB | R27: Kahl
A28: 27 | D28: Injected | E28: 40301.378 | F28: RFI | G28: JIEE | H28: JIEE | I28: KAHL | J28: JOC | K28: Does the JOC need a JET or PARRT | M28: Request for JET | R28: Kahl
A29: 28 | B29: 40301 | D29: Injected | E29: 40301.378 | F29: INFO | I29: SEOC LNO | M29: The State Emergency Response Team (SERT) is recalled to the State Emergency Operations Center (SEOC (AL)) and activated at Level 1 effective 0900 3 May 2010. | P29: The State Emergency Response Team (SERT) is recalled to the State Emergency Operations Center (SEOC (AL)) and activated at Level 1 effective 0900 3 May 2010. | R29: Keane
A30: 29 | B30: 40301 | C30: 40301.375 | D30: Injected | E30: 40301.379 | F30: MISSION | G30: Email | H30: USPFO, S&S | I30: DENNIS | J30: JOC J4 | M30: USPFO Warehouse to push 20 pallets of MREs and 20 pallets of bottled water to Ft McClellan, AL (pre-positioning for soldier support). | P30: USPFO Warehouse to push 20 pallets of MREs and 20 pallets of bottled water to Ft McClellan, AL (pre-positioning for soldier support). | Q30: USPFO Warehouse SOP, SA only | R30: Keane
A31: 30 | B31: 40301 | D31: Injected | E31: 40301.381 | F31: INFO - Evacuation | I31: SEOC LNO | M31: AEMA recommends voluntary evacuation of Baldwin and Mobile counties. | P31: AEMA recommends voluntary evacuation of Baldwin and Mobile counties. Voluntary evacuations recommended for citizens living in mobile homes for the following counties: Washington, Clarke, Monroe, Conecuh, Escambia, Covington, Geneva, and Houston. | R31: Keane
A32: 31 | B32: 40301 | D32: Injected | E32: 40301.381 | F32: INFO | I32: KEANE | M32: JFHQ activates JTF-South (FTUS) Primary Staff (LNO's)and local units for possible support | P32: JFHQ activates JTF-South (FTUS) Primary Staff (LNO's)and local units for possible support | R32: Keane
A33: 32 | D33: Injected | E33: 40301.385 | F33: INFO | G33: Email | H33: MED DET | I33: BENTON | J33: SPS MED & J1 | K33: 1 Soldier found HIV positive in the 226th MEB after a periodic health assessment (PHA) performed by the medical detachment, from 10-11 Apr 10 SRP in Mobile. | M33: 1 Soldier found HIV positive in the 226th MEB after a periodic health assessment (PHA) performed by the medical detachment, from 10-11 Apr 10 SRP in Mobile. | P33: 1 Soldier found HIV positive in the 226th MEB after a periodic health assessment (PHA) performed by the medical detachment, from 10-11 Apr 10 SRP in Mobile. | R33: Benton
A34: 33 | D34: Injected | E34: 40301.385 | I34: P. MCDONALD | J34: JOC MSG CTR | K34: Army National Guard CAT requests Alabama review resources available IOT support FL with 1X Med Trk Co and 1X DS/GS Maint Co. | O34: At 0939 hours LTC Small , ARNG CAT, contacted MAJ Davis @ 334.273.3547 after several attempts to other numbers provided by SGT Vice. He is to advise. At 1114 hours, MAJ Davis advises TAG-AL requests a 48 hour hold before approving the EMAC request. | P34: Army National Guard CAT requests Alabama review resources available IOT support FL with 1X Med Trk Co and 1X DS/GS Maint Co. | R34: McDonald
A35: 34 | D35: Injected | E35: 40301.386 | F35: INFO | G35: Telephone Call | H35: STATE SURGEON | I35: BENTON | J35: SPS MED | K35: All JTFs must perform a medical readiness screening of the potential personnel being considered for DSCA support mission to ensure that they have a current PHA, Dental Exam, Routine Adult Immunizations (to include H1N1) and have no outstanding noon-deployable medical conditions. Submit status report back to SPS.MED NLT 1200 4 May 10. | M35: All JTFs must perform a medical readiness screening of the potential personnel being considered for DSCA support mission to ensure that they have a current PHA, Dental Exam, Routine Adult Immunizations (to include H1N1) and have no outstanding noon-deployable medical conditions. Submit status report back to SPS.MED NLT 1200 4 May 10. | P35: All JTFs must perform a medical readiness screening of the potential personnel being considered for DSCA support mission to ensure that they have a current PHA, Dental Exam, Routine Adult Immunizations (to include H1N1) and have no outstanding noon-deployable medical conditions. Submit status report back to SPS.MED NLT 1200 4 May 10. | R35: Benton
A36: 35 | B36: 40301 | D36: Injected | E36: 40301.387 | F36: INFO | I36: SEOC LNO | M36: TF South gets notification of pending activation | P36: TF South gets notification of pending activation | R36: Keane
A37: 36 | D37: Injected | E37: 40301.389 | I37: P. MCDONALD | K37: Army National Guard CAT requests Alabama review resources available IOT support TX with 1x Light/Medium Truck Company and 1x POL Co. | O37: At 0923 hours LTC Small, ARNG CAT, contacted MSG Woodall @ 334.213.7748 and he took message and would have someone return our call. At 1007 hours called MSG Woodall and advised no one had called. Left another message. At 1114 hours MAJ Davis, AL JOC returned call and received request. Will advise. At 1715 hours, MAJ Davis advises TAG will concur with request but requests a 48 hours delay for the EMAC request. | P37: Army National Guard CAT requests Alabama review resources available IOT support TX with 1x Light/Medium Truck Company and 1x POL Co. | R37: McDonald
A38: 37 | B38: 40301 | D38: Injected | E38: 40301.39 | F38: INFO | I38: SEOC LNO | M38: FEMA Region JFO ERT-A will deploy to AEMA on 4 May about 1200, FEMA Region 9 DCO will serve as JFO-AL DCO | P38: FEMA Region JFO ERT-A will deploy to AEMA on 4 May about 1200, FEMA Region 9 DCO will serve as JFO-AL DCO | R38: Keane
A39: 38 | B39: 40301 | D39: Injected | E39: 40301.39 | F39: MISSION | I39: SEOC LNO | M39: Deploy SERT (AL) LNOs to Mobile and Baldwin counties NLT 4 May 1800. | P39: Deploy SERT (AL)LNOs to Mobile and Baldwin counties NLT 4 May 1800. | R39: Keane
A40: 39 | D40: Omitted | E40: 40301.392 | K40: Army National Guard CAT requests Alabama review resources available IOT support Tx and LA with unfilled EMAC Requests. | P40: Army National Guard CAT requests Alabama review resources available IOT support Tx and LA with unfilled EMAC Requests.
A41: 40 | B41: 40301 | D41: Injected | E41: 40301.395 | F41: INFO | I41: KEANE | M41: AEMA Teleconference | P41: AEMA Teleconference | R41: Keane
A42: 41 | B42: 40301 | C42: 40301.375 | D42: Injected | E42: 40301.396 | F42: MISSION | G42: Email | H42: USPFO, S&S | I42: SEOC LNO | J42: JOC J4 | M42: USPFO Warehouse to push 20 pallets of MREs and 20 pallets of bottled water to Ft Whiting, Mobile, AL (pre-positioning for soldier support). | P42: USPFO Warehouse to push 20 pallets of MREs and 20 pallets of bottled water to Ft Whiting, Mobile, AL (pre-positioning for soldier support). | Q42: USPFO Warehouse SOP, SA only | R42: Keane
A43: 42 | B43: 40301 | C43: 40301.382 | D43: Injected | E43: 40301.406 | F43: RFI | G43: JIEE or Email | H43: ARNG CAT | I43: KAHL | J43: JOC | K43: EMAC | M43: Army National Guard CAT requests Alabama review resources available, specifically UH 60/CH 47 BN and BDE level multipurpose purpose task forces. | P43: Army National Guard CAT requests Alabama review resources available, specifically UH 60/CH 47 BN and BDE level multipurpose purpose task forces. | R43: Keane
A44: 43 | B44: 40301 | C44: 0.41666667 | D44: Deferred | E44: 40301.417 | F44: INFO | G44: Email | H44: simcell-SEOC | I44: SEOC LNO | J44: MSG CTR/TAG | M44: The Governor of Alabama has issued a declaration of emergency for Mobile, Baldwin and surrounding counties. | N44: MSG CTR informs TAG/Sr. Staff/JOC | P44: The Governor of Alabama has issued a declaration of emergency for Mobile, Baldwin and surrounding counties. | R44: Messer
A45: 44 | D45: Omitted | E45: 40301.417 | F45: 31st CHEM BDE - Dispatch LNO to Montgomery | G45: Not Injected | R45: Napier
A46: 45 | B46: 40301 | C46: 40301.417 | D46: Injected | E46: 40301.417 | F46: INFO | G46: Email | H46: Simcell - National Hurricane Center | I46: KEANE | J46: JOC, All | K46: Tropical Storm Al Update 10 | L46: 5, 15 | M46: Tropical Storm Al Update 10 | P46: ... HURRICANE AL MOVING NORTHWESTWARD...APPROACHING THE YUCATAN PENINSULA TOMORROW... SUMMARY OF 1100 AM EDT...1500 UTC...INFORMATION ----------------------------------------------- LOCATION...18.3N 83.1W ABOUT 129 MILES...208 KM...SOUTHWEST OF GEORGE TOWN CAYMAN ISLANDS ABOUT 290 MILES...466 KM...SOUTHEAST OF COZUMEL MEXICO ABOUT 339 MILES...545 KM...EAST-NORTHEAST OF BELIZE CITY BELIZE MAXIMUM SUSTAINED WINDS...120 MPH...193 KM/HR PRESENT MOVEMENT...WNW OR 303 DEGREES AT 14 MPH...23 KM/HR MINIMUM CENTRAL PRESSURE...956 MB...28.23 INCHES | R46: Keane
A47: 46 | B47: 40301 | D47: Injected | E47: 40301.438 | F47: RFI | G47: Phone | I47: SEOC LNO/P MCDONALD | J47: JOC-AVN | K47: EMAC | M47: Mississippi Issues EMAC Request for Aviation support, 3x UH60's for SAR | O47: At 1107 hours, MAJ Johns, MS-JOC- Battle Capt, contacted CW5 Fontenot, AVN, he said to send EMAC request ALNG can support 3 UH60 out of Mobile because they are having to relocate due to impeding storm. | P47: Mississippi Issues EMAC Request for Aviation support, 3x UH60's for SAR | R47: McDonald
A48: 47 | D48: Injected | E48: 40301.448 | F48: MISSION | G48: Email | I48: TOMBERLIN | M48: Request 900 MREs, 100 cots, and 100 blankets to be prepositioned at Fort Whiting, Mobile AL. | P48: Request 900 MREs, 100 cots, and 100 blankets to be preposition at Fort Whiting, Mobile AL. | R48: Therman
A49: 48 | B49: 40301 | D49: Ready to Inject | E49: 40301.458 | F49: RFI | I49: SEOC LNO | K49: EMAC | M49: Army National Guard CAT requests Alabama review resources available IOT support MSNG 3X UH60. | P49: Army National Guard CAT requests Alabama review resources available IOT support MSNG 3X UH60. | R49: Keane
A50: 49 | B50: 40301 | D50: Ready to Inject | E50: 40301.479 | F50: MISSION - BPT | I50: SEOC LNO | M50: BPT establish LSA | P50: BPT establish ONE LSA Brookley Field, Mobile, requires 20 PAX, 24hrs operations duration of support TBD. | R50: Keane
A51: 50 | B51: 40301 | D51: Ready to Inject | E51: 40301.499 | F51: MISSION - BPT | I51: SEOC LNO | M51: BPT establish and staff 15 PODs at Mobile and Baldwin counties | P51: BPT establish and staff 15 PODs at Mobile and Baldwin counties | R51: Keane
A52: 51 | B52: 40301 | C52: 0.5 | D52: Deleted | E52: 40301.5 | F52: RFI | G52: Email | H52: Each Task Force | I52: TF S2 | J52: JOC, J2 | M52: Weather Update/Storm Track | N52: J2 Provides latest Weather and Storm Track to the TFs | P52: Weather RFI from Task Force to J2 | R52: Houlton
A53: 52 | B53: 40301 | D53: Ready to Inject | E53: 40301.521 | F53: MISSION | I53: SEOC LNO | M53: Provide support to SERT (AL)LOG Chief in SEOC (AL) | P53: Provide support to SERT (AL)LOG Chief in SEOC (AL) | R53: Keane
A54: 53 | B54: 40301 | D54: Ready to Inject | E54: 40301.542 | F54: MISSION - BPT | I54: SEOC LNO | M54: Stage & BPT deploy 2 SAR teams to Mobile and Baldwin County EOC locations. | P54: Stage & BPT deploy 2 SAR teams consisting of 4ea 5tons 16 PAX to Mobile and Baldwin County EOC locations. POC will be Mr. Evens and Mr Raines | R54: Keane
A55: 54 | D55: Injected | E55: 40301.542 | F55: RFI | G55: Email | I55: HICKS | K55: CHAPLAIN & UMT ACTIIVITIES | N55: Deny request & cover with chaplain from another unit | P55: A Battalion commander reports his unit chaplain cannot be contacted. As a replacement he wants to bring with the unit his civilian pastor to do the chaplain work | R55: Hicks
A56: 55 | B56: 40301 | D56: Injected | E56: 40301.583 | F56: MISSION | I56: SEOC LNO | L56: 9 | M56: Provide SAR Planner to SEOC (AL) ESF 9 | P56: Provide SAR Planner to SEOC (AL) ESF 9 | R56: Keane
A57: 56 | B57: 40301 | D57: Injected | E57: 40301.604 | F57: MISSION - BPT | I57: SEOC LNO | M57: BPT support Aviation assets to assist with SAR | P57: BPT support Aviation assets to assist with SAR | R57: Keane
A58: 57 | B58: 40301 | D58: Injected | E58: 40301.625 | F58: MISSION - BPT | I58: SEOC LNO | M58: BPT to provide airlift of Gov and his key staff for aerial assessment on or about 6 May 10 | P58: BPT to provide airlift of Gov and his key staff for aerial assessment on or about 6 May 10 | R58: Keane
A59: 58 | D59: Injected | E59: 40301.625 | K59: Due to the impending threat of Hurricane Al the Governor's of Texas, LA, MS has ordered a state of emergency for all of the respective Coastal areas. Officials ordered a mandatory evacuation of visitors and special needs clients beginning at 9 a.m. Tuesday, 4 May. A phased evacuation of all residents begins Tuesday, May 4, 2010 at 8 a.m. | P59: Due to the impending threat of Hurricane Al the Governor's of Texas, LA, MS has ordered a state of emergency for all of the respective Coastal areas. Officials ordered a mandatory evacuation of visitors and special needs clients beginning at 9 a.m. Tuesday, 4 May. A phased evacuation of all residents begins Tuesday, May 4, 2010 at 8 a.m.
A60: 59 | B60: 40301 | D60: Injected | E60: 40301.646 | F60: MISSION - BPT | I60: SEOC LNO | M60: BPT provide Comms to affected areas EOCs | P60: BPT provide Comms to affected areas EOCs | R60: Keane
A61: 60 | B61: 40301 | D61: Injected | E61: 40301.656 | F61: MISSION - BPT | I61: SEOC LNO | M61: BPT to provide 3000 Soldiers for security operations in South and Central Alabama | P61: BPT to provide 3000 Soldiers for security operations in South and Central Alabama; locations TBD. Request units be self sustaining. | R61: Keane
A62: 61 | B62: 40301 | C62: 40301.667 | D62: Injected | E62: 40301.667 | F62: INFO | G62: Email | H62: Simcell - National Hurricane Center | I62: KEANE | J62: JOC, All | K62: Tropical Storm Al Update 11 | L62: 5, 15 | M62: Tropical Storm Al Update 11 | P62: ... HURRICANE AL MOVING NORTHWESTWARD...APPROACHING THE YUCATAN PENINSULA TOMORROW... SUMMARY OF 1700 AM EDT...2100 UTC...INFORMATION ----------------------------------------------- LOCATION...19.0N 84.1W ABOUT 179 MILES...288 KM...SOUTHWEST OF GEORGE TOWN CAYMAN ISLANDS ABOUT 229 MILES...367 KM...SOUTHEAST OF COZUMEL MEXICO ABOUT 287 MILES...463 KM...EAST-NORTHEAST OF BELIZE CITY BELIZE MAXIMUM SUSTAINED WINDS...120 MPH...193 KM/HR PRESENT MOVEMENT...WNW OR 307 DEGREES AT 15 MPH...24 KM/HR MINIMUM CENTRAL PRESSURE...953 MB...28.14 INCHES | R62: Keane
A63: 62 | B63: 40301 | D63: Injected | E63: 40301.688 | I63: DENNIS | M63: USPFO - ADP requests a 30 KW generator to be positioned at the USPFO building to maintain computer connectivity for AL Nat Guard. | P63: USPFO - ADP requests a 30 KW generator to be positioned at the USPFO building to maintain computer connectivity for AL Nat Guard. | R63: Keane
A64: 63 | B64: 40301.698 | C64: 40301.698 | D64: Injected | E64: 40301.698 | F64: INFO - Holman Prison | G64: E-Mail | H64: SEOC Department of Public Safety LNO | I64: SEOC LNO | J64: JOC Message Center | K64: Holman Prison Blues | M64: Gulf Shores police report confrontation with motorcycle gang | P64: Gulf Shores Police Department reports confrontation with twelve members of out-of-state outlaw motorcycle club(Road Vermin M/C) who were drunk and disorderly at a local bar. Gulf Shores Police indicate that incident was handled with no need for arrests. They also indicate that an unusually large number of outlaw M/C members are present in the Gulf Coast area, particularly prior to a hurricane. They indicate that the Road Vermin M/C has known alliances with white supremacist organizations. | R64: Jenne
A65: 64 | B65: 40301 | D65: Injected | E65: 40301.708 | F65: MISSION - BPT | I65: SEOC LNO | M65: BPT provide Engineer assets for re-entry and debris operations in affected counties. | P65: BPT provide Engineer assets for re-entry and debris operations in affected counties. | R65: Keane
A66: 65 | D66: Injected | E66: 40301.708 | F66: RFI | G66: Phone | I66: P. MCDONALD | K66: The Department of Defense has ordered an evacuation of personnel, aircraft and ships from the Gulf of Mexico. Some DoD aircraft will be made available to state and federal agencies until 24 hours from estimated landfall. | O66: At 1711 hours, CAPT Manson, DCSOPS NAVOPS, advised MAJ Davis, AL-JOC that DoD assets were available through DCO. | P66: The Department of Defense has ordered an evacuation of personnel, aircraft and ships from the Gulf of Mexico. Some DoD aircraft will be made available to state and federal agencies until 24 hours from estimated landfall. | R66: McDonald
A67: 66 | B67: 40301 | D67: Injected | E67: 40301.728 | F67: RFI | I67: SEOC LNO | K67: CONTRA FLOW | M67: DOT through AEMA requests information on availability of 100 soldiers and 50 vehicles for assistance in implementing the I-65 Lane Reversal Contingency Plan. | P67: DOT through AEMA requests information on availability of 100 soldiers and 50 vehicles for assistance in implementing the I-65 Lane Reversal Contingency Plan. | R67: Keane
A68: 67 | B68: 40301.771 | C68: 40301.771 | D68: Injected | E68: 40301.771 | F68: INFO - Holman Prison | G68: Phone Call | H68: SEOC LNO | I68: SEOC LNO | J68: J-3 | K68: Holman Prison Blues | M68: SEOC LNO calls in "heads up" notification that DOC may request Guard assistance at Holman Prison | P68: SEOC LNO describes developing situation at Holman Prison in which inmates apparently intend to riot and take over the prison during the hurricane, followed by a mass escape assisted by external forces. LNO states that DOC and State Troopers are confident that they can manage the situation inside the prison, to include the perimeter, but are concerned about the potential of external forces attempting to force their way in to breach fences and other security measures. Are considering asking for "two to three platoons" of MPs or infantry to establish extra security perimeter. | R68: Jenne
A69: 68 | B69: 40301 | C69: 0.625 | D69: Injected | E69: 40301.875 | F69: INFO | G69: email | H69: simcell-SEOC | I69: SEOC LNO | J69: J35 | K69: CONTRA FLOW | M69: Governor orders Contra-flow of I-65 | N69: FRAGO to 62nd Troop Command | P69: Governor oders I 65 contra flow operations conducted beginning 0800 4 May 2010 | R69: Messer
A70: 69 | D70: Injected | E70: 40301.913 | F70: INFO - Evacuation | G70: Email | I70: SEOC LNO | K70: EVACUATION | M70: Governor Orders Evacuation of Dauphin Island and Gulf Shores | P70: Governor Orders Evacuation of Dauphin Island and Gulf Shores | R70: Keane
A71: 70 | B71: 40301 | C71: 40301.917 | D71: Injected | E71: 40301.917 | F71: INFO | G71: Email | H71: Simcell - National Hurricane Center | I71: KEANE | J71: JOC, All | K71: Tropical Storm Al Update 12 | L71: 5, 15 | M71: Tropical Storm Al Update 12 | P71: ... HURRICANE AL THREATENS CANCUN... SUMMARY OF 2300 AM EDT...0300 UTC...INFORMATION ----------------------------------------------- LOCATION...19.9N 85.1W ABOUT 141 MILES...228 KM...SOUTHWEST OF CANCUN MEXICO ABOUT 245 MILES...395 KM...WEST-SOUTHWEST OF GEORGE TOWN CAYMAN ISLANDS ABOUT 261 MILES...421 KM...NORTHEAST OF BELIZE CITY BELIZE MAXIMUM SUSTAINED WINDS...120 MPH...193 KM/HR PRESENT MOVEMENT...WNW OR 306 DEGREES AT 20 MPH...32 KM/HR MINIMUM CENTRAL PRESSURE...952 MB...28.11 INCHES | R71: Keane
A72: 71 | B72: 40302 | C72: 40302.167 | D72: Injected | E72: 40302.167 | F72: INFO | G72: Email | H72: Simcell - National Hurricane Center | I72: KEANE | J72: JOC, All | K72: Tropical Storm Al Update 13 | L72: 5, 15 | M72: Tropical Storm Al Update 13 | P72: ... HURRICANE AL EYE JUST OFF THE TIP OF THE YUCATAN... SUMMARY OF 0500 AM EDT...0900 UTC...INFORMATION ----------------------------------------------- LOCATION...21.2N 86.2W ABOUT 41 MILES...66 KM...EAST OF CANCUN MEXICO ABOUT 67 MILES...109 KM...NORTHEAST COZUMEL MEXICO ABOUT 94 MILES...152 KM...WEST-SOUTHWEST OF THE WESTERN TIP OF CUBA MAXIMUM SUSTAINED WINDS...105 MPH...168 KM/HR PRESENT MOVEMENT...WNW OR 316 DEGREES AT 12 MPH...19 KM/HR MINIMUM CENTRAL PRESSURE...955 MB...28.20 INCHES | R72: Keane
A73: 72 | D73: Omitted | E73: 40302.167 | F73: 31st CHEM BDE - Staff security requirements for Evac Shelters | G73: Not Injected | R73: Napier
A74: 73 | D74: Omitted | E74: 40302.208 | F74: 31st CHEM BDE - Coordinate w/ JTF-S and establish direct communications with 1165th and 690th | G74: Not Injected | R74: Napier
A75: 74 | D75: Injected | E75: 40302.292 | G75: EMITS | H75: White Cell - AEMA | I75: SEOC LNO | J75: JOC | P75: DOT through AEMA requests resources resources (vehicles and manpower) to staff twenty traffic control points to assist in implementing the I-65 Lane Reversal Contingency Plan. | R75: Keane
A76: 75 | B76: 40302.083 | C76: 40302.083 | D76: Injected | E76: 40302.302 | F76: INFO - Holman Prison | G76: E-Mail | H76: SEOC Department of Public Safety LNO | I76: SEOC LNO | J76: JOC Message Center | K76: Holman Prison Blues | M76: Armored cars stolen in Mobile | P76: Mobile Police Department reports incident where three armored cars were stolen from a Brinks Company parking lot in Mobile. Report states that parking lot guard and vehicle dispatcher were overpowered by five armed men at approximately 0200. Three armored cars (no money or valuables) were taken. Vehicles were equipped with tracking devices, but the tracking devices were disabled shortly after the incident. | R76: Jenne
A77: 76 | D77: Injected | E77: 40302.316 | F77: INFO - KC-135 Crash | I77: JENNE | M77: Initial Report of KC-135 Crash in Birmingham (soldier calls in to report that it is on the news)
A78: 77 | D78: Injected | E78: 40302.319 | F78: INFO - KC-135 Crash | I78: 117TH OPS | M78: Follow-Up Report on KC-135 Crash (from 117th Operations to Air ATAG)
A79: 78 | D79: Injected | E79: 40302.333 | F79: INFO - KC-135 Crash | I79: 117TH OPS | M79: Follow-Up Report on KC-135 Crash (from 117th Operations to Air ATAG) concerning radioactive materials found on aircraft
A80: 79 | D80: Omitted | E80: 40302.333 | F80: 31st CHME BDE - Stands up the CMOC | G80: Not Injected | R80: Napier
A81: 80 | B81: 40302.354 | C81: 40302.354 | D81: Injected | E81: 40302.354 | F81: RFI - Holman Prison | G81: EMITS | H81: SEOC | I81: SEOC LNO | J81: JOC Message Center | K81: Holman Prison Blues | M81: SEOC requests contingency study on providing security assistance at Holman Prison | P81: SEOC requests that Guard conduct a contingency study to determine if they can provide security assistance to Holman Prison at same time hurricane response operations are underway. Potential security assistance requirement is for approximately a company-sized element (preferably MPs or infantry) to establish VCPs, roadblocks and blocking positions on external perimeter to prevent external forces from entering prison compound and providing assistance to prisoners. All Guard operations are anticipated to be external to prison; DOC and State Troopers will manage in-prison and internal security perimeter. Governor states that because of political sensitivity of situation, he wants a detailed briefback on ground tactical plan (via VTC or other means, if necessary) to Directors of DOC and DPS. | R81: Jenne
A82: 81 | D82: Injected | E82: 40302.417 | F82: INFO | G82: Phone | H82: White Cell - JTF South | I82: POLLARD | J82: JTF South | M82: Sgt ……. Vehicle rolled over on interstate in route to armory. He was wearing a seat belt but rolled into ditch and drowned | Q82: SIR should be developed/ NGB notified/ TAG/ PAO/ CCIR tracking established | R82: Kahl
A83: 82 | D83: Injected | E83: 40302.427 | F83: INFO - KC-135 Crash | I83: HOWARD | M83: News media calling concerning KC-135 Crash and radioactive materials
A84: 83 | B84: 40303.396 | C84: 0.39583333 | D84: Injected | E84: 40302.438 | F84: INFO - Train Derailment | G84: Telephone | H84: FTUS NCO manning Grove Hill armory | I84: POLLARD | J84: JTF-S | K84: Grove Hill Train Derailment | M84: Grove Hill soldier reports significant train derailment | N84: JTF-S should pass this information upline to JFHQ JOC. | O84: The entire purpose of ths thread is to determine if the information (which will be received from multiple sources at different levels) is passed up-line to JFHQ JOC, and then subsequently assessed by various J-Staff elements. The location of the train derailment is directly adjacent to US 43, which should be an MSR for moving troops and equipment downrange, so will J-2 and J-4 receive info and advise TAG and units accordingly? | P84: FTUS NCO from Det 1, Co A, 711 BSB is standing by at Grove Hill armory to support hurricane response operations. He reports that a north-bound Norfolk Southern train experienced a serious derailment between Grove Hill and Thomasville (to the north). Clarke County Sheriff's Department and local fire departments are responding. A hazardous materials release is suspected. NCO states that local officials indicate that Grove Hill and surrounding communities will likely be evacuated. He is requesting guidance if evacuation is required. | R84: Jenne
A85: 84 | D85: Injected | E85: 40302.441 | F85: INFO - KC-135 Crash | H85: BFRS | I85: JENNE | M85: Birmingham Fire and Rescue Service isolating KC-135 crash site until radioactive materials can be identified. Requesting Guard assistance.
A86: 85 | B86: 40302.396 | C86: 0.40625 | D86: Injected | E86: 40302.448 | F86: INFO - Train Derailment | G86: Telephone or e-mail | H86: SEOC LNO | I86: SEOC LNO | J86: JOC Chief | K86: Grove Hill Train Derailment | M86: SEOC LNO reports train derailment just north of Grove Hill | N86: JOC Chief should notify TAG and key leaders, pertinent staff personnel and JTFs. | O86: The entire purpose of ths thread is to determine if the information (which will be received from multiple sources at different levels) is passed up-line to JFHQ JOC, and then subsequently assessed by various J-Staff elements. The location of the train derailment is directly adjacent to US 43, which should be an MSR for moving troops and equipment downrange, so will J-2 and J-4 receive info and advise TAG and units accordingly? | P86: SEOC LNO calls JOC Chief with a "heads up" that a Norfolk Southern train has derailed approximately ten miles north of Grove Hill (Clarke County). The train was being "pushed" north to get it out of the hurricane impact area. Derailment involves multiple tank cars of hazardous materials, including chlorine, anhydrous ammonia, and flourine. Local emergency responders are on scene; State Troopers and ADEM are en route. SEOC LNO states that EMA may request technical assistance from the CST. | R86: Jenne
A87: 86 | B87: 40302 | C87: 40302.417 | D87: Injected | E87: 40302.417 | F87: INFO | G87: Email | H87: Simcell - National Hurricane Center | I87: KEANE | J87: JOC, All | K87: Tropical Storm Al Update 14 | L87: 5, 15 | M87: Tropical Storm Al Update 14 | P87: ... HURRICANE AL PASSES NORTH OF CANCUN...ENTERS THE GULF OF MEXICO... SUMMARY OF 1100 AM EDT...1500 UTC...INFORMATION ----------------------------------------------- LOCATION...22.0N 86.8W ABOUT 58 MILES...94 KM...NORTH OF CANCUN MEXICO ABOUT 120 MILES...193 KM...WEST OF THE WESTERN TIP OF CUBA MAXIMUM SUSTAINED WINDS...105 MPH...169 KM/HR PRESENT MOVEMENT...WNW OR 314 DEGREES AT 15 MPH...24 KM/HR MINIMUM CENTRAL PRESSURE...960 MB...28.35 INCHES | R87: Keane
A88: 87 | D88: Injected | E88: 40302.459 | G88: Email | I88: TOMBERLIN | K88: All units activated submit travel vouchers for identified soldiers. | P88: All units activated submit travel vouchers for identified soldiers. | R88: Therman
A89: 88 | D89: Injected | E89: 40302.479 | F89: RFI | G89: Email | I89: DENNIS | M89: Task Force South is requesting a Class A Agent. | P89: Task Force South is requesting a Class A Agent. | R89: Therman
A90: 89 | D90: Injected | E90: 40302.486 | F90: INFO - KC-135 Crash | I90: JENNE | M90: Birmingham Police bomb robot being used to inspect interior of aircraft. Located container with marking (NSN number)
A91: 90 | B91: 40302.396 | C91: 0.44791667 | D91: Injected | E91: 40302.49 | F91: RFI - Train Derailment | G91: EMITS | H91: SEOC WC | I91: SEOC LNO | J91: JOC Message Center | K91: Grove Hill Train Derailment | M91: EMITS Request for Assistance for Train Derailment emergency response | N91: JOC Chief should notify TAG and key leaders, pertinent staff personnel and JTFs. | O91: The entire purpose of ths thread is to determine if the information (which will be received from multiple sources at different levels) is passed up-line to JFHQ JOC, and then subsequently assessed by various J-Staff elements. The location of the train derailment is directly adjacent to US 43, which should be an MSR for moving troops and equipment downrange, so will J-2 and J-4 receive info and advise TAG and units accordingly? | P91: EMITS message requests capability assessment of potential Guard capabilities to assist with train derailment north of Grove Hill. Area, including US 43, is being evacuated. EMA wants to know viability of CST providing hazardous materials assistance. Additionally, EMA wants to determine availability of FLIRS-equipped R/W aircraft to locate "hot spots" in train, to assist in firefighting effort. There is extensive smoke as a result of multiple fires, which is why FLIR is being requested. State Trooper FLIR-equipped aircraft are currently tasked to other activities. | R91: Jenne
A92: 91 | B92: 40302 | C92: 0.45833333 | D92: Injected | E92: 40302.501 | F92: INFO | G92: Phone | H92: GATE GUARD | I92: DONAHUE | J92: MSG CTR | K92: AT/FP | M92: Citizen reports accident at front gate | N92: MSG CTR reports to J3/ who calls 911? | P92: I just witnessed an accident at the gate in which a large truck was hit by a civilian car. What should I do? | R92: Messer
A93: 92 | D93: Injected | E93: 40302.501 | F93: RFI | G93: Email | H93: USPFO | I93: DENNIS | M93: National Guard Bureau is requesting a spreadsheet which capture and track funding costs associated with the hurricane disaster. | P93: National Guard Bureau is requesting a spreadsheet which capture and track funding costs associated with the hurricane disaster. | R93: Therman
A94: 93 | D94: Injected | E94: 40302.521 | F94: INFO - KC-135 Crash | H94: GOVERNOR'S OFFICE | I94: REAGAN | M94: Governor asks TAG to conduct press conference concerning KC-135 crash
A95: 94 | B95: 40302 | C95: 0.5 | D95: Injected | E95: 40302.042 | F95: RFI | G95: Email | I95: TF S2 | J95: JOC, J2 | M95: Weather Update/Storm Track | N95: J2 Provides latest Weather and Storm Track to the TFs | P95: Weather RFI from Task Force to J2 | R95: Houlton
A96: 95 | B96: 40302 | C96: 0.54166667 | D96: Injected | E96: 40302.583 | F96: RFI | G96: Email | I96: MCLEOD | J96: CFMO | K96: Provide information as to what armories are under construction. Specifically in areas of the projected landfall, or planned staging areas. | M96: SA | P96: Provide information as to what armories are under construction. Specifically in areas of the projected landfall, or planned staging areas. | R96: McLeod
A97: 96 | B97: 40302.396 | C97: 0.54166667 | D97: Injected | E97: 40302.584 | F97: INFO - Train Derailment | G97: Telephone | H97: SEOC WC | I97: SEOC LNO | J97: JOC Message Center | K97: Grove Hill Train Derailment | M97: SEOC LNO forwards report from DPS concerning train derailment north of Grove Hill | N97: JOC Chief should notify TAG and key leaders, pertinent staff personnel and JTFs. | O97: The entire purpose of ths thread is to determine if the information (which will be received from multiple sources at different levels) is passed up-line to JFHQ JOC, and then subsequently assessed by various J-Staff elements. The location of the train derailment is directly adjacent to US 43, which should be an MSR for moving troops and equipment downrange, so will J-2 and J-4 receive info and advise TAG and units accordingly? | P97: SEOC LNO calls to report that DPS has just given a briefing on Grove Hill train derailment. DPS stated that the derailment involved a train consisting of four diesel-electric locomotives and roughly two hundred railcars of varying types. They stated that at least a third of the rolling stock had physically left the railroad tracks as a result of the derailment. The accident involved numerous tank cars containing hazardous materials, but there is no clear indication whether any of these cars are breached or in danger of breaching. The derailment involves multiple fires, most apparently involving rail cars carrying building materials (plywood) and bulk carpet scraps. Because of the fires, thesre is considerable amount of low-hanging smoke in the area, which is slowing the efforts of emergency responders to assess damages. Until hazards can be completely assessed, a mandatory evacuation is currently underway for the towns of Grove Hill, Fulton, Dickenson, and Thomasville. US 43 is closed, and all motorists are advised to avoid Clarke County because of all the evacuation-related traffic in the vicinity of the accident. | R97: Jenne
A98: 97 | D98: Injected | E98: 40302.585 | F98: INFO | G98: Email | H98: USPFO | I98: DENNIS | M98: There are no military transportation assets available, provide commercial haul to deliver 50 tents (GP Medium) to Fort Whiting. | N98: Identify assets to be used for haul | P98: There are no military transportation assets available, provide commercial haul to deliver 50 tents (GP Medium) to Fort Whiting. | R98: Therman
A99: 98 | B99: 40302 | C99: 0.5625 | D99: Injected | E99: 40302.604 | F99: INFO | G99: Email | I99: MCLEOD | J99: CFMO | M99: "X" armory is being renovated, and is not suitable for occupation before, during, or after land fall. BPT coordinate with local/regional contractors for services at alternate locations. | P99: "X" armory is being renovated, and is not suitable for occupation before, during, or after land fall. BPT coordinate with local/regional contractors for services at alternate locations. | R99: McLeod
A100: 99 | B100: 40302.396 | C100: 0.58333333 | D100: Injected | E100: 40302.625 | F100: RFI - Train Derailment | G100: EMITS | H100: SEOC WC | I100: SEOC LNO | J100: JOC Message Center | K100: Grove Hill Train Derailment | M100: EMITS Request for Assistance for Train Derailment emergency response | N100: JOC Chief should notify TAG and key leaders, pertinent staff personnel and JTFs. | O100: JOC planners may determine that a more appropriate targeting/attack method would be linear slurry drops with fixed wing aircraft (like C-130s) rather than spot attacks with helicopters. JOC may determine if slurry-equipped aircraft are available for EMACS request. | P100: EMITS message requests capability assessment of potential Guard capabilities to assist with train derailment north of Grove Hill. Request is to determine availability of CH-47 or UH-60 "Bambi Bucket" capability to help extinguish fires on railcars because of difficulty reaching fires with conventional fire apparatus. | R100: Jenne
...

Sheet MSEL INFO ONLY
A1: MSEL NUMBER | B1: DATE | C1: Time | D1: INJECT DTG | E1: SUBJECT | F1: INJECT MODE | G1: SEND FROM (Simulated) | H1: INJECTED BY | I1: SEND TO | J1: STORYLINE/THREAD | K1: ESF | L1: DESCRIPTION | M1: EXPECTED ACTION | N1: NOTES/REMARKS | O1: IMPLEMENTER (Actual Narrative) | P1: BACKGROUND INFORMATION | Q1: Inject Author
B2: 40298.208 | C2: 40298.208 | D2: 40298.208 | E2: INFO | F2: Not Injected - MSEL Planning Info only | J2: Background Information (Hurricane Synchronization Matrix) | L2: 187 FW - Assemble EOC/Review CEMP 10-2, Annex B | Q2: Jenne
B3: 40298.208 | C3: 40298.208 | D3: 40298.209 | E3: INFO | F3: Not Injected - MSEL Planning Info only | J3: Background Information (Hurricane Synchronization Matrix) | L3: 20 SF - ID JOC LNO | Q3: Jenne
B4: 40298.208 | C4: 40298.208 | D4: 40298.21 | E4: INFO | F4: Not Injected - MSEL Planning Info only | J4: Background Information (Hurricane Synchronization Matrix) | L4: 62 TC - FTUS Hurricane Tracking, Initial PERSTAT and Logistics Capabilities PLACE SUB UNITS on REDCON 4 | Q4: Jenne
B5: 40298.208 | C5: 40298.208 | D5: 40298.21 | E5: INFO | F5: Not Injected - MSEL Planning Info only | J5: Background Information (Hurricane Synchronization Matrix) | L5: EOC/JOC - Assume Adaptive Battle Staff (ABS) 4; Submit Updated AL Capabilites Slide to NGB; place units on REDCON 4 | Q5: Jenne
B6: 40298.208 | C6: 40298.208 | D6: 40298.211 | E6: INFO | F6: Not Injected - MSEL Planning Info only | J6: Background Information (Hurricane Synchronization Matrix) | L6: J-1 / Family Readiness - Contact FRG Coordinators down range | Q6: Jenne
B7: 40298.208 | C7: 40298.208 | D7: 40298.212 | E7: INFO | F7: Not Injected - MSEL Planning Info only | J7: Background Information (Hurricane Synchronization Matrix) | L7: J-1 / Medical - Review CLS Qualifed Personnel | Q7: Jenne
B8: 40298.208 | C8: 40298.208 | D8: 40298.213 | E8: INFO | F8: Not Injected - MSEL Planning Info only | J8: Background Information (Hurricane Synchronization Matrix) | L8: J-1 / Safety - Begin statewide push on Hurricane and Tornado | Q8: Jenne
B9: 40298.208 | C9: 40298.208 | D9: 40298.213 | E9: INFO | F9: Not Injected - MSEL Planning Info only | J9: Background Information (Hurricane Synchronization Matrix) | L9: J-1 / Strength - Review J-1 / Medical, Avn/Trans, EN, MP, LG and SIG/IT Personnel Assets | Q9: Jenne
B10: 40298.208 | C10: 40298.208 | D10: 40298.214 | E10: INFO | F10: Not Injected - MSEL Planning Info only | J10: Background Information (Hurricane Synchronization Matrix) | L10: J-4 / Class I - Review MRE DOS, ensure sufficient 2 DOS per JTF | Q10: Jenne
B11: 40298.208 | C11: 40298.208 | D11: 40298.215 | E11: INFO | F11: Not Injected - MSEL Planning Info only | J11: Background Information (Hurricane Synchronization Matrix) | L11: J-4 / Class III - Link up with SPDOF and verify that fuel contracts listed are valid | Q11: Jenne
B12: 40298.208 | C12: 40298.208 | D12: 40298.215 | E12: INFO | F12: Not Injected - MSEL Planning Info only | J12: Background Information (Hurricane Synchronization Matrix) | L12: J-4 / Class IX - Verify status of CL IX push package. Verify maint status of equipement | Q12: Jenne
B13: 40298.208 | C13: 40298.208 | D13: 40298.216 | E13: INFO | F13: Not Injected - MSEL Planning Info only | J13: Background Information (Hurricane Synchronization Matrix) | L13: J-4 / Class V - Review requirements with FMARNGTC ATP. Verify sufficient on hand | Q13: Jenne
... B19: 40298.208 | C19: 40298.208 | D19: 40298.22 | E19: INFO | F19: Not Injected - MSEL Planning Info only | J19: Background Information (Hurricane Synchronization Matrix) | L19: JTF-S/226 MEB - FTUS Hurricane Tracking | Q19: Jenne
B20: 40299 | C20: 40299.167 | D20: 40299.167 | E20: INFO | F20: Email | G20: Simcell - National Hurricane Center | H20: Keane | I20: JOC, All | J20: Tropical Depression One Forms | K20: 5, 15 | L20: Tropical Depression One Forms | O20: On 01 May, 0400 HRS CDT, The National Hurricane Center issues Tropical Depression Advisory "One". Current Location 14.5 N 74.1 W Max Sustained Wind 30mph | Q20: Keane
B21: 40299.208 | C21: 40299.208 | D21: 40299.208 | E21: INFO | F21: Not Injected - MSEL Planning Info only | J21: Background Information (Hurricane Synchronization Matrix) | L21: 117 ARW - Inventory DR assets | Q21: Jenne
B22: 40299.208 | C22: 40299.208 | D22: 40299.209 | E22: INFO | F22: Not Injected - MSEL Planning Info only | J22: Background Information (Hurricane Synchronization Matrix) | L22: 187 FW - Inventory DR assets/Prepare to respond to JOC tasking | Q22: Jenne
B23: 40299.208 | C23: 40299.208 | D23: 40299.21 | E23: INFO | F23: Not Injected - MSEL Planning Info only | J23: Background Information (Hurricane Synchronization Matrix) | L23: 20 SF - Place SAR Tm on Alert, ID additional 20th Volunteers, Pre-Mission Checks on J-4 / Transportation and critical log | Q23: Jenne
B24: 40299.208 | C24: 40299.208 | D24: 40299.21 | E24: INFO | F24: Not Injected - MSEL Planning Info only | J24: Background Information (Hurricane Synchronization Matrix) | L24: 62 TC - Telecon with Unit Commanders, Issue verbal WARN ORDER | Q24: Jenne
B25: 40299.208 | C25: 40299.208 | D25: 40299.211 | E25: INFO | F25: Not Injected - MSEL Planning Info only | J25: Background Information (Hurricane Synchronization Matrix) | L25: EOC/JOC - Place units on REDCON 3 BPT activate FOSA at MAFB | Q25: Jenne
B26: 40299.208 | C26: 40299.208 | D26: 40299.212 | E26: INFO | F26: Not Injected - MSEL Planning Info only | J26: Background Information (Hurricane Synchronization Matrix) | L26: J-1 / Medical - Review Out of State Personnel Assets | Q26: Jenne
B27: 40299.208 | C27: 40299.208 | D27: 40299.213 | E27: INFO | F27: Not Injected - MSEL Planning Info only | J27: Background Information (Hurricane Synchronization Matrix) | L27: J-1 / Strength - Review Out of State Personnel Assets | Q27: Jenne
B28: 40299.208 | C28: 40299.208 | D28: 40299.213 | E28: INFO | F28: Not Injected - MSEL Planning Info only | J28: Background Information (Hurricane Synchronization Matrix) | L28: J-4 / Class IX - Continue to take necessary action to bring DSCA centric equipment to FMC | Q28: Jenne
B29: 40299.208 | C29: 40299.208 | D29: 40299.214 | E29: INFO | F29: Not Injected - MSEL Planning Info only | J29: Background Information (Hurricane Synchronization Matrix) | L29: JTF-S/226 MEB - Advise TF Units of REDCON 3 Status | Q29: Jenne
B30: 40299.208 | C30: 40299.208 | D30: 40299.215 | E30: INFO | F30: Not Injected - MSEL Planning Info only | J30: Background Information (Hurricane Synchronization Matrix) | L30: JTF-S/226 MEB - Assumes REDCON 4 and prepares to execute JFHQ OPLAN 10-200. | Q30: Jenne
B31: 40299.208 | C31: 40299.208 | D31: 40299.215 | E31: INFO | F31: Not Injected - MSEL Planning Info only | J31: Background Information (Hurricane Synchronization Matrix) | L31: JTF-S/226 MEB - Begin initial preparation for standing up JTF-S staff and the IEF. | Q31: Jenne
B32: 40299.208 | C32: 40299.208 | D32: 40299.216 | E32: INFO | F32: Not Injected - MSEL Planning Info only | J32: Background Information (Hurricane Synchronization Matrix) | L32: JTF-S/226 MEB - Establish communications with Baldwin and Mobile Counties | Q32: Jenne
... B34: 40299.208 | C34: 40299.208 | D34: 40299.217 | E34: INFO | F34: Not Injected - MSEL Planning Info only | J34: Background Information (Hurricane Synchronization Matrix) | L34: JTF-S/226 MEB - Test alert roster for key personnel TPFDD to JTF-S | Q34: Jenne
B35: 40299 | C35: 40299.417 | D35: 40299.417 | E35: INFO | F35: Email | G35: Simcell - National Hurricane Center | H35: Keane | I35: JOC, All | J35: Tropical Storm Al Update 2 | K35: 5, 15 | L35: Tropical Storm Al Update 2 | O35: ...FIRST TROPICAL STORM OF THE SEASON...AL NEARS THE COAST OF NICARAGUA... SUMMARY OF 1100 AM EDT...1500 UTC...INFORMATION ----------------------------------------------- LOCATION...14.9N 74.9W ABOUT 220 MILES...354 KM...SOUTH SOUTHEAST OF KINGSTON JAMA | Q35: Keane
B36: 40299 | C36: 40299.667 | D36: 40299.667 | E36: INFO | F36: Email | G36: Simcell - National Hurricane Center | H36: Keane | I36: JOC, All | J36: Tropical Storm Al Update 3 | K36: 5, 15 | L36: Tropical Storm Al Update 3 | O36: ...TROPICAL STORM AL STRENGTHENS AS IT NEARS THE COAST OF NICARAGUA... SUMMARY OF 1700 AM EDT...2100 UTC...INFORMATION ----------------------------------------------- LOCATION...15.30 N 76.20 W ABOUT 188 MILES...303 KM...167 DEGREES...SOUTH-SOUTHEAST OF | Q36: Keane
B37: 40299 | C37: 40299.917 | D37: 40299.917 | E37: INFO | F37: Email | G37: Simcell - National Hurricane Center | I37: JOC, All | J37: Tropical Storm Al Update 4 | K37: 5, 15 | L37: Tropical Storm Al Update 4 | O37: ...AL BECOMES A HURRICANE AS IT NEARS THE NORTH COAST OF NICARAGUA... SUMMARY OF 1100 PM EDT...0300 UTC...INFORMATION ----------------------------------------------- LOCATION...15.50 N 77.10 W ABOUT 172 MILES...277 KM...SOUTH SOUTHEAST OF KINGSTON JAMAI | Q37: Keane
B38: 40300 | C38: 40300.167 | D38: 40300.167 | E38: INFO | F38: Email | G38: Simcell - National Hurricane Center | H38: Keane | I38: JOC, All | J38: Tropical Storm Al Update 4 | K38: 5, 15 | L38: Tropical Storm Al Update 4 | O38: ...AL REMAINS A CAT 1 HURRICANE MOVING EAST TO WEST...SOUTH OF JAMAICA...GAINING STRENGTH... SUMMARY OF 0500 AM EDT...0900 UTC...INFORMATION ----------------------------------------------- LOCATION...15.90 N 78.10 W ABOUT 159 MILES... 255 KM... SOUTH NE | Q38: Keane
B39: 40300.208 | C39: 40300.208 | D39: 40300.208 | E39: INFO | F39: Not Injected - MSEL Planning Info only | J39: Tropical Storm Al Update 5 | L39: Tropical Storm Al Update 5 | Q39: Jenne
B40: 40300.208 | C40: 40300.208 | D40: 40300.209 | E40: INFO | F40: Not Injected - MSEL Planning Info only | J40: Background Information (Hurricane Synchronization Matrix) | L40: 167 TSC - Issue BPT deploy order to 122d ASG and alert LNOs | Q40: Jenne
B41: 40300.208 | C41: 40300.208 | D41: 40300.21 | E41: INFO | F41: Not Injected - MSEL Planning Info only | J41: Background Information (Hurricane Synchronization Matrix) | L41: 187 FW - Implement CEMP 10-2 Annex B | Q41: Jenne
B42: 40300.208 | C42: 40300.208 | D42: 40300.21 | E42: INFO | F42: Not Injected - MSEL Planning Info only | J42: Background Information (Hurricane Synchronization Matrix) | L42: 20 SF - Dispatch LNO to State JOC, Cooridnate with 131st AVN | Q42: Jenne
B43: 40300.208 | C43: 40300.208 | D43: 40300.211 | E43: INFO | F43: Not Injected - MSEL Planning Info only | J43: Background Information (Hurricane Synchronization Matrix) | L43: 62 TC - Issue WARN ORDER 1, CMC Prep | Q43: Jenne
B44: 40300.208 | C44: 40300.208 | D44: 40300.212 | E44: INFO | F44: Not Injected - MSEL Planning Info only | J44: Background Information (Hurricane Synchronization Matrix) | L44: AEMA SEOC - Alert Alabama Mutual Aid System and County Liaisons | Q44: Jenne
B45: 40300.208 | C45: 40300.208 | D45: 40300.213 | E45: INFO | F45: Not Injected - MSEL Planning Info only | J45: Background Information (Hurricane Synchronization Matrix) | L45: AEMA SEOC -Activate Logistics Staging at Maxwell AFB | Q45: Jenne
B46: 40300.208 | C46: 40300.208 | D46: 40300.213 | E46: INFO | F46: Not Injected - MSEL Planning Info only | J46: Background Information (Hurricane Synchronization Matrix) | L46: AEMA SEOC -Activate Resource Contracts for Security, Food, Ice and Water | Q46: Jenne
B47: 40300.208 | C47: 40300.208 | D47: 40300.214 | E47: INFO | F47: Not Injected - MSEL Planning Info only | J47: Background Information (Hurricane Synchronization Matrix) | L47: AEMA SEOC -Begin Opening Shelters | Q47: Jenne
B48: 40300.208 | C48: 40300.208 | D48: 40300.215 | E48: INFO | F48: Not Injected - MSEL Planning Info only | J48: Background Information (Hurricane Synchronization Matrix) | L48: AEMA SEOC -Begin Public Information Briefings | Q48: Jenne
B49: 40300.208 | C49: 40300.208 | D49: 40300.215 | E49: INFO | F49: Not Injected - MSEL Planning Info only | J49: Background Information (Hurricane Synchronization Matrix) | L49: AEMA SEOC -Begin Twice Daily Situation Updates | Q49: Jenne
B50: 40300.208 | C50: 40300.208 | D50: 40300.216 | E50: INFO | F50: Not Injected - MSEL Planning Info only | J50: Background Information (Hurricane Synchronization Matrix) | L50: AEMA SEOC -Participate in FEMA and Hurricane Liaison Team Conference Calls | Q50: Jenne
... B66: 40300.208 | C66: 40300.208 | D66: 40300.227 | E66: INFO | F66: Not Injected - MSEL Planning Info only | J66: Background Information (Hurricane Synchronization Matrix) | L66: LNO'S - ALERT LNOs | Q66: Jenne
B67: 40300 | C67: 40300.417 | D67: 40300.417 | E67: INFO | F67: Email | G67: Simcell - National Hurricane Center | I67: JOC, All | J67: Tropical Storm Al Update 6 | K67: 5, 15 | L67: Tropical Storm Al Update 6 | O67: ... HURRICANE AL TRACKS TOWARD THE YUCATAN... SUMMARY OF 1100 AM EDT...0900 UTC...INFORMATION ----------------------------------------------- LOCATION...16.3N 79.0W ABOUT 257 MILES... 321 KM...SOUTH SOUTHEAST OF GEORGE TOWN CAYMAN ISLANDS ABOUT 137 MIL | Q67: Keane
B68: 40300 | C68: 0.5 | D68: 40300.5 | E68: RFI | F68: Email | G68: Each Task Force | H68: TF S2 | I68: JOC, J2 | L68: Weather Update/Storm Track | M68: J2 Provides latest Weather and Storm Track to the TFs | O68: Weather RFI from Task Force to J2 | Q68: Houlton
B69: 40300 | C69: 40300.667 | D69: 40300.667 | E69: INFO | F69: Email | G69: Simcell - National Hurricane Center | I69: JOC, All | J69: Tropical Storm Al Update 7 | K69: 5, 15 | L69: Tropical Storm Al Update 7 | O69: ... HURRICANE AL TRACKS TOWARD THE YUCATAN...AS A CATEGORY TWO HURRICANE... SUMMARY OF 0500 AM EDT...0900 UTC...INFORMATION ----------------------------------------------- LOCATION...16.7N 80.0W ABOUT 199 MILES... 321 KM...SOUTH SOUTHEAST OF GEORGE TOWN | Q69: Keane
B70: 40300 | C70: 40300.917 | D70: 40300.917 | E70: INFO | F70: Email | G70: Simcell - National Hurricane Center | I70: JOC, All | J70: Tropical Storm Al Update 8 | K70: 5, 15 | L70: Tropical Storm Al Update 8 | O70: ... HURRICANE AL GAINS MOMENTUM AS A CATEGORY TWO HURRICANE... SUMMARY OF 2300 PM EDT...0300 UTC...INFORMATION ----------------------------------------------- LOCATION...17.1N 80.9W ABOUT 184 MILES...296 KM...WEST-SOUTHWEST NEGRIL JAMAICA ABOUT 154 MIL | Q70: Keane
B71: 40301 | C71: 40301.167 | D71: 40301.167 | E71: INFO | F71: Email | G71: Simcell - National Hurricane Center | I71: JOC, All | J71: Tropical Storm Al Update 9 | K71: 5, 15 | L71: Tropical Storm Al Update 9 | O71: ... HURRICANE AL CONTINUES ON A TRACK TOWARD COZUMEL... SUMMARY OF 0500 AM EDT...0900 UTC...INFORMATION ----------------------------------------------- LOCATION...17.7N 82.1W ABOUT 250 MILES...401 KM...WEST-SOUTHWEST NEGRIL JAMAICA ABOUT 154 MILES...24 | Q71: Keane
B72: 40301.208 | C72: 40301.208 | D72: 40301.208 | E72: INFO | F72: Not Injected - MSEL Planning Info only | J72: Background Information (Hurricane Synchronization Matrix) | L72: J-6 - Alert JISCC | Q72: Jenne
B73: 40301.208 | C73: 40301.208 | D73: 40301.209 | E73: INFO | F73: Not Injected - MSEL Planning Info only | J73: Background Information (Hurricane Synchronization Matrix) | L73: 167 TSC - 122d dispatches LNO's to JTFHQ | Q73: Jenne
B74: 40301.208 | C74: 40301.208 | D74: 40301.21 | E74: INFO | F74: Not Injected - MSEL Planning Info only | J74: Background Information (Hurricane Synchronization Matrix) | L74: 187 FW - Implement HURCON 4 Checklist/Identify personnel for JOC tasking | Q74: Jenne
B75: 40301.208 | C75: 40301.208 | D75: 40301.21 | E75: INFO | F75: Not Injected - MSEL Planning Info only | J75: Background Information (Hurricane Synchronization Matrix) | L75: 62 TC - Stand up CMC with FTUS, Coordinate with other JTFs for handoff and receipt of subordinate units, issue WARN ORD 2 | Q75: Jenne
B76: 40301.208 | C76: 40301.208 | D76: 40301.211 | E76: INFO | F76: Not Injected - MSEL Planning Info only | J76: Background Information (Hurricane Synchronization Matrix) | L76: AEMA SEOC - Begin Incident Action Plan | Q76: Jenne
B77: 40301.208 | C77: 40301.208 | D77: 40301.212 | E77: INFO | F77: Not Injected - MSEL Planning Info only | J77: Background Information (Hurricane Synchronization Matrix) | L77: AEMA SEOC - Deploy Communications Vans | Q77: Jenne
B78: 40301.208 | C78: 40301.208 | D78: 40301.213 | E78: INFO | F78: Not Injected - MSEL Planning Info only | J78: Background Information (Hurricane Synchronization Matrix) | L78: AEMA SEOC - Deploy County Liaisons | Q78: Jenne
B79: 40301.208 | C79: 40301.208 | D79: 40301.213 | E79: INFO | F79: Not Injected - MSEL Planning Info only | J79: Background Information (Hurricane Synchronization Matrix) | L79: AEMA SEOC - Establish Unified Command | Q79: Jenne
B80: 40301.208 | C80: 40301.208 | D80: 40301.214 | E80: INFO - Evacuation | F80: Not Injected - MSEL Planning Info only | J80: Background Information (Hurricane Synchronization Matrix) | L80: AEMA SEOC - Initiate Voluntary Evacuations | Q80: Jenne
B81: 40301.208 | C81: 40301.208 | D81: 40301.215 | E81: INFO | F81: Not Injected - MSEL Planning Info only | J81: Background Information (Hurricane Synchronization Matrix) | L81: AEMA SEOC - Plan Back-Up Communications | Q81: Jenne
B82: 40301.208 | C82: 40301.208 | D82: 40301.215 | E82: INFO | F82: Not Injected - MSEL Planning Info only | J82: Background Information (Hurricane Synchronization Matrix) | L82: AEMA SEOC - Receive FEMA Emergency Response Team | Q82: Jenne
B83: 40301.208 | C83: 40301.208 | D83: 40301.216 | E83: INFO | F83: Not Injected - MSEL Planning Info only | J83: Background Information (Hurricane Synchronization Matrix) | L83: AEMA SEOC -SEOC Activates at Level Two | Q83: Jenne
... B96: 40301.208 | C96: 40301.208 | D96: 40301.225 | E96: INFO | F96: Not Injected - MSEL Planning Info only | J96: Background Information (Hurricane Synchronization Matrix) | L96: LNO'S - Dispatch LNOs to AL EMA; Dispatched LOG Cell to EMA JOC | Q96: Jenne
D97: 40301.292 | E97: MISSION - BPT | F97: EMITS | G97: Director AEMA | I97: JOC | L97: BPT provide Engineer assets for re-entry and debris operations in affected counties. | O97: BPT provide Engineer assets for re-entry and debris operations in affected counties. | Q97: Keane
B98: 40301 | C98: 40301.292 | D98: 40301.292 | E98: LNO to SEOC | F98: EMITS | G98: SEOC | I98: JOC | L98: NG LNO's to State EOC by 0700 4 May 10 | O98: NG LNO's to State EOC by 0700 4 May 10 | Q98: Keane
D99: 40301.312 | E99: MISSION - BPT | F99: EMITS | G99: Director AEMA | I99: JOC | L99: BPT to provide airlift of Gov and his key staff for aerial assessment on or about 6 May 10 | O99: BPT to provide airlift of Gov and his key staff for aerial assessment on or about 6 May 10 | Q99: Keane
D100: 40301.312 | E100: MISSION - BPT | F100: EMITS | G100: Director AEMA | I100: JOC | L100: BPT provide Comms to affected areas EOCs | O100: BPT provide Comms to affected areas EOCs | Q100: Keane
B101: 40301.312 | C101: 40301.312 | D101: 40301.313 | E101: RFI - Holman Prison | F101: Phone Call | G101: JTF-S White Cell (subordinnate commander) | H101: JTF-S WC | I101: 226 MEB | J101: Holman Prison Blues | L101: Company commander requests guidance on soldier | O101: Company commander has a soldier who is a prison guard at Holman Prison. Soldier states that he has been directed to remain at prison and not to report to Guard. Indicates rumors of potential inmate takeover and mass escape during hurricane. Soldier/gua | Q101: Jenne
D102: 40301.314 | E102: MISSION | F102: EMITS | G102: AEMA ESF 5 | I102: JOC | K102: 5 | L102: Provide meteorological services to SEOC (AL) | O102: Provide meteorological services to SEOC (AL) | Q102: Keane
D103: 40301.323 | E103: MISSION - BPT | F103: EMITS | G103: Director AEMA | I103: JOC | L103: BPT to provide 3000 Soldiers for security operations in South and Central Alabama; locations TBD. Request units be self sustaining. | O103: BPT to provide 3000 Soldiers for security operations in South and Central Alabama; locations TBD. Request units be self sustaining. | Q103: Keane
D104: 40301.333 | E104: AEMA Contacts JOC | F104: Phone | G104: AEMA | I104: AL J3 | L104: AEMA Director contacts AL TAG/J3 to discuss hurricane response planning/operations. | O104: AEMA Director contacts AL TAG/J3 to discuss hurricane response planning/operations. AEMA Director states that they are making preliminary plans for possible Alex response operations. Suggests issuing warning orders to MACOMs for potential in-state respon | Q104: Keane
B105: 40301 | C105: 0.33333333 | D105: 40301.334 | E105: LNO | F105: Email | G105: simcell-SEOC | H105: AEMA | I105: J35 | L105: LNO Request | M105: EOC contacts Troop Command | O105: Email Emits message' AEMA SEOC Request ALNG Provide LNO to Mobile and Baldwin Cty EMAs. Report to County EOC | Q105: Messer
B106: 40301 | C106: 0.33333333 | D106: 40301.335 | E106: MISSION - SASO | F106: Email | G106: simcell-SEOC | H106: AEMA | I106: J35 | J106: SASO | L106: SASO Request | M106: EOC contacts 122CSG | O106: Email Emits message' AEMA SEOC Request ALNG Provide SASO to MAFB | Q106: Messer
B107: 40301 | C107: 0.33333333 | D107: 40301.335 | E107: MISSION - SEOC LOG CELL | F107: Email | G107: simcell-SEOC | H107: AEMA | I107: J35 | J107: SEOC Log Cell | L107: SEOC Log Cell Request | M107: EOC contacts 122CSG | O107: Email Emits message' AEMA SEOC Request ALNG Provide SEOC Log Cell to Clanton Al. | Q107: Messer
B108: 40301 | C108: 0.35416667 | D108: 40301.354 | E108: INFO | F108: Phone | G108: simcell-citizen | H108: citizen | I108: Message Center | J108: MVC/ Fatality | L108: Report of Accident | M108: EOC RFIs MACOMS regarding report of accident/vehicles on road | O108: Citizen: I am a retired ARNG member and I just say one of your Humvee's run a stop sign and hit a mini van, and flipped it and it ran off the road. I didn't see anyone get out of either vehicle. I have called 911, just thought you guys wanted to know. | Q108: Messer
D109: 40301.376 | E109: INFO | F109: Email | G109: JIEE | H109: NGB | I109: JOC | J109: Set NGB Conference call up on DCO | Q109: Kahl
B110: 40301 | C110: 0.375 | D110: 40301.376 | E110: INFO | F110: Phone | G110: simcell_LNO | H110: SEOC/LNO | I110: J35 | J110: Contra Flow | L110: Informal message from LNO | M110: WARNO to 62nd Troop Command | O110: I just heard that the Governor is probably going to order contra flow on I 65 sometimes tomorrow morning. I will let you know more as I hear it. | Q110: Messer
D111: 40301.377 | E111: INFO | F111: Email | G111: NGB | H111: NGB | I111: JOC | J111: Set up event and Share with NGB | Q111: Kahl
D112: 40301.378 | E112: RFI | F112: JIEE | G112: JIEE | H112: NGB | I112: JOC | J112: Does the JOC need a JET or PARRT | L112: Request for JET | Q112: Kahl
B113: 40301 | D113: 40301.378 | E113: INFO | L113: The State Emergency Response Team (SERT) is recalled to the State Emergency Operations Center (SEOC (AL)) and activated at Level 1 effective 0900 3 May 2010. | O113: The State Emergency Response Team (SERT) is recalled to the State Emergency Operations Center (SEOC (AL)) and activated at Level 1 effective 0900 3 May 2010. | Q113: Keane
B114: 40301 | C114: 40301.375 | D114: 40301.379 | E114: MISSION | F114: Email | G114: USPFO, S&S | I114: JOC J4 | L114: USPFO Warehouse to push 20 pallets of MREs and 20 pallets of bottled water to Ft McClellan, AL (pre-positioning for soldier support). | O114: USPFO Warehouse to push 20 pallets of MREs and 20 pallets of bottled water to Ft McClellan, AL (pre-positioning for soldier support). | P114: USPFO Warehouse SOP, SA only | Q114: Keane
B115: 40301 | C115: 40301.375 | D115: 40301.38 | E115: MISSION | F115: Email | G115: USPFO, S&S | I115: JOC J4 | L115: USPFO Warehouse to push 20 pallets of MREs and 20 pallets of bottled water to Ft Whiting, Mobile, AL (pre-positioning for soldier support). | O115: USPFO Warehouse to push 20 pallets of MREs and 20 pallets of bottled water to Ft Whiting, Mobile, AL (pre-positioning for soldier support). | P115: USPFO Warehouse SOP, SA only | Q115: Keane
B116: 40301 | D116: 40301.381 | E116: INFO - Evacuation | L116: AEMA recommends voluntary evacuation of Baldwin and Mobile counties. | O116: AEMA recommends voluntary evacuation of Baldwin and Mobile counties. Voluntary evacuations recommended for citizens living in mobile homes for the following counties: Washington, Clarke, Monroe, Conecuh, Escambia, Covington, Geneva, and Houston. | Q116: Keane
B117: 40301 | D117: 40301.381 | E117: INFO | L117: JFHQ activates JTF-South (FTUS) Primary Staff (LNO's)and local units for possible support | O117: JFHQ activates JTF-South (FTUS) Primary Staff (LNO's)and local units for possible support | Q117: Keane
B118: 40301 | D118: 40301.382 | E118: RFI | J118: EMAC | L118: Mississippi Issues EMAC Request for Aviation support, 3x UH60's for SAR | O118: Mississippi Issues EMAC Request for Aviation support, 3x UH60's for SAR | Q118: Keane
B119: 40301 | D119: 40301.383 | E119: RFI | J119: EMAC | L119: Army National Guard CAT requests Alabama review resources available IOT support MSNG 3X UH60. | O119: Army National Guard CAT requests Alabama review resources available IOT support MSNG 3X UH60. | Q119: Keane
B120: 40301 | D120: 40301.384 | E120: MISSION - BPT | L120: BPT establish LSA | O120: BPT establish ONE LSA Brookley Field, Mobile, requires 20 PAX, 24hrs operations duration of support TBD. | Q120: Keane
B121: 40301 | D121: 40301.385 | E121: MISSION - BPT | L121: BPT establish and staff 15 PODs at Mobile and Baldwin counties | O121: BPT establish and staff 15 PODs at Mobile and Baldwin counties | Q121: Keane
B122: 40301 | D122: 40301.385 | E122: MISSION | L122: Provide support to SERT (AL)LOG Chief in SEOC (AL) | O122: Provide support to SERT (AL)LOG Chief in SEOC (AL) | Q122: Keane
B123: 40301 | D123: 40301.386 | E123: MISSION - BPT | L123: Stage & BPT deploy 2 SAR teams to Mobile and Baldwin County EOC locations. | O123: Stage & BPT deploy 2 SAR teams consisting of 4ea 5tons 16 PAX to Mobile and Baldwin County EOC locations. POC will be Mr. Evens and Mr Raines | Q123: Keane
B124: 40301 | D124: 40301.387 | E124: INFO | L124: TF South gets notification of pending activation | O124: TF South gets notification of pending activation | Q124: Keane
B125: 40301 | D125: 40301.388 | E125: MISSION | L125: Provide meteorological services to SEOC (AL) | O125: Provide meteorological services to SEOC (AL) | Q125: Keane
B126: 40301 | D126: 40301.388 | E126: MISSION | K126: 9 | L126: Provide SAR Planner to SEOC (AL) ESF 9 | O126: Provide SAR Planner to SEOC (AL) ESF 9 | Q126: Keane
B127: 40301 | D127: 40301.389 | E127: MISSION - BPT | L127: BPT support Aviation assets to assist with SAR | O127: BPT support Aviation assets to assist with SAR | Q127: Keane
B128: 40301 | D128: 40301.39 | E128: INFO | L128: FEMA Region JFO ERT-A will deploy to AEMA on 4 May about 1200, FEMA Region 9 DCO will serve as JFO-AL DCO | O128: FEMA Region JFO ERT-A will deploy to AEMA on 4 May about 1200, FEMA Region 9 DCO will serve as JFO-AL DCO | Q128: Keane
B129: 40301 | D129: 40301.39 | E129: MISSION | L129: Deploy SERT (AL) LNOs to Mobile and Baldwin counties NLT 4 May 1800. | O129: Deploy SERT (AL)LNOs to Mobile and Baldwin counties NLT 4 May 1800. | Q129: Keane
B130: 40301 | D130: 40301.391 | E130: MISSION - BPT | L130: BPT to provide airlift of Gov and his key staff for aerial assessment on or about 6 May 10 | O130: BPT to provide airlift of Gov and his key staff for aerial assessment on or about 6 May 10 | Q130: Keane
B131: 40301 | D131: 40301.392 | E131: MISSION - BPT | L131: BPT provide Comms to affected areas EOCs | O131: BPT provide Comms to affected areas EOCs | Q131: Keane
B132: 40301 | D132: 40301.392 | E132: MISSION - BPT | L132: BPT to provide 3000 Soldiers for security operations in South and Central Alabama | O132: BPT to provide 3000 Soldiers for security operations in South and Central Alabama; locations TBD. Request units be self sustaining. | Q132: Keane
B133: 40301 | D133: 40301.393 | L133: USPFO - ADP requests a 30 KW generator to be positioned at the USPFO building to maintain computer connectivity for AL Nat Guard. | O133: USPFO - ADP requests a 30 KW generator to be positioned at the USPFO building to maintain computer connectivity for AL Nat Guard. | Q133: Keane
...

Sheet Venue Fail Safe
A1: Hurricane Scenario
A2: Master Scenario Events List (MSEL)
A3: MSEL NUMBER | B3: DATE | C3: INJECT DTG | D3: SUBJECT | E3: INJECT MODE | F3: SEND FROM (Simulated) | G3: INJECTED BY | H3: SEND TO | I3: STORYLINE/THREAD | J3: ESF | K3: DESCRIPTION | L3: EXPECTED ACTION | M3: NOTES/REMARKS | N3: IMPLEMENTER (Actual Narrative) | O3: BACKGROUND INFORMATION | P3: Inject Author
A4: FS-1 | B4: 40301 | C4: 5/3/10 0715 | D4: NGB ABS Standup | E4: E-Mail | F4: NGB | G4: Huddleston | H4: ALNG JOC | I4: NGB JoCC has established ABS Level 2 in response to Hurricane AL | K4: NGB JoCC has established ABS Level 2 in response to Hurricane AL | L4: None | N4: Exercise Exercise Exercise | P4: Huddleston
A5: FS-2 | B5: 40301 | C5: 1015 | D5: NGB JoCC Requesting Hurricane States update Hurrican Matrices | E5: JIEE | F5: NGB-JoCC | G5: Huddleston | H5: All States | I5: NGB JoCC request all supported and supporting Hurricane State update their Hurricane Matrices ASAP and Provide to NGB JoCC, NLT 1400 EDT. | K5: NGB JoCC request all supported and supporting Hurricane State update their Hurricane Matrices ASAP and Provide to NGB JoCC, NLT 1400 EDT. | L5: AL JOC update their Hurricane Matrices | N5: NGB JoCC request all supported and supporting Hurricane State update their Hurricane Matrices ASAP and Provide to NGB JoCC, NLT 1400 EDT. | P5: Huddleston
A6: FS-3 | B6: 40301 | C6: 1900 | D6: RFI for Update of mission status | E6: JIEE | F6: NGB JoCC | G6: Huddleston | H6: AL JoCC | I6: The Gulf States in the potential path of Hurricane Al should keep NGB aprised of certain information but are not. | K6: The Gulf States in the potential path of Hurricane Al should keep NGB aprised of certain information | N6: As a result of Hurrican Al, the National Guard Bureau Adaptive Battle staff has been established at ABS Level 2 as of 0700 EDT, 3 May 2010. NGB Point of Contact for AL HURREX, Hurricane AL is, COL Sanders, 571-606-2396.
A7: FS-4 | B7: 40302 | C7: 930 | D7: Forklift request capable of handling L-463 pallets | E7: Telephone call, follow-up email JOC | F7: White Cell J4 | G7: McDonald | H7: J4 (telephone), email J33 | I7: Supplies are beginning to stock pile as they arrived at Mobile Regional Airport. The Airfield Manager indicated shipment after shipment are waiting to be off loaded as air cargo arrived. The only forklift presently located at Mobile regional Airport, which is capable of Handling L-463 pallets is not functioning. | L7: States ability to transport a forklift capable of handling L-463 pallets. NG ability to identify which unit MTOE has Line # T-49119 | N7: As a result of a malfunction forklift, Airfield Manager is requesting two 10,000lbs forklift capable of Handling L-463 pallets. POC whitecell J4, 4731
A8: FS-5 | B8: 40302 | C8: 1055 | D8: 1165th MP CO down vehicle | E8: Telephone call, follow-up email JOC | F8: White Cell TFAL | G8: Napier | H8: 31st Chem Bde | I8: While in route to report to JTF-S 1165th had a HMMWV's rear axle went out and is blocking one lane on Bay Bridge. 1165th does not have a tow bar or wrecker with the convoy. The company has left two soldiers with the vehicle and the rest of the company went to Fort Whiting. The traffic on Bay Bridge is backing up. | L8: 31st Chem Bde to JTF-S for support to assist with the down HMMWV
A9: FS-6 | B9: 40302 | C9: 1400 | D9: Engineers Batteries | E9: email | F9: White cell J-4 | G9: Cannon | H9: J-4 | I9: Engineers task to remove debris from roadway has equipment with dead batteries. Unit need 30ea of NSN 6140-01-493-1962, supporting FMS has zero on-hand. | L9: Expect purchase to be on Impac Card. Ensure J4 follows Impac procedures. | N9: NGB JoCC
A10: FS-7 | B10: 40302 | C10: 1730 | D10: Recovery Mission | E10: e-mail | F10: White cell J-4 | G10: Cannon, McDonald | H10: J-4 | I10: Accident on I-65 aand I-85 interchange involving 2 military LMTV's at 1715 hrs, request recovery mission, owning unit has no recovery capability | L10: Determine capability to task appropriate unit | N10: COL Sanders
N11: 571-606-2396
N12: exercise.ngb.jocc@gmail.com
N14: Exercise Exercise Exercise
A15: FS-8 | B15: 40303 | C15: 900 | D15: Network Problems | E15: Cell Phone Call | F15: FTUS NCO manning Citronelle Armory | G15: CW2 Snider | H15: JTF-South | I15: Citronelle Network Problems | K15: Question Concerning Network | L15: JTF South contact JFHQ-JOC. JFHQ-JOC contact J-6. | N15: I was walking down the hall and noticed that water was coming out from under the door of the telecom room. I opened the door and noticed that water is leaking from the roof all over the equipment that is in there. | O15: J6 should be involved for solution. | P15: Snider
A16: FS-9 | B16: 40303 | C16: 930 | D16: Students return to school | E16: e-mail | F16: white cell 1 | G16: MAJ Johnson | H16: jfhqal.j33.msg1 | I16: Troy University called and stated that SPC Mitchell and PFC Howard, with JTF South, need to return to class on Thursday. | L16: Message center contact JTF-S and J1 in order to take action. Action will affect Pay and will require communication and a plan to get these soldiers back to their HS. | N16: Troy University called and stated that SPC Mitchell and PFC Howard, with JTF South, need to return to class on Thursday. | P16: Johnson
A17: FS-10 | B17: 40303 | C17: 1130 | D17: Unknown individual shows up in uniform. Request to assist in mission. | E17: e-mail | F17: white cell 1 | G17: MAJ Johnson | H17: jfhqal.j33.msg1 | I17: JTF-South reports individual showed up in uniform stating he is a member of 31st Chem Brigade. No soldier with that name or SSN is on a Battle Roster or in SIDPERS. Individual insist on helping and states he will go to Civilian Reporters if rejected. Request guidance. | L17: Message center contact J1/JAG/PAO in order to take action. Action will require interaction with Civilian Authorities in the area of JTF-S and will require communication and a plan to remove individual from AO. | N17: JTF-South reports individual showed up in uniform stating he is a member of 31st Chem Brigade. No soldier with that name or SSN is on a Battle Roster or in SIDPERS. Individual insist on helping and states he will go to Civilian Reporters if rejected. Request guidance. | P17: Johnson
A18: FS-11 | B18: 40303 | C18: 1300 | D18: Soldier's wife going into labor and demanding that soldier be allowed to meet her at the hospital. | E18: e-mail | F18: white cell 1 | G18: MAJ Johnson | H18: jfhqal.j33.msg1 | I18: Red Cross states MAJ Sawyer's wife is going into labor at Sacred Heart in Pensacola. She is frantic and demands his presence. | L18: Message center contacts J1 in order to take action. Action will require interaction with J1 and soldier's unit. | N18: Red Cross states MAJ Sawyer's wife is going into labor at Sacred Heart in Pensacola. She is frantic and demands his presence. | P18: Johnson
A19: FS-12 | B19: 40303 | C19: 1020 | D19: A M916 hauling a MW24C 2 1/2 Yard Scooper Loader overturn I-10 | E19: email | F19: white cell 4 | G19: McDonald/Canno | H19: jfhqal.j33.msg1 | I19: M916 hauling a MW24C 2 1/2 Yard Scooper Loader convoying east on I-10 in Mobile, braking action cause tie down to break, which in turn, let the loader fall off the trailer, backing tracffic east bound. | L19: Heavy equipment Recovery procedure | N19: TF-South Dispacted Wrecker
A20: FS-13 | B20: 40303 | C20: 1300 | D20: Grove Hill - Jackson City Emergency Manager requested evacuation assistance from NG | E20: email | F20: white cell 4 | G20: McDonald/Canno | H20: State EMA | I20: Grove Hill - Jackson City area EM, requested assistance from ALNG to evacuation of 20 elderly personnel from the city of Jackson, relocating to B'Ham until Hurricrane had cleared. | L20: ALT Route procedure when main route is closed
A21: FS-14 | B21: 40301 | C21: 030932MAY10 | D21: Medical Readiness Status Update | E21: Telephone Call | F21: State Surgeon | G21: White Cell - Medical (MAJ Benton) | H21: J33 Message Center | I21: DTG (3029MAY2010) TELEPHONE CALL FROM STATE SURGEON: All JTFs need to screen all potential personnel to be activated for DSCA support missions to ensure that they have a current periodic health assessment (PHA), current dental examination, current on Routine Adult Immunizations (to include H1N1 Influenza) and have no outstanding non-deployable medical conditions. Status report needs to be submitted back to JFHQ-MED NLT 1200 4 May 10 in order to establish any follow on PHA, Dental and/or immunization mission requirements. | L21: JTFs to scrub potential personnel rosters and identify any shortfalls that the JFHQAL could establish missions to support. | M21: CLOSED | P21: BENTON
A22: FS-15 | B22: 40302 | C22: 041730MAY10 | D22: CL VIII/Vaccine Request | E22: EMAIL | F22: JTF North | G22: White Cell - Medical (MAJ Benton) | H22: J33 Message Center | I22: TF MED of JTF North requests Routine Adult Immunizations as follows: Hep A: 75 doses, Hep B: 90 doses, Hep A/B: 25 doses, TDAP: 15 doses, & H1N1: 435 doses. Note: TF MED has all expendable CL VIII to administer vaccines with the exception of needles (25g x 1"). Need items above NLT 0900 in preparation for incoming support personnel. | L22: JTF N to Coordinate with JFHQAL MED to set up CL VIII mission with MED DET. | P22: BENTON
A23: FS-16 | B23: 40302 | C23: 042100MAY10 | D23: MVA Medical Update 1 | E23: EMAIL | F23: JTF North | G23: White Cell - Medical (MAJ Benton) | H23: J33 Message Center | I23: UPDATE: Three (3) of the military personnel injurred received minor injuries from the accident and were treated/released at 2030. One (1) soldier received a minor head injury that requires him to remain overnight and further testing. | L23: Coordinate J1 Actions (LODs & Accountablity), Chaplain Support and Medical Patient Tracking. | P23: BENTON
A24: FS-17 | B24: 40303 | C24: 050859MAY10 | D24: Medical Equipment Repair | E24: EMAIL | F24: JTF South | G24: White Cell - Medical (MAJ Benton) | H24: J33 Message Center | I24: The TF MED (JTF S) is reporting that the dental xray machine in the Ft. Whiting medical facility is down and requesting medical maintenance support. | L24: JFHQ MED will set up support. Military support will not be available. Contract support will need to be coordinated. | P24: BENTON
A25: FS-18 | B25: 40303 | C25: 050859MAY10 | D25: MVA Medical Update 2 | E25: EMAIL | F25: JTF North | G25: White Cell - Medical (MAJ Benton) | H25: J33 Message Center | I25: UPDATE: SGT Joe Doe's condition has worsened and the SM will remain in the hospital until further notice. The Doe family is currently at Jackson Hospital and terribly upset with the fact that no military family support is being offered at this time. | L25: JFHQ MED will provide detailed patient tracking. J1 will account for SM in PERSTAT & Chaplian will send rep to meet with family. | P25: BENTON
A26: FS-19 | B26: 40304 | C26: 060700MAY10 | D26: Sexual Assault Incident | E26: EMAIL | F26: JTF South | G26: White Cell - Medical (MAJ Benton) | H26: JTF S Whitecell | I26: A SM from JTF South was brought to sick call this morning by her battle buddy. The SM was badly beaten and raped around 0200 by a fellow soldier. TF MED (JTF S) has stabilized the soldier's injuries and conducted the initial mental health evaluation. TF MED (JTF S) is requesting SM being transferred back to HOR (Birmingham) by MEDEVAC to complete follow up medical care. SM SSN: ###-###-1234 | L26: Should initiate J3 AVN coord, J1 SARC, Safety, MED, JAG, PAO and CID/CIV Police OPEN | P26: BENTON

Sheet Backup
A1: Hurricane Scenario
A2: Master Scenario Events List (MSEL)
A3: MSEL NUMBER | B3: DATE | C3: INJECT DTG | D3: SUBJECT | E3: INJECT MODE | F3: SEND FROM (Simulated) | G3: INJECTED BY | H3: SEND TO | I3: STORYLINE/THREAD | J3: ESF | K3: DESCRIPTION | L3: EXPECTED ACTION | M3: NOTES/REMARKS | N3: IMPLEMENTER (Actual Narrative) | O3: BACKGROUND INFORMATION | P3: Inject Author

Sheet Examples
A1: MSEL NUMBER | B1: DATE | C1: Time | D1: INJECT DTG | E1: SUBJECT | F1: INJECT MODE | G1: SEND FROM (Simulated) | H1: INJECTED BY | I1: SEND TO | J1: STORYLINE/THREAD | K1: ESF | L1: DESCRIPTION | M1: EXPECTED ACTION | N1: NOTES/REMARKS | O1: IMPLEMENTER (Actual Narrative) | P1: BACKGROUND INFORMATION | Q1: Inject Author
C2: 0.33333333 | D2: 1/0/2020 08:00:00 | K2: 5 | M2: A joint basis with (State Coordinating Officer), Federal Emergency Management Agency (FEMA) (Region #), FEMA Regional Response Coordination Center (RRCC) and (Appropriate Military Command) (via the [Defense Coordinating Office]). Crisis action planning will focus on vulnerabilities and resource availability. Crisis action planning will result in a (State Coordinating Officer)/FEMA (Region #) Planning Order. Begin incident-specific operational planning. | Q2: Example - Keane
C3: 0.33333333 | D3: 1/0/2020 08:00:00 | F3: Handout | G3: Control | I3: All | K3: 5 | O3: Scenario read-in, IAP and SitRep received. | Q3: Example - Keane
C4: 0.33333333 | D4: 1/0/2020 08:00:00 | F4: Handout | G4: Control | I4: All | K4: 5 | O4: Start of Exercise: (Operations Plan [OPLAN]) Phase 2 Operations begin at scenario: Landfall + (#) hours. | Q4: Example - Keane
C5: 0.33333333 | D5: 1/0/2020 08:00:00 | F5: Handout | G5: Control | I5: All | K5: 5, 15 | O5: Weather Package #4: (Month/Year) AM: warnings dropped (provided at Start of Exercise (Month/Day): summary (actual onset, etc.) and weather package "5 clear"). | Q5: Example - Keane
C6: 0.33333333 | D6: 1/0/2020 08:00:00 | F6: Handout | G6: Control | I6: All | K6: 5, 15 | O6: Weather Product: Weather summary/situation for exercise time period of landfall through (Month/Day) (NOT a package: "fill in gaps" product) Note slowing of storm, locational details, etc. Rest of Exercise weather is "real" (National Weather Service [NWS]) packages. | Q6: Example - Keane
C7: 0.33333333 | D7: 1/0/2020 08:00:00 | K7: 5 | O7: Activate (Emergency Management Assistance Compact [ EMAC])and applicable Memorandums of Understanding [MOUs]/(Memorandum of Agreement [MOAs]). - Coordinate mass care and temporary housing support to an estimated population of (#), including special needs and pets. - Coordinate evacuation operations (including prioritization). - Account for, shelter, and initiate evacuations of tourist populations. - Assess functionality of water distribution systems, and establish emergency water distribution. - Provide fuel at critical locations, plan for restoration of retail fuel delivery process. - Clear key transportation routes of debris. - Coordinate deployment of critical resources. - Deconflict power restoration priorities. | Q7: Example - Keane
C8: 0.33333333 | D8: 1/0/2020 08:00:00 | F8: Phone | G8: SimCell (City/County) | I8: ESF 8 | K8: 8 | M8: DoD Inject 135: See (Name) for details and additional information. | O8: Locals are requesting assistance with mortuary affairs. | Q8: Example - Keane
C9: 0.33680556 | D9: 1/0/2020 08:05:00 | F9: Phone | G9: SimCell (City/County) | I9: ESF 9 | K9: 9 | M9: Est. victims = (#–#) people | O9: Search and Rescue support is needed at the following locations: - Tourists sheltered in (Location) (Hotel) above 3rd floor with partial collapse and debris blocking exits, some trapped in elevator. - (City Fire Department) requests (#) type I (Urban Search and Rescue [USAR]) teams for operations within (Location). - Update of Group Care for elderly residents in central (City): residents tried to shelter in place but home collapsed. Multiple injuries, and potential trapped victims. - Structure collapse on (campus), trapping over a hundred people sheltered there. - (Retirement Community) reports (#) senior residents are stranded on the upper floors of their facility and are unable to use the elevators (power outage) or stairs. | Q9: Example - Keane
C10: 0.33680556 | D10: 1/0/2020 08:05:00 | F10: Phone | G10: SimCell (City/County) | I10: ESF 3 | K10: 3 | O10: Oil trucks can’t get to refinery due to traffic-clogged roads. Need police to open route to fuel tanks at (Location) refineries and prioritize routes to distribution points. | Q10: Example - Keane
C11: 0.34027778 | D11: 1/0/2020 08:10:00 | F11: Fax | G11: SimCell (City/County) | I11: ESF 8 | K11: 8 | M11: Details on damage for each location found in fax to be injected later, and in truth binder. | O11: Hospital Update: We anticipate (#) hospitals were affected by the storm and assume at a minimum (#) hospitals lost (#) percent of their windows and (#) are on generator power. So far we have received damage reports from the following hospitals and urgent care clinics: (Names of Clinics and Hospitals). In addition, the following Urgent Care Centers were in the inundation and are closed: the (Names of Clinics and Hospitals). | Q11: Example - Keane
C12: 0.34027778 | D12: 1/0/2020 08:10:00 | F12: Phone | G12: SimCell (City/County) | I12: ESF 6 | K12: 6 | O12: Many shelters are running out of potable water and supplies. When will more supplies be coming in from the (Location)? There is a need for food, blankets, first aid supplies, and hygiene kits. | Q12: Example - Keane
C13: 0.34375 | D13: 1/0/2020 08:15:00 | K13: 5 | M13: DoD Inject 136: See (Name) for details and additional information. | O13: FEMA assigns this mission to DoD, drafts a (Mission Assignment [MA]) to assist with the strategic airlift of FEMA commodities, and sends it to the (Defense Coordinating Officer [DCO/E]) for validation. | Q13: Example - Keane
C14: 0.34375 | D14: 1/0/2020 08:15:00 | F14: Phone | G14: SimCell (City/County) | I14: ESF 13 | K14: 13 | O14: (Location) airfield reports crowd of hundreds of civilians seeking food and shelter at front gate. In addition, thousands of others are congregating outside of fire houses looking for medical aid, food, water and where to go find shelter. | Q14: Example - Keane
C15: 0.34722222 | D15: 1/0/2020 08:20:00 | F15: Phone | G15: SimCell (City) | I15: ESF 1 | K15: 1 | O15: (City) International Airport remains closed because of debris on the runways. Anticipate one runway (in conjunction with (AFB) will be operational under daylight (Visual Flight Rules [VFR]) by midday (Month/Day). | Q15: Example - Keane
C16: 0.34722222 | D16: 1/0/2020 08:20:00 | F16: Phone | G16: SimCell (Utilities) | I16: ESF 6 | K16: 6 | O16: (Electric Company) requests base camp space for (#) linemen arriving from (Location) and priority sheltering for family members. | Q16: Example - Keane
C17: 0.35069444 | D17: 1/0/2020 08:25:00 | F17: Phone | G17: SimCell (State Tourist Association Emergency Operations Center [EOC]) | I17: ESF (#) | K17: 7 | M17: Identify power teams to assess specific generator requirements. If (City) (Department of Emergency Management) is not playing, they should be simulated so this request can be delivered to the (City Emergency Operations Center). | O17: Initial assessment of tourist population reports (#) tourists in hotels on (Location) (#) percent of hotels are without emergency power for elevators. (#) tourists are special needs. Request generator support for elevators. | Q17: Example - Keane
C18: 0.35416667 | D18: 1/0/2020 08:30:00 | F18: Phone | G18: SimCell (City and County) | I18: ESF 1 | K18: 1 | O18: (City) Harbor: Pier (#) and (#) were inspected and are intact. Depth alongside Piers (#) and (#) concurs with charted depth. There are damages to (#) pier-side ramp systems and perimeter fencing. A large portable crane used for offloading of cargo has mechanical damage to its arm and is nonfunctional, but could be fixed with (#) hours of maintenance. | Q18: Example - Keane
C19: 0.35416667 | D19: 1/0/2020 08:30:00 | F19: Phone | G19: SimCell (County) | I19: ESF 1 | K19: 7 | M19: Provide a status on the (Location). | O19: This is (City/County/State Emergency Management Agency) . When can we expect the (Location) to be operational so that we can receive fuel and supplies? | Q19: Example - Keane
C20: 0.35763889 | D20: 1/0/2020 08:35:00 | F20: Phone | G20: SimCell (City and County) | I20: ESF 1 | K20: 1 | O20: (City) Harbor is generally clear from the approaches to: (Points). Depths are clear to charted depths. At the eastern end of (Point), there is a sheen in close proximity to a barge that is resting on a partially sunk (drydock). It is unclear if the source of the sheen is the barge, the drydock or something else. | Q20: Example - Keane
C21: 0.35763889 | D21: 1/0/2020 08:35:00 | F21: Phone | G21: SimCell (Private Sector) | I21: ESF 1 | K21: 1 | O21: (Company Name) barges and (State)Tug and Barge were generally successful in conducting storm evasion, but the following barges were damaged: (Location) (#-ton barge), (Location) (#-ton barge), (Location) (#-ton barge). | Q21: Example - Keane
C22: 0.36111111 | D22: 1/0/2020 08:40:00 | F22: Phone | G22: SimCell (City and County) | I22: ESF 1 | K22: 1 | O22: Sunken and floating debris make Pier (#) inaccessible, and the piers themselves are covered with debris. (#) (Location) Gantry Cranes are damaged and require inspection, repair, and testing. There are oil and HazMat releases in the vicinity of Piers (#) and (#). The area north of Piers (#) and (#) is impacted by spilled fuel. Southern portion of (Location) is covered by a large pond of wastewater. | Q22: Example - Keane
C23: 0.36111111 | D23: 1/0/2020 08:40:00 | F23: Phone | G23: SimCell (Utilities) | I23: ESF 12 | K23: 12 | O23: (#) power poles and (#) cherry pickers arrive at (Location). (Electric Company) requests assistance in getting supplies to (City). | Q23: Example - Keane
C24: 0.36458333 | D24: 1/0/2020 08:45:00 | F24: Phone | G24: SimCell (City/County) | I24: ESF 8 | K24: 8 | M24: DoD Inject 46: See (Name) for details and additional information. | O24: Medical personnel are needed to augment medical facilities in several locations across (Location). | Q24: Example - Keane
C25: 0.36458333 | D25: 1/0/2020 08:45:00 | F25: Phone | G25: SimCell (City/County) | I25: ESF 6 | K25: 6 | M25: Cross-check. | O25: The following shelters have reportedly been severely damaged. Search and rescue resources are required and transportation to move evacuees is needed. The number of injuries at these locations is unknown. The shelters affected include: (Names of Shelters). | Q25: Example - Keane
C26: 0.36458333 | D26: 1/0/2020 08:45:00 | F26: Fax | G26: SimCell (City/County) | I26: ESF 1 | K26: 1 | O26: Port Update: - (City) Fire Department reports that the building located on Pier (#) that provides accommodations and a headquarters for the fire boat crew has collapsed. - Pier (#) has been completely blocked by floating debris. A (#)-ft. access roadway that extends across the inner slip has been washed out. - Several piers along (Location) have suffered severe structural damage. Fishing vessels, equipment, and supplies have been lost or damaged. Structures on the wharf to include the former cannery and the (Name) Restaurant have been inundated with flood waters. - Parking lot areas at the foot of (Name) Streets have been consumed by debris and vessels washed up on shore blocking inland access to Pier (#). - On the East Side of (Location) Drainage Canal, below (highway) Bridge, Pier (#) has been completely washed out. - At Pier (#) a transit shed used for storage and automobile parking has been washed out scattering equipment and supplies across the piers and leaving abandoned vehicles blocking portions of Pier (#). | Q26: Example - Keane
C27: 0.36805556 | D27: 1/0/2020 08:50:00 | F27: Fax | G27: Control | I27: All | K27: 5, 15 | M27: Situation report (SitRep)-type document outlining status of response efforts, shelter status, fire/ems/search and rescue, transportation, debris clearance status, health/medical, HazMat, utility updates. | O27: County perdisreps (Periodic Situation Reports) provided. | Q27: Example - Keane
C28: 0.36805556 | D28: 1/0/2020 08:50:00 | F28: Fax | G28: Control | I28: All | K28: 5, 15 | M28: SitRep-type document outlining status of response efforts, shelter status, fire/ems/search and rescue, transportation, debris clearance status, health/medical, HazMat, utility updates. | O28: County perdisreps (Periodic Situation Reports) provided. | Q28: Example - Keane
C29: 0.37152778 | D29: 1/0/2020 08:55:00 | F29: Phone | G29: SimCell (Hospitals) | I29: ESF 8 | K29: 8 | O29: Hospital Update: Generator fuel is running low in most medical facilities. Satellite phone batteries are wearing down and medical supplies are running low in ALL hospitals. The four (Hospital) medical equipment cached (Location) has been damaged and cannot be relied on; incomplete inventory makes gap analysis difficult. Need basic first aid supplies, as well as intravenous fluids, emergency room supplies, general hospital supplies. Expect supplies of most materials will run out in approximately (#) hours. | Q29: Example - Keane
C30: 0.375 | D30: 1/0/2020 09:00:00 | F30: Phone | G30: SimCell (City/County) | I30: ESF12 | K30: 7 | M30: DoD Inject 51: See (Name) for details and additional information. | O30: Locals are requesting fuel delivery in order to main essential services. | Q30: Example - Keane
C31: 0.375 | D31: 1/0/2020 09:00:00 | F31: Phone | G31: SimCell (City/County) | I31: ESF 12 | K31: 12 | M31: DoD Inject 53: This should be injected during phone call between the locals and JFO. See (Name) for details and additional information. | O31: Due to the power outage on (Location), emergency power is needed to maintain emergency water distribution to shelters and key facilities. | Q31: Example - Keane
C32: 0.375 | D32: 1/0/2020 09:00:00 | F32: Phone | G32: SimCell (County) | I32: ESF 1 | K32: 1 | M32: DoD Inject 54: See (Name) for details and additional information. | O32: Locals request emergency salvage operations for a grounded ship blocking the (Port) (City). | Q32: Example - Keane
C33: 0.375 | D33: 1/0/2020 09:00:00 | F33: Phone | G33: SimCell (City/County) | I33: ESF 3 | K33: 1, 3 | M33: DoD Inject 55: See (Name) for details and additional information. | O33: Locals request support for debris clearance on impassable highways. | Q33: Example - Keane
C34: 0.375 | D34: 1/0/2020 09:00:00 | F34: Phone | G34: SimCell (City/County) | I34: ESF 8 | K34: 8 | M34: DoD Inject 56: See (Name) for details and additional information. | O34: Request for a medical aid station to deploy to (Location). Request support to provide immediate care and first aid to windward residents for at least (#) month. | Q34: Example - Keane
C35: 0.375 | D35: 1/0/2020 09:00:00 | K35: 5 | O35: Conference with (City/County/State Emergency Management Agencies). | Q35: Example - Keane
C36: 0.375 | D36: 1/0/2020 09:00:00 | I36: ESF 8 | K36: 8 | M36: Details on damage for each location found in fax to be injected later and in truth binder. | O36: Hospital Update: Additional reports from hospitals on the (Locations) have been received. The following locations have provided reports of damage to their facilities: (Names of Locations). | Q36: Example - Keane
C37: 0.375 | D37: 1/0/2020 09:00:00 | K37: 5 | O37: (Unified Command Group [UCG]) requests plan for the postlandfall evacuation of tourists brief: the location of assembly areas, movement to ports of embarkation, and throughput estimates for the next (#) days. Include list of damaged hotels that are closed. Plans to schedule briefing. | Q37: Example - Keane
C38: 0.375 | D38: 1/0/2020 09:00:00 | F38: Phone | G38: SimCell (Governor's Office) | I38: ESF 15 | K38: 15 | M38: Provide information or a time when it will be provided. | O38: This is (Name), the executive assistant to the Lieutenant Governor. Governor (Name) would like to know the current steps being taken to mitigate and ensure the safety of the tourists in the (Locations). | Q38: Example - Keane
C39: 0.375 | D39: 1/0/2020 09:00:00 | G39: SimCell (City and County) | K39: 5 | M39: DoD Inject 138: See (Name) for details and additional information. | O39: A medium-lift rotary wing asset is needed to be on standby for personnel transport. FEMA assigns this mission to DoD, drafts an MA to provide a medium-lift rotary wing asset to be on standby for personnel transport, and sends it to the (District Corps of Engineers) for validation. | Q39: Example - Keane
C40: 0.375 | D40: 1/0/2020 09:00:00 | F40: Phone | G40: SimCell (City/County) | I40: ESF 10 | K40: 10 | O40: (Company Name) reports that a major pipeline that carries Jet Fuel-A from Pier (#) storage tanks on the opposite side of (Location) basin west of (Name) Road has suffered damage. Based on visual evidence and smell, there is a large area of contaminated soil that will need to be remediated. | Q40: Example - Keane
C41: 0.37708333 | D41: 1/0/2020 09:03:00 | F41: Phone | G41: SimCell (City/County) | I41: ESF 6 | K41: 8 | O41: Certain (Points of Distribution [POD]) sites (list) still can not be accessed due to debris blocking roadways. The movement of police vehicles is difficult because of downed trees, power lines, etc. Need debris clearance team to support first responders. | Q41: Example - Keane
C42: 0.37847222 | D42: 1/0/2020 09:05:00 | F42: Phone | G42: SimCell (Department of Education and Department Operations Center) | I42: ESF 6 | K42: 6 | M42: (Education Officer) (State Coordinating Officer) work with (Department of Education Department Operations Center) to give a timeframe for school reopening; (Name of School) (Department of Education). | O42: School Issues: - (Name) Assistant Superintendent of (Department of Education), requests a timeline when all schools presently used as a shelter will be released and school operations will begin assessment. (State) presently under (Name) consent decree, special needs children need to have their instructional time resumed or severe penalties will result. - (School) principal requests a time when their postponed commencement exercise on (Month/Day) can be held. -Summer school starts on (Day/Month/Year). When will the schools used as shelters be closed in order to open the summer program? | Q42: Example - Keane
C43: 0.37916667 | D43: 1/0/2020 09:06:00 | F43: Phone | G43: SimCell (City/County) | I43: ESF 2 | K43: 2 | O43: (Location) microwave dish is out of alignment and unable to communicate over State's radio network to the east of (Location). Need debris cleared on road to (Location) and access to restore microwave hub. Additionally, even with generator power, (State Coordinating Officer) is still unable to access television or wired Internet. Unable to validate messages to the public or access information sites. | Q43: Example - Keane
C44: 0.38125 | D44: 1/0/2020 09:09:00 | F44: Phone | G44: SimCell (City/County) | I44: ESF 4 | K44: 4 | O44: (City/County/State Emergency Management Agency) reports approximately (#) percent of heavy equipment has been damaged in the storm and is unusable across the (Location). Alternative vehicles are needed for victim transport, firefighting, and other functions. | Q44: Example - Keane
C45: 0.38194444 | D45: 1/0/2020 09:10:00 | F45: Phone | G45: SimCell (City/County) | I45: ESF (#) | K45: 6 | O45: Several Hotels like the (Name) (Location) Resort and Spa report that their hotels are being flooded with evacuees, many with pets, and that they do not have room for them. | Q45: Example - Keane
C46: 0.38333333 | D46: 1/0/2020 09:12:00 | F46: Phone | G46: SimCell (City/County) | I46: ESF 4 | K46: 4 | M46: Fire Stations (#s) buildings damaged due to water and wind. Details in perdisrep and truth binder. | O46: Fire station status: Stations (#s) had equipment moved prior to impact, but stations are not functional. (List attached). | Q46: Example - Keane
C47: 0.38541667 | D47: 1/0/2020 09:15:00 | F47: Phone | G47: SimCell (Disaster Mortuary Operational Response Team [DMORT]) | I47: ESF (#) | K47: 8 | M47: Provide additional (Disaster Mortuary Teams) and coordinate with (State Coordinating Officer) to provide for storage of remains. | O47: This is (Name) from the Region (#) (Disaster Mortuary Response Team [DMORT]). We need assistance in identifying the cemeteries in (Location) that were in the inundation zone and how many bodies you believe were exposed. | Q47: Example - Keane
C48: 0.38541667 | D48: 1/0/2020 09:15:00 | F48: Phone | G48: SimCell (City/County) | I48: ESF 3 | K48: 7 | M48: Fuel task force assigned responsibility. Potential tasks for (Defense Logistics Agency) and GSA. | O48: Limited supplies of generator fuel at (#) air fields. Provide an update on when to expect generator fuel resupply. Neighbor (Locations) affected with no fuel/oil. (County) requests additional aviation fuel to resupply airport in support of air frames prestaged in (City) airports prior to landfall. | Q48: Example - Keane
C49: 0.3875 | D49: 1/0/2020 09:18:00 | F49: Phone | G49: SimCell (City and County) | I49: ESF 6 | K49: 6 | O49: We have had reports that many shelters are overcrowded and some evacuees have to be turned away. We can't seem to get a message out on where they should go or how they should get there. Many are trying to go back to their homes, and it may not be safe for them. | Q49: Example - Keane
C50: 0.38888889 | D50: 1/0/2020 09:20:00 | F50: Phone | G50: SimCell (City/County) | I50: ESF (#) | K50: 9 | M50: ESF 9 will coordinate with (State Emergency Management Agency) to provide resources and take appropriate actions. | O50: This is (Name) with (Command and Control [C&C]). I have a (Request for Federal Assistance [RFA]) for a (Urban Search and Rescue [USAR]) team to investigate, locate, and extricate possible survivors. There are a number of missing hikers in the vicinity of (Location) who have been scavenging for food after the storm. | Q50: Example - Keane
C51: 0.38958333 | D51: 1/0/2020 09:21:00 | F51: Phone | G51: SimCell (City/County) | I51: ESF 1 | K51: 1 | O51: (Bridge) is closed pending inspection. There is visual damage (cracks in surface) and foundation compromise. | Q51: Example - Keane
C52: 0.39166667 | D52: 1/0/2020 09:24:00 | F52: Phone | G52: SimCell (Private Sector) | I52: ESF 10 | K52: 10 | O52: Oil pipelines at (Location) are damaged. Spills are minimal, but there is no access to any fuel stored on (Location). | Q52: Example - Keane
C53: 0.39236111 | D53: 1/0/2020 09:25:00 | F53: Phone | G53: SimCell (City/County) | I53: ESF 3 | K53: 3 | O53: The (Location) Ice plant at Pier (#) was destroyed. Combined with the loss of electrical power, the port refrigeration storage capability is unavailable. Estimated time to repair: (#) months. | Q53: Example - Keane
C54: 0.39375 | D54: 1/0/2020 09:27:00 | F54: Phone | G54: SimCell (City/County) | I54: ESF 6 | K54: 6 | O54: The windows have blown out of the (City/State) Convention Center, but it is otherwise still intact. It is unsafe to take in additional people until the glass and debris are cleared. | Q54: Example - Keane
C55: 0.39583333 | D55: 1/0/2020 09:30:00 | K55: 5 | M55: DoD Inject 52: If this does not happen, need to put in a contingency inject. See (Name) for details and additional information for contingency inject. | O55: (State) submits an (Action Request Form [ARF]) to FEMA (Region #) for support with the manifest and movement of evacuees from the assembly areas to the airport of embarkation (APOE) and seaport of embarkation (SPOE). | Q55: Example - Keane
C56: 0.39583333 | D56: 1/0/2020 09:30:00 | F56: Phone | G56: SimCell (City/County) | I56: ESF 6 | K56: 6 | M56: DoD Inject 57: See (Name) for details and additional information. | O56: Locals are requesting tent city shelter space for (#) civilian displaced hurricane victims. | Q56: Example - Keane
C57: 0.39583333 | D57: 1/0/2020 09:30:00 | F57: Phone | G57: SimCell (Private Sector) | I57: ESF 8 | K57: 8 | O57: The blood bank is running low on their blood supplies and is in need of about (#) donors and blood donation supplies to help hospitals donate blood. | Q57: Example - Keane
C58: 0.39583333 | D58: 1/0/2020 09:30:00 | F58: Phone | G58: SimCell (City/County) | I58: ESF 6 | K58: 5 | M58: Details on each neighborhood found in fax to be injected at (Time) and in truth binder. | O58: Housing Update: - So far we have reports of significant damage to residential structures due to wind and flooding in (City/County/State). - Additional reports of damage to residences in (City/County/State). Casualties not known, but search and rescue efforts may be necessary. - (#) homes on (City/County/State) damaged by (Stream) overtopping its banks. - There are four major landslides and mudslides reported in (Location) that have destroyed numerous houses. | Q58: Example - Keane
C59: 0.39791667 | D59: 1/0/2020 09:33:00 | F59: Phone | G59: SimCell (City/County) | I59: ESF 9 | K59: 8 | M59: Details on damage for each location found in fax to be injected later and in truth binder. | O59: The following Urgent Care Centers closed except for triage and stabilization in their parking lots: (Locations); however, (Highway) is still closed. | Q59: Example - Keane
C60: 0.39930556 | D60: 1/0/2020 09:35:00 | F60: Fax | G60: SimCell (City/County) | I60: ESF 8 | K60: 6 | O60: Shelter Update: - LIST shelter sustained severe flood damage in parts of campus. (Location) special needs evacuees need to be transported to another location with the capabilities to care for them. - (Name) Center reports that the shelter is at full capacity, housing (#) evacuees. The facilities are to take care of more special needs patients than they are currently housing, but other evacuees are using those spaces. Can they be moved anywhere? - Over (#) people with pets are looking for shelter. The owners will not leave their pets, where can they go? | Q60: Example - Keane
C61: 0.4 | D61: 1/0/2020 09:36:00 | F61: Fax | G61: SimCell (City and County) | I61: ESF 2 | K61: 2 | O61: (State) telecommunications field unit reports on current assessment of landline and Internet service status: (Location) central office cable vault flooded by storm surge. CO Switch is operational, but (#) cables are wet. Some fiber-based services operational, but unstable. Should be operational within (#) hours. Multiple pole lines down due to high winds. Equipment shortages (poles) and debris cleanup will delay restoration; estimated repair time is (#) weeks. Isolated MXU (remote switching equipment in the field) outages due to power outage. Restoration pending debris clearing and placing of portable generators. Request assistance for debris clearance and generators. At the (Location) (Supply and Logistics), the storm surge caused major flooding to facility. Having problem providing equipment for restoration, may require (#) days for restoration. | Q61: Example - Keane
C62: 0.40208333 | D62: 1/0/2020 09:39:00 | F62: Phone | G62: SimCell (Private Sector) | I62: ESF 1 | K62: 1 | M62: Fax list of ships from (Name) document if asked for specific information. | O62: The (Shipping Companies) have ships queued up for bringing their ships into (City) after the storm. There are (#) ships operating within very high frequency (VHF) range of (City) and are awaiting offload instructions. What is the priority order for these ships? | Q62: Example - Keane
C63: 0.40277778 | D63: 1/0/2020 09:40:00 | F63: Phone | G63: SimCell (City/County) | I63: ESF 6 | K63: 6 | M63: (American Red Cross)/FEMA provide information on organizing. (American Red Cross) International or USAID may be able to assist. | O63: Request technical assistance in organizing encampment and tent cities. Disorganization is creating health, fire, and logistics problems. | Q63: Example - Keane
C64: 0.40416667 | D64: 1/0/2020 09:42:00 | F64: Phone | G64: SimCell (City/County) | I64: ESF 1 | K64: 7 | M64: Provide a status on the (Location). | O64: This is (City/County/State Emergency Management Agency). With the (Location) being damaged, could you provide a timeframe for receiving goods into the port to be distributed here as well as shipped off to the other (Location)? What other options do we have? | Q64: Example - Keane
C65: 0.40625 | D65: 1/0/2020 09:45:00 | F65: Phone | G65: SimCell (Department of Education and Department Operations Center) | I65: ESF 6, 13 | K65: 6, 13 | M65: (Education Officer) (State Coordinating Officer) work with (Department of Education Department Operations Center) to give a timeframe for school re-opening; (Name of School) (Department of Education) | O65: Security for School Shelters Needed: - This is (Name), (High School) Superintendent. Individuals being sheltered at (High School) are ripping out the siding of the building and using it for firewood. That building is on the National Register and is one of the oldest buildings in the county. She would like the shelter moved, the cattle gates closed, and the school secured. - Principal of (Location) is reporting that sheltering individuals are breaking into rooms on campus and occupying these rooms as shelters. - (High School) custodian reports that sheltering individuals are destroying the (State)/Chorus room and are removing valuable (Location) pieces. Custodian requests that the sheltering individuals be moved to (City) Recreation Center. | Q65: Example - Keane
C66: 0.40625 | D66: 1/0/2020 09:45:00 | F66: Phone | G66: SimCell (City/County) | I66: ESF (#) | K66: 6 | O66: The assistant manager at the (Location) reports that about over (#) evacuees are looking for a place to stay but that the hotel is at capacity. Where can they go? The hotel also reported that they are having sewage backups throughout the property. | Q66: Example - Keane
C67: 0.40833333 | D67: 1/0/2020 09:48:00 | F67: Phone | G67: SimCell (City/County) | I67: ESF 7 | K67: 7 | M67: (General Services Announcement) Inject. Logistics coordination. | O67: Task (General Services Administration [GSA]) and DoD to locate potential Federal Operations Staging Areas ([#] acres of land plus [#] square feet of warehouse buildings) on the West Coast and (State). Lease term of six months firm with month-to-month options up to a total of (#) months. | Q67: Example - Keane
C68: 0.40972222 | D68: 1/0/2020 09:50:00 | F68: Phone | G68: SimCell (Private Sector) | I68: ESF 13 | K68: 13 | O68: (Name of Shipping Companies) report that their security perimeter fences were compromised during the storm and that there is evidence that vandalism has occurred on their property. They request security personnel to guard their property until they can get the fence repaired. However, there is a shortage of security guards on (Location) as well as the neighboring (Locations) because of businesses hiring extra security help. | Q68: Example - Keane
C69: 0.41041667 | D69: 1/0/2020 09:51:00 | F69: Phone | G69: SimCell (City/County) | I69: ESF (#) | K69: 8 | O69: (City/County/State Emergency Management Agency) expects casualty numbers to rise. They estimate the window of survivability of those trapped in debris is (#) hours. In addition, the leeward coast reports dozens of bodies washing up on shore and interred remains at cemeteries washed from graves. Exact number not known, but it appears to be several hundred. Request deployment of cadaver dogs, DMORTs and identification of hasty mortuary sites. | Q69: Example - Keane
C70: 0.4125 | D70: 1/0/2020 09:54:00 | F70: Phone | G70: SimCell (County) | I70: ESF 2 | K70: 2 | M70: ESF 2 will coordinate with Department of Accounting and General Services to provide the requested support. | O70: This is (Name) from (City/County/State Emergency Management Agency). We need assistance with repairs to an undersea cable at (Beach Name) Beach reported to be badly damaged that could affect emergency communications severely. | Q70: Example - Keane
C71: 0.41319444 | D71: 1/0/2020 09:55:00 | F71: Phone | G71: SimCell (American Red Cross) | I71: ESF 8 | K71: 6 | M71: Prompt a discussion on whether or not vaccination is necessary since (Department of Hospitals) does not maintain a cache in a nearby location. | O71: This is the Red Cross shelter near the windward area of (Location). We are receiving displaced people who were exposed to and contaminated with sewage that backed up in their area. Evacuees who are physicians here are demanding mass vaccination for hepatitis A/IG injections based on fecal-oral exposure. | Q71: Example - Keane
C72: 0.41458333 | D72: 1/0/2020 09:57:00 | F72: Phone | G72: SimCell (Hospitals) | I72: ESF 8 | K72: 8 | O72: Hospital Update: After (#) hours, hospitals report in that only 800mHz radios and a few satellite phones are operational. (#) other forms of communication are down. Several hospitals are able to triage and treat victims to a limited degree. (#) hospitals held some staff in place. Hospitals are just identifying capabilities and have staff that were held over but will need restaffing in (#) hours. | Q72: Example - Keane
C73: 0.41666667 | D73: 1/0/2020 10:00:00 | K73: 2 | M73: If this does not happen by (Time) need to inject a contingency from counties to initiate the call. Also need to make sure at the end of this call they have established a call schedule with two calls per day. | O73: (State) initiates a call with the counties. | Q73: Example - Keane
C74: 0.41666667 | D74: 1/0/2020 10:00:00 | K74: 5 | M74: DoD Inject 73: See (Name) for details and additional information. | O74: (Area) establishes a Base Support Installation (BSI) at (Airfield). | Q74: Example - Keane
C75: 0.41666667 | D75: 1/0/2020 10:00:00 | F75: Phone | G75: SimCell (City and County) | I75: ESF 10 | K75: 8 | O75: There are numerous pig carcasses floating in the (Location) area creating health concerns to area residents. | Q75: Example - Keane
C76: 0.41666667 | D76: 1/0/2020 10:00:00 | F76: Phone | G76: SimCell (City/County) | I76: ESF 6, 13 | K76: 6, 13 | M76: Cross-check with shelter sheet. | O76: Security problems at several shelters (Schools). Evacuees are stealing blankets and food from each other and large fights are breaking out. Request additional security presence. | Q76: Example - Keane
C77: 0.41875 | D77: 1/0/2020 10:03:00 | F77: Phone | G77: SimCell (Utilities) | I77: ESF 12 | K77: 12 | O77: (Electric Company Name) reports city transmission lines in (City) have sustained damage to several lines, but at least one line section may be functional within a week to service the city area up to (Shopping Center). The subtransmission system has sustained substantial damage to many pole lines, but temporary repairs can be made in some areas. Estimated repair time: Several days to (#) to (#) weeks, depending on the area and severity of damage. Distribution system has sustained substantial damage to many pole lines, but areas with underground facilities have minimal damage. Most residences are without power throughout the (Location). | Q77: Example - Keane
C78: 0.42013889 | D78: 1/0/2020 10:05:00 | F78: Phone | G78: SimCell (DMORT) | I78: ESF (#) | K78: 8 | M78: (Department of Hospitals) provides additional resources and coordinates with (State Coordinating Officer) to store remains and establish collection points/plans. | O78: This is (Location) (Disaster Mortuary Response Team [DMORT]). We just arrived at the (Cemetery) (Address). We haven't reached any other sites and are already overwhelmed with the handling and identification of the exposed bodies. We estimate thousands of exposed bodies and will need assistance with the collection of the exposed. | Q78: Example - Keane
C79: 0.42083333 | D79: 1/0/2020 10:06:00 | F79: Phone | G79: SimCell (City/County) | I79: ESF 4 | K79: 4 | M79: List location. | O79: There are reports of a high rise fire in (Location), and there is no water at the hydrant. Are there any Federal resources available to contain this fire? | Q79: Example - Keane
C80: 0.42291667 | D80: 1/0/2020 10:09:00 | F80: Phone | G80: GSA (General Services Administration) | I80: ESF 7 | K80: 7 | M80: (General Service Administration) Inject. This is to supplement ESF 3 mission. Logistics will provide locations for distribution. | O80: Task (General Services Administration [GSA]) to provide bottled water in small containers of approximately (#) liter each. Estimated quantities of (#) liters per day for a period of (#) days. Have these been tasked to you yet? | Q80: Example - Keane
C81: 0.42361111 | D81: 1/0/2020 10:10:00 | F81: Phone | G81: SimCell (City/County) | I81: Emergency Support Function (ESF) 1 | K81: 12 | M81: Department of Defense (DoD) Inject 20: See (Name) for details and additional information. | O81: Locals request field storage containers be transported to designated locations to augment fuel storage capability at essential sites. | Q81: Example - Keane
C82: 0.42361111 | D82: 1/0/2020 10:10:00 | F82: Phone | G82: SimCell (Private Sector) | I82: ESF 11 | K82: 11 | O82: The (#) concrete grain silos at Piers (#) and (#) were not structurally affected by the storm based on a cursory visual inspection, but a more detailed secondary inspection is needed before they can be put back into operation. (Food Service) reports that this will have an enormous impact on their operations. They are want to know if they can process the grain stored in the silos or if it must be destroyed. | Q82: Example - Keane
C83: 0.425 | D83: 1/0/2020 10:12:00 | F83: Phone | G83: SimCell (City/County) | I83: ESF (#) | K83: 11 | M83: ESF 19 will coordinate with (State Emergency Management Agency) to provide requested resources. | O83: This is (Name) from (City/County/State Emergency Management Agency). There are hundreds of stray animals running free in various areas of (City) and the (Location). Could you please coordinate this request to provide any assistance needed to catch and shelter these animals so they can be reunited with their owners. | Q83: Example - Keane
C84: 0.42708333 | D84: 1/0/2020 10:15:00 | F84: Phone | G84: SimCell (City and County) | I84: ESF 8 | K84: 6 | M84: Coordinate to provide requested resource. | O84: We will be needing additional mental health support at shelters across the (City/State) to help residents and visitors deal with the trauma of the recent few days. How many can we expect to obtain, and when? | Q84: Example - Keane
C85: 0.42708333 | D85: 1/0/2020 10:15:00 | F85: Phone | G85: SimCell (Private Sector) | I85: ESF 3 | K85: 3 | M85: Unable to make repairs to damaged roads. | O85: (Plant Name) unable to make asphalt at plant in (Location) due to hurricane damage. In addition, the (Name) Asphalt facility located between Piers (#) and (#) at (Location) Harbor is also damaged. Expected time to repair both facilities is (#) months. | Q85: Example - Keane
C86: 0.42916667 | D86: 1/0/2020 10:18:00 | F86: Phone | G86: SimCell (City County) | I86: ESF 1 | K86: 1 | O86: (City/County/State Emergency Management Agency) volunteers report sections of (Highway) in the (Area) are covered with sand and debris. In addition, mud, debris, and standing water have caused road closures in (Locations). Area residents are requesting help in clearing the mud and debris. Transportation road crews have been requested to assist with debris clearance. | Q86: Example - Keane
C87: 0.43055556 | D87: 1/0/2020 10:20:00 | F87: Phone | G87: SimCell (Private Sector) | I87: ESF (#) | K87: 13 | O87: Hotel Update: The hotel manager of the (Hotel) reports that guests want to know where else they can stay. (Hotel) has reported that their generators are running out of fuel and will not last more than (#) hours. | Q87: Example - Keane
C88: 0.43125 | D88: 1/0/2020 10:21:00 | F88: Phone | G88: SimCell (City and County) | I88: ESF 6 | K88: 6 | M88: ESF 6 will coordinate with (City/County Emergency Management Agency) to provide tents to various locations around the (City/County/State). | O88: This is (Name) from (City/County/State Emergency Management Agency) contacting you with a (Request for Federal Assistance [RFA]) for support of (#) residents that have been displaced in (Location). Tents and other sources of sheltering are needed for residents. | Q88: Example - Keane
C89: 0.43333333 | D89: 1/0/2020 10:24:00 | F89: Phone | G89: SimCell (City/County) | I89: ESF 7 | K89: 7 | M89: ESF 7 will coordinate with (State Emergency Management Agency) to provide requested resources. | O89: This is (Name) from (City) requesting (#) bulldozers to assist in debris cleanup in downtown area of (City). | Q89: Example - Keane
C90: 0.43402778 | D90: 1/0/2020 10:25:00 | F90: Fax | G90: SimCell (City/County) | I90: ESF 6 | K90: 6 | M90: Details on damage for each location are found in truth binder. | O90: Shelter Update: The following shelters report that they only have enough food to sustain the people staying at their locations for another (#) hours. (Name of Schools) need food to support their current sheltered populations. | Q90: Example - Keane
C91: 0.43541667 | D91: 1/0/2020 10:27:00 | F91: Phone | G91: SimCell (Political) | I91: ESF 15 | K91: 15 | M91: Provide information or a time when it will be provided. | O91: This is (Name), Chief of Staff to U.S. Senator (Name). When can we expect a formal briefing on the situation for the (Location)? | Q91: Example - Keane
C92: 0.4375 | D92: 1/0/2020 10:30:00 | F92: Phone | G92: SimCell (Health and Hospitals) | I92: ESF 8 | K92: 2 | M92: DoD Inject 140: See (Name) for details and additional information. | O92: (Hospital) is requesting communication support. | Q92: Example - Keane
C93: 0.4375 | D93: 1/0/2020 10:30:00 | F93: Phone | G93: SimCell (City/County) | I93: ESF 10 | K93: 10 | O93: On the (Location), opposite Pier (#) (Location), sewer, waste oil, and compressed air pipelines have been punctured. The waste oil pipeline has suffered a minor leak, and a small sheen is noticeable. | Q93: Example - Keane
C94: 0.4375 | D94: 1/0/2020 10:30:00 | F94: Phone | G94: SimCell (City/County) | I94: ESF 9 | K94: 4, 9 | O94: (City Fire Department [FD]) reports a house collapsed on neighborhood rescuers while trying to extract trapped family members and neighbors. (#) dead, over (#) injured. Search and rescue assistance is needed. | Q94: Example - Keane
C95: 0.43958333 | D95: 1/0/2020 10:33:00 | F95: Phone | G95: SimCell (City/County) | I95: ESF 6 | K95: 5 | O95: (Area) stream topped its banks and flooded (Elementary School). | Q95: Example - Keane
C96: 0.44097222 | D96: 1/0/2020 10:35:00 | F96: Fax | G96: SimCell (City/County) | I96: ESF 1 | K96: 1 | O96: Port Update: - The (Location) located at the rear of Pier (#) suffered significant damage from wind and inundation. Bottom floors destroyed, and people are present trying to steal goods from the damaged stores. Additional security is needed to seal this building from looters. - Pier (#) has suffered minor damages. Several (Name) trees lie across the piers and will need to be removed. Additional debris is blocking the roadway directly behind the piers and the (location). Will need chainsaws and heavy equipment to remove the vegetative debris. - Debris left by the retreating flood (storm surge) waters blocks access in and out of Pier (#). - Pier (#) suffered severe structural damage to the area used by the Coast Guard for shuttle boat service to the Main base on (Location). - Mud, sand, and other debris left from retreating flood waters has created hazards at entry points to Pier (#). The South side of Pier (#) has been washed out and is unusable. | Q96: Example - Keane
C97: 0.44166667 | D97: 1/0/2020 10:36:00 | F97: Fax | G97: SimCell (City/County) | I97: ESF 2 | K97: 2 | O97: (#) percent of the cellular network is inoperable because of relay tower outages. Text message capability is extremely sporadic, and no voice communications are available. Approximately (#) percent of cell sites in (Location) have backup battery or generator power available. (#) percent of sites and towers are down because of flooding and wind damage, with debris blocking access for repairs and generator startups for the site. (Communications Company) cellular service reports that the MCS (mobile cellular switch) is on generator backup with only (#) days of fuel. Several cell sites in (Location) are down because of transport issues (either [Name] Telcom/Time Warner/AT&T Microwave). Need estimate from them on time to recovery. There are tower failures affecting microwave hops. Microwave dish alignment or cellular antenna failures. Verizon, T-Mobile, Sprint/Nextel all report widespread outages, time to repair is unknown. Debris blocks many cell relay tower locations, making repairs difficult. | Q97: Example - Keane
C98: 0.44375 | D98: 1/0/2020 10:39:00 | F98: Phone | G98: SimCell (Utilities) | I98: ESF 12 | K98: 12 | M98: Details on damage for each location are found in truth binder and should be called in as updates or faxed if players do not call back for more detail. | O98: (Electric Company Name) reports the entire (Location) power outage will take approximately (#) days to repair and reports there is damage to the following power plants: (Locations). Extensive damage throughout (Location), downed poles and debris issues are hindering access to areas. | Q98: Example - Keane
C99: 0.44444444 | D99: 1/0/2020 10:40:00 | F99: Phone | G99: SimCell (City/County) | I99: ESF 8 | K99: 8 | O99: Hundreds of people are seeking medical care at fire stations, emergency rooms, etc. for cuts, puncture wounds, etc. We do not have enough medics to triage these individuals or bandages/splints/etc. | Q99: Example - Keane
C100: 0.44583333 | D100: 1/0/2020 10:42:00 | F100: Phone | G100: SimCell (Governor's Office) | I100: ESF 15 | K100: 15 | O100: This is the Governor's Office calling.(He/she) would like talking points on the temporary housing strategy to transition from tents on lawns to something more livable. Need talking points by (Time). | Q100: Example - Keane
...

Sheet PRINT_SMALL
A1: MSEL # | B1: STATUS | C1: DTG | D1: SUBJECT | E1: INJECT MODE: / SEND FROM: / INJECTED BY: / SEND TO: | F1: STORYLINE / DESCRIPTION / NOTES & REMARKS / BACKGROUND INFO | G1: IMPLEMENTER | H1: EXPECTED ACTIONS | I1: AUTHOR
A2: ='Excercise - Al '!A2 -> 1 | B2: Ready to Inject | C2: ='Excercise - Al '!E2 -> 40298.208 | D2: =IF('Excercise - Al '!F2<>0,'Excercise - Al '!F2,"") -> 31st CHEM BDE - Notifies select staff | E2: =IF('Excercise - Al '!G2<>"","MODE: "&'Excercise - Al '!G2,"")&IF('Excercise - Al '!H2<>""," FROM: "&'Excercise - Al '!H2,"")&IF('Excercise - Al '!I2<>""," INJECTED BY: "&'Excercise - Al '!I2,"")&IF('Excercise - Al '!J2<>""," SEND TO: "&'Excercise - Al '!J2,"") -> MODE: Not Injected | F2: =IF('Excercise - Al '!K2<>"","STORYLINE: "&'Excercise - Al '!K2,"")&IF('Excercise - Al '!M2<>""," DESCRIPTION: "&'Excercise - Al '!M2,"")&IF('Excercise - Al '!O2<>""," NOTES/REMARKS: "&'Excercise - Al '!O2,"")&IF('Excercise - Al '!Q2<>""," BACKGROUND INFO: "&'Excercise - Al '!Q2,"") | G2: =IF('Excercise - Al '!P2<>"","IMPLEMENTER: "&'Excercise - Al '!P2,"") | H2: =IF('Excercise - Al '!N2<>"","EXPECTED ACTIONS: "&'Excercise - Al '!N2,"") | I2: ='Excercise - Al '!R2 -> Napier
A3: ='Excercise - Al '!A3 -> 2 | C3: ='Excercise - Al '!E3 -> 40299.167 | D3: =IF('Excercise - Al '!F3<>0,'Excercise - Al '!F3,"") -> INFO | E3: =IF('Excercise - Al '!G3<>"","MODE: "&'Excercise - Al '!G3,"")&IF('Excercise - Al '!H3<>""," FROM: "&'Excercise - Al '!H3,"")&IF('Excercise - Al '!I3<>""," INJECTED BY: "&'Excercise - Al '!I3,"")&IF('Excercise - Al '!J3<>""," SEND TO: "&'Excercise - Al '!J3,"") -> MODE: Email FROM: Simcell - National Hurricane Center INJECTED BY: KEANE SEND TO: JOC, All | F3: =IF('Excercise - Al '!K3<>"","STORYLINE: "&'Excercise - Al '!K3,"")&IF('Excercise - Al '!M3<>""," DESCRIPTION: "&'Excercise - Al '!M3,"")&IF('Excercise - Al '!O3<>""," NOTES/REMARKS: "&'Excercise - Al '!O3,"")&IF('Excercise - Al '!Q3<>""," BACKGROUND INFO: "&'Excercise - Al '!Q3,"") -> STORYLINE: Tropical Depression One Forms DESCRIPTION: Tropical Depression One Forms | G3: =IF('Excercise - Al '!P3<>"","IMPLEMENTER: "&'Excercise - Al '!P3,"") -> IMPLEMENTER: On 01 May, 0400 HRS CDT, The National Hurricane Center issues Tropical Depression Advisory "One". Current Location 14.5 N 74.1 W Max Sustained Wind 30mph | H3: =IF('Excercise - Al '!N3<>"","EXPECTED ACTIONS: "&'Excercise - Al '!N3,"") | I3: ='Excercise - Al '!R3 -> Keane
A4: ='Excercise - Al '!A4 -> 3 | C4: ='Excercise - Al '!E4 -> 40299.208 | D4: =IF('Excercise - Al '!F4<>0,'Excercise - Al '!F4,"") -> 31st CHEM BDE - Telecon with unit CDRs and issue verbal WARNO | E4: =IF('Excercise - Al '!G4<>"","MODE: "&'Excercise - Al '!G4,"")&IF('Excercise - Al '!H4<>""," FROM: "&'Excercise - Al '!H4,"")&IF('Excercise - Al '!I4<>""," INJECTED BY: "&'Excercise - Al '!I4,"")&IF('Excercise - Al '!J4<>""," SEND TO: "&'Excercise - Al '!J4,"") -> MODE: Not Injected | F4: =IF('Excercise - Al '!K4<>"","STORYLINE: "&'Excercise - Al '!K4,"")&IF('Excercise - Al '!M4<>""," DESCRIPTION: "&'Excercise - Al '!M4,"")&IF('Excercise - Al '!O4<>""," NOTES/REMARKS: "&'Excercise - Al '!O4,"")&IF('Excercise - Al '!Q4<>""," BACKGROUND INFO: "&'Excercise - Al '!Q4,"") | G4: =IF('Excercise - Al '!P4<>"","IMPLEMENTER: "&'Excercise - Al '!P4,"") | H4: =IF('Excercise - Al '!N4<>"","EXPECTED ACTIONS: "&'Excercise - Al '!N4,"") | I4: ='Excercise - Al '!R4 -> Napier
A5: ='Excercise - Al '!A5 -> 4 | C5: ='Excercise - Al '!E5 -> 40299.208 | D5: =IF('Excercise - Al '!F5<>0,'Excercise - Al '!F5,"") -> 31st CHEM BDE - Test alert roster of key personnel and for the 1165th and 690th | E5: =IF('Excercise - Al '!G5<>"","MODE: "&'Excercise - Al '!G5,"")&IF('Excercise - Al '!H5<>""," FROM: "&'Excercise - Al '!H5,"")&IF('Excercise - Al '!I5<>""," INJECTED BY: "&'Excercise - Al '!I5,"")&IF('Excercise - Al '!J5<>""," SEND TO: "&'Excercise - Al '!J5,"") -> MODE: Not Injected | F5: =IF('Excercise - Al '!K5<>"","STORYLINE: "&'Excercise - Al '!K5,"")&IF('Excercise - Al '!M5<>""," DESCRIPTION: "&'Excercise - Al '!M5,"")&IF('Excercise - Al '!O5<>""," NOTES/REMARKS: "&'Excercise - Al '!O5,"")&IF('Excercise - Al '!Q5<>""," BACKGROUND INFO: "&'Excercise - Al '!Q5,"") | G5: =IF('Excercise - Al '!P5<>"","IMPLEMENTER: "&'Excercise - Al '!P5,"") | H5: =IF('Excercise - Al '!N5<>"","EXPECTED ACTIONS: "&'Excercise - Al '!N5,"") | I5: ='Excercise - Al '!R5 -> Napier
A6: ='Excercise - Al '!A6 -> 5 | C6: ='Excercise - Al '!E6 -> 40299.417 | D6: =IF('Excercise - Al '!F6<>0,'Excercise - Al '!F6,"") -> INFO | E6: =IF('Excercise - Al '!G6<>"","MODE: "&'Excercise - Al '!G6,"")&IF('Excercise - Al '!H6<>""," FROM: "&'Excercise - Al '!H6,"")&IF('Excercise - Al '!I6<>""," INJECTED BY: "&'Excercise - Al '!I6,"")&IF('Excercise - Al '!J6<>""," SEND TO: "&'Excercise - Al '!J6,"") -> MODE: Email FROM: Simcell - National Hurricane Center INJECTED BY: KEANE SEND TO: JOC, All | F6: =IF('Excercise - Al '!K6<>"","STORYLINE: "&'Excercise - Al '!K6,"")&IF('Excercise - Al '!M6<>""," DESCRIPTION: "&'Excercise - Al '!M6,"")&IF('Excercise - Al '!O6<>""," NOTES/REMARKS: "&'Excercise - Al '!O6,"")&IF('Excercise - Al '!Q6<>""," BACKGROUND INFO: "&'Excercise - Al '!Q6,"") -> STORYLINE: Tropical Storm Al Update 2 DESCRIPTION: Tropical Storm Al Update 2 | G6: =IF('Excercise - Al '!P6<>"","IMPLEMENTER: "&'Excercise - Al '!P6,"") -> IMPLEMENTER: _x000D_...FIRST TROPICAL STORM OF THE SEASON...AL NEARS THE COAST OF NICARAGUA..._x000D__x000D_SUMMARY OF 1100 AM EDT...1500 UTC...INFORMATION_x000D_-----------------------------------------------_x000D_LOCATION...14.9N 74.9W_x000D_ABOUT 220 MILES...354 KM...SOUTH SOUTHEAST OF KINGSTON JAMAICA _x000D_ABOUT 280 MILES...450 KM...NORTH OF BARRANQUILLA COLUMBIA _x000D_ABOUT 510 MILES...820 KM...NORTHEAST OF PANAMA CITY PANAMA_x000D_MAXIMUM SUSTAINED WINDS...45 MPH...39 KM/HR_x000D_PRESENT MOVEMENT...WNW OR 276 DEGREES AT 15 MPH...24 KM/HR_x000D_MINIMUM CENTRAL PRESSURE...999 MB...29.5 INCHES_x000D__x000D_ | H6: =IF('Excercise - Al '!N6<>"","EXPECTED ACTIONS: "&'Excercise - Al '!N6,"") | I6: ='Excercise - Al '!R6 -> Keane
A7: ='Excercise - Al '!A7 -> 6 | C7: ='Excercise - Al '!E7 -> 40299.667 | D7: =IF('Excercise - Al '!F7<>0,'Excercise - Al '!F7,"") -> INFO | E7: =IF('Excercise - Al '!G7<>"","MODE: "&'Excercise - Al '!G7,"")&IF('Excercise - Al '!H7<>""," FROM: "&'Excercise - Al '!H7,"")&IF('Excercise - Al '!I7<>""," INJECTED BY: "&'Excercise - Al '!I7,"")&IF('Excercise - Al '!J7<>""," SEND TO: "&'Excercise - Al '!J7,"") -> MODE: Email FROM: Simcell - National Hurricane Center INJECTED BY: KEANE SEND TO: JOC, All | F7: =IF('Excercise - Al '!K7<>"","STORYLINE: "&'Excercise - Al '!K7,"")&IF('Excercise - Al '!M7<>""," DESCRIPTION: "&'Excercise - Al '!M7,"")&IF('Excercise - Al '!O7<>""," NOTES/REMARKS: "&'Excercise - Al '!O7,"")&IF('Excercise - Al '!Q7<>""," BACKGROUND INFO: "&'Excercise - Al '!Q7,"") -> STORYLINE: Tropical Storm Al Update 3 DESCRIPTION: Tropical Storm Al Update 3 | G7: =IF('Excercise - Al '!P7<>"","IMPLEMENTER: "&'Excercise - Al '!P7,"") -> IMPLEMENTER: _x000D_...TROPICAL STORM AL STRENGTHENS AS IT NEARS THE COAST OF NICARAGUA..._x000D__x000D_SUMMARY OF 1700 AM EDT...2100 UTC...INFORMATION_x000D_-----------------------------------------------_x000D_LOCATION...15.30 N 76.20 W_x000D_ABOUT 188 MILES...303 KM...167 DEGREES...SOUTH-SOUTHEAST OF KINGSTON JAMAICA _x000D_ABOUT 312 MILES...502 KM...343 DEGREES...NORTH-NORTHWEST OF BARRANQUILLA COLUMBIA _x000D_MAXIMUM SUSTAINED WINDS...60 MPH...99 KM/HR_x000D_PRESENT MOVEMENT...WESTERLY OR 275 DEGREES AT 10 MPH...16 KM/HR_x000D_MINIMUM CENTRAL PRESSURE...997 MB...29.44 INCHES_x000D__x000D_ | H7: =IF('Excercise - Al '!N7<>"","EXPECTED ACTIONS: "&'Excercise - Al '!N7,"") | I7: ='Excercise - Al '!R7 -> Keane
A8: ='Excercise - Al '!A8 -> 7 | C8: ='Excercise - Al '!E8 -> 40299.917 | D8: =IF('Excercise - Al '!F8<>0,'Excercise - Al '!F8,"") -> INFO | E8: =IF('Excercise - Al '!G8<>"","MODE: "&'Excercise - Al '!G8,"")&IF('Excercise - Al '!H8<>""," FROM: "&'Excercise - Al '!H8,"")&IF('Excercise - Al '!I8<>""," INJECTED BY: "&'Excercise - Al '!I8,"")&IF('Excercise - Al '!J8<>""," SEND TO: "&'Excercise - Al '!J8,"") -> MODE: Email FROM: Simcell - National Hurricane Center INJECTED BY: KEANE SEND TO: JOC, All | F8: =IF('Excercise - Al '!K8<>"","STORYLINE: "&'Excercise - Al '!K8,"")&IF('Excercise - Al '!M8<>""," DESCRIPTION: "&'Excercise - Al '!M8,"")&IF('Excercise - Al '!O8<>""," NOTES/REMARKS: "&'Excercise - Al '!O8,"")&IF('Excercise - Al '!Q8<>""," BACKGROUND INFO: "&'Excercise - Al '!Q8,"") -> STORYLINE: Tropical Storm Al Update 4 DESCRIPTION: Tropical Storm Al Update 4 | G8: =IF('Excercise - Al '!P8<>"","IMPLEMENTER: "&'Excercise - Al '!P8,"") -> IMPLEMENTER: _x000D_...AL BECOMES A HURRICANE AS IT NEARS THE NORTH COAST OF NICARAGUA..._x000D__x000D_SUMMARY OF 1100 PM EDT...0300 UTC...INFORMATION_x000D_-----------------------------------------------_x000D_LOCATION...15.50 N 77.10 W_x000D_ABOUT 172 MILES...277 KM...SOUTH SOUTHEAST OF KINGSTON JAMAICA _x000D_ABOUT 366 MILES...589 KM...NORTH-NORTHWEST OF CARTAGENA COLUMBIA _x000D_MAXIMUM SUSTAINED WINDS...85 MPH...137 KM/HR_x000D_PRESENT MOVEMENT...WNW OR 284 DEGREES AT 12 MPH...19 KM/HR_x000D_MINIMUM CENTRAL PRESSURE...980 MB...28.94 INCHES_x000D__x000D_ | H8: =IF('Excercise - Al '!N8<>"","EXPECTED ACTIONS: "&'Excercise - Al '!N8,"") | I8: ='Excercise - Al '!R8 -> Keane
A9: ='Excercise - Al '!A9 -> 8 | C9: ='Excercise - Al '!E9 -> 40300.167 | D9: =IF('Excercise - Al '!F9<>0,'Excercise - Al '!F9,"") -> INFO | E9: =IF('Excercise - Al '!G9<>"","MODE: "&'Excercise - Al '!G9,"")&IF('Excercise - Al '!H9<>""," FROM: "&'Excercise - Al '!H9,"")&IF('Excercise - Al '!I9<>""," INJECTED BY: "&'Excercise - Al '!I9,"")&IF('Excercise - Al '!J9<>""," SEND TO: "&'Excercise - Al '!J9,"") -> MODE: Email FROM: Simcell - National Hurricane Center INJECTED BY: KEANE SEND TO: JOC, All | F9: =IF('Excercise - Al '!K9<>"","STORYLINE: "&'Excercise - Al '!K9,"")&IF('Excercise - Al '!M9<>""," DESCRIPTION: "&'Excercise - Al '!M9,"")&IF('Excercise - Al '!O9<>""," NOTES/REMARKS: "&'Excercise - Al '!O9,"")&IF('Excercise - Al '!Q9<>""," BACKGROUND INFO: "&'Excercise - Al '!Q9,"") -> STORYLINE: Tropical Storm Al Update 4 DESCRIPTION: Tropical Storm Al Update 4 | G9: =IF('Excercise - Al '!P9<>"","IMPLEMENTER: "&'Excercise - Al '!P9,"") -> IMPLEMENTER: _x000D_...AL REMAINS A CAT 1 HURRICANE MOVING EAST TO WEST...SOUTH OF JAMAICA...GAINING STRENGTH..._x000D__x000D_SUMMARY OF 0500 AM EDT...0900 UTC...INFORMATION_x000D_-----------------------------------------------_x000D_LOCATION...15.90 N 78.10 W_x000D_ABOUT 159 MILES... 255 KM... SOUTH NEGRIL JAMAICA _x000D_ABOUT 317 MILES... 510 KM... SOUTHEAST OF GEORGE TOWN CAYMAN ISLANDS _x000D_ABOUT 375 MILES... 604 KM... EAST-NORTHEAST OF PUERTO CABEZAS NICARAGUA _x000D_MAXIMUM SUSTAINED WINDS...85 MPH...137 KM/HR_x000D_PRESENT MOVEMENT...WNW OR 282 DEGREES AT 12 MPH...19 KM/HR_x000D_MINIMUM CENTRAL PRESSURE...979 MB...28.91 INCHES_x000D__x000D_ | H9: =IF('Excercise - Al '!N9<>"","EXPECTED ACTIONS: "&'Excercise - Al '!N9,"") | I9: ='Excercise - Al '!R9 -> Keane
A10: ='Excercise - Al '!A10 -> 9 | C10: ='Excercise - Al '!E10 -> 40300.208 | D10: =IF('Excercise - Al '!F10<>0,'Excercise - Al '!F10,"") -> INFO | E10: =IF('Excercise - Al '!G10<>"","MODE: "&'Excercise - Al '!G10,"")&IF('Excercise - Al '!H10<>""," FROM: "&'Excercise - Al '!H10,"")&IF('Excercise - Al '!I10<>""," INJECTED BY: "&'Excercise - Al '!I10,"")&IF('Excercise - Al '!J10<>""," SEND TO: "&'Excercise - Al '!J10,"") | F10: =IF('Excercise - Al '!K10<>"","STORYLINE: "&'Excercise - Al '!K10,"")&IF('Excercise - Al '!M10<>""," DESCRIPTION: "&'Excercise - Al '!M10,"")&IF('Excercise - Al '!O10<>""," NOTES/REMARKS: "&'Excercise - Al '!O10,"")&IF('Excercise - Al '!Q10<>""," BACKGROUND INFO: "&'Excercise - Al '!Q10,"") -> STORYLINE: Tropical Storm Al Update 5 DESCRIPTION: Tropical Storm Al Update 5 | G10: =IF('Excercise - Al '!P10<>"","IMPLEMENTER: "&'Excercise - Al '!P10,"") | H10: =IF('Excercise - Al '!N10<>"","EXPECTED ACTIONS: "&'Excercise - Al '!N10,"") | I10: ='Excercise - Al '!R10 -> Jenne
A11: ='Excercise - Al '!A11 -> 10 | C11: ='Excercise - Al '!E11 -> 40300.417 | D11: =IF('Excercise - Al '!F11<>0,'Excercise - Al '!F11,"") -> INFO | E11: =IF('Excercise - Al '!G11<>"","MODE: "&'Excercise - Al '!G11,"")&IF('Excercise - Al '!H11<>""," FROM: "&'Excercise - Al '!H11,"")&IF('Excercise - Al '!I11<>""," INJECTED BY: "&'Excercise - Al '!I11,"")&IF('Excercise - Al '!J11<>""," SEND TO: "&'Excercise - Al '!J11,"") -> MODE: Email FROM: Simcell - National Hurricane Center INJECTED BY: KEANE SEND TO: JOC, All | F11: =IF('Excercise - Al '!K11<>"","STORYLINE: "&'Excercise - Al '!K11,"")&IF('Excercise - Al '!M11<>""," DESCRIPTION: "&'Excercise - Al '!M11,"")&IF('Excercise - Al '!O11<>""," NOTES/REMARKS: "&'Excercise - Al '!O11,"")&IF('Excercise - Al '!Q11<>""," BACKGROUND INFO: "&'Excercise - Al '!Q11,"") -> STORYLINE: Tropical Storm Al Update 6 DESCRIPTION: Tropical Storm Al Update 6 | G11: =IF('Excercise - Al '!P11<>"","IMPLEMENTER: "&'Excercise - Al '!P11,"") -> IMPLEMENTER: _x000D_... HURRICANE AL TRACKS TOWARD THE YUCATAN..._x000D__x000D_SUMMARY OF 1100 AM EDT...0900 UTC...INFORMATION_x000D_-----------------------------------------------_x000D_LOCATION...16.3N 79.0W_x000D_ABOUT 257 MILES... 321 KM...SOUTH SOUTHEAST OF GEORGE TOWN CAYMAN ISLANDS _x000D_ABOUT 137 MILES... 222 KM...SOUTH OF NEGRIL JAMAICA _x000D_MAXIMUM SUSTAINED WINDS...85 MPH...137 KM/HR_x000D_PRESENT MOVEMENT...WNW OR 284 DEGREES AT 12 MPH...19 KM/HR_x000D_MINIMUM CENTRAL PRESSURE...977 MB...28.85 INCHES_x000D__x000D_ | H11: =IF('Excercise - Al '!N11<>"","EXPECTED ACTIONS: "&'Excercise - Al '!N11,"") | I11: ='Excercise - Al '!R11 -> Keane
A12: ='Excercise - Al '!A12 -> 11 | C12: ='Excercise - Al '!E12 -> 40300.5 | D12: =IF('Excercise - Al '!F12<>0,'Excercise - Al '!F12,"") -> RFI | E12: =IF('Excercise - Al '!G12<>"","MODE: "&'Excercise - Al '!G12,"")&IF('Excercise - Al '!H12<>""," FROM: "&'Excercise - Al '!H12,"")&IF('Excercise - Al '!I12<>""," INJECTED BY: "&'Excercise - Al '!I12,"")&IF('Excercise - Al '!J12<>""," SEND TO: "&'Excercise - Al '!J12,"") -> MODE: Email FROM: Each Task Force INJECTED BY: TF S2 SEND TO: JOC, J2 | F12: =IF('Excercise - Al '!K12<>"","STORYLINE: "&'Excercise - Al '!K12,"")&IF('Excercise - Al '!M12<>""," DESCRIPTION: "&'Excercise - Al '!M12,"")&IF('Excercise - Al '!O12<>""," NOTES/REMARKS: "&'Excercise - Al '!O12,"")&IF('Excercise - Al '!Q12<>""," BACKGROUND INFO: "&'Excercise - Al '!Q12,"") -> DESCRIPTION: Weather Update/Storm Track | G12: =IF('Excercise - Al '!P12<>"","IMPLEMENTER: "&'Excercise - Al '!P12,"") -> IMPLEMENTER: Weather RFI from Task Force to J2 | H12: =IF('Excercise - Al '!N12<>"","EXPECTED ACTIONS: "&'Excercise - Al '!N12,"") -> EXPECTED ACTIONS: J2 Provides latest Weather and Storm Track to the TFs | I12: ='Excercise - Al '!R12 -> Houlton
A13: ='Excercise - Al '!A13 -> 12 | C13: ='Excercise - Al '!E13 -> 40300.667 | D13: =IF('Excercise - Al '!F13<>0,'Excercise - Al '!F13,"") -> INFO | E13: =IF('Excercise - Al '!G13<>"","MODE: "&'Excercise - Al '!G13,"")&IF('Excercise - Al '!H13<>""," FROM: "&'Excercise - Al '!H13,"")&IF('Excercise - Al '!I13<>""," INJECTED BY: "&'Excercise - Al '!I13,"")&IF('Excercise - Al '!J13<>""," SEND TO: "&'Excercise - Al '!J13,"") -> MODE: Email FROM: Simcell - National Hurricane Center INJECTED BY: KEANE SEND TO: JOC, All | F13: =IF('Excercise - Al '!K13<>"","STORYLINE: "&'Excercise - Al '!K13,"")&IF('Excercise - Al '!M13<>""," DESCRIPTION: "&'Excercise - Al '!M13,"")&IF('Excercise - Al '!O13<>""," NOTES/REMARKS: "&'Excercise - Al '!O13,"")&IF('Excercise - Al '!Q13<>""," BACKGROUND INFO: "&'Excercise - Al '!Q13,"") -> STORYLINE: Tropical Storm Al Update 7 DESCRIPTION: Tropical Storm Al Update 7 | G13: =IF('Excercise - Al '!P13<>"","IMPLEMENTER: "&'Excercise - Al '!P13,"") -> IMPLEMENTER: _x000D_... HURRICANE AL TRACKS TOWARD THE YUCATAN...AS A CATEGORY TWO HURRICANE..._x000D__x000D_SUMMARY OF 0500 AM EDT...0900 UTC...INFORMATION_x000D_-----------------------------------------------_x000D_LOCATION...16.7N 80.0W_x000D_ABOUT 199 MILES... 321 KM...SOUTH SOUTHEAST OF GEORGE TOWN CAYMAN ISLANDS _x000D_ABOUT 150 MILES... 241 KM...NEGRIL JAMAICA _x000D_MAXIMUM SUSTAINED WINDS...105 MPH...169 KM/HR_x000D_PRESENT MOVEMENT...WNW OR 292 DEGREES AT 12 MPH...19 KM/HR_x000D_MINIMUM CENTRAL PRESSURE...968 MB...28.59 INCHES_x000D__x000D_ | H13: =IF('Excercise - Al '!N13<>"","EXPECTED ACTIONS: "&'Excercise - Al '!N13,"") | I13: ='Excercise - Al '!R13 -> Keane
A14: ='Excercise - Al '!A14 -> 13 | C14: ='Excercise - Al '!E14 -> 40300.917 | D14: =IF('Excercise - Al '!F14<>0,'Excercise - Al '!F14,"") -> INFO | E14: =IF('Excercise - Al '!G14<>"","MODE: "&'Excercise - Al '!G14,"")&IF('Excercise - Al '!H14<>""," FROM: "&'Excercise - Al '!H14,"")&IF('Excercise - Al '!I14<>""," INJECTED BY: "&'Excercise - Al '!I14,"")&IF('Excercise - Al '!J14<>""," SEND TO: "&'Excercise - Al '!J14,"") -> MODE: Email FROM: Simcell - National Hurricane Center INJECTED BY: KEANE SEND TO: JOC, All | F14: =IF('Excercise - Al '!K14<>"","STORYLINE: "&'Excercise - Al '!K14,"")&IF('Excercise - Al '!M14<>""," DESCRIPTION: "&'Excercise - Al '!M14,"")&IF('Excercise - Al '!O14<>""," NOTES/REMARKS: "&'Excercise - Al '!O14,"")&IF('Excercise - Al '!Q14<>""," BACKGROUND INFO: "&'Excercise - Al '!Q14,"") -> STORYLINE: Tropical Storm Al Update 8 DESCRIPTION: Tropical Storm Al Update 8 | G14: =IF('Excercise - Al '!P14<>"","IMPLEMENTER: "&'Excercise - Al '!P14,"") -> IMPLEMENTER: _x000D_... HURRICANE AL GAINS MOMENTUM AS A CATEGORY TWO HURRICANE..._x000D__x000D_SUMMARY OF 2300 PM EDT...0300 UTC...INFORMATION_x000D_-----------------------------------------------_x000D_LOCATION...17.1N 80.9W_x000D_ABOUT 184 MILES...296 KM...WEST-SOUTHWEST NEGRIL JAMAICA _x000D_ABOUT 154 MILES...249 KM...SOUTH-SOUTHEAST OF GEORGE TOWN CAYMAN ISLANDS _x000D_MAXIMUM SUSTAINED WINDS...105 MPH...169 KM/HR_x000D_PRESENT MOVEMENT...WNW OR 292 DEGREES AT 15 MPH...24 KM/HR_x000D_MINIMUM CENTRAL PRESSURE...963 MB...28.44 INCHES_x000D__x000D_ | H14: =IF('Excercise - Al '!N14<>"","EXPECTED ACTIONS: "&'Excercise - Al '!N14,"") | I14: ='Excercise - Al '!R14 -> Keane
... A240: ='Excercise - Al '!A240 -> 239 | C240: ='Excercise - Al '!E240 -> 40304.75 | D240: =IF('Excercise - Al '!F240<>0,'Excercise - Al '!F240,"") | E240: =IF('Excercise - Al '!G240<>"","MODE: "&'Excercise - Al '!G240,"")&IF('Excercise - Al '!H240<>""," FROM: "&'Excercise - Al '!H240,"")&IF('Excercise - Al '!I240<>""," INJECTED BY: "&'Excercise - Al '!I240,"")&IF('Excercise - Al '!J240<>""," SEND TO: "&'Excercise - Al '!J240,"") | F240: =IF('Excercise - Al '!K240<>"","STORYLINE: "&'Excercise - Al '!K240,"")&IF('Excercise - Al '!M240<>""," DESCRIPTION: "&'Excercise - Al '!M240,"")&IF('Excercise - Al '!O240<>""," NOTES/REMARKS: "&'Excercise - Al '!O240,"")&IF('Excercise - Al '!Q240<>""," BACKGROUND INFO: "&'Excercise - Al '!Q240,"") -> STORYLINE: Transport food, water, and ice from LSA Brookley Field to LSA's located in Mobile and Baldwin Counties. Commodities to move are 400 Pallets of MRE, 500 Pallets of water, 100 Pallets of Ice, this will be a LOG Push mission daily. Mission duration is TBD. | G240: =IF('Excercise - Al '!P240<>"","IMPLEMENTER: "&'Excercise - Al '!P240,"") -> IMPLEMENTER: Transport food, water, and ice from LSA Brookley Field to LSA's located in Mobile and Baldwin Counties. Commodities to move are 400 Pallets of MRE, 500 Pallets of water, 100 Pallets of Ice, this will be a LOG Push mission daily. Mission duration is TBD. | H240: =IF('Excercise - Al '!N240<>"","EXPECTED ACTIONS: "&'Excercise - Al '!N240,"") | I240: ='Excercise - Al '!R240 -> 0
